Workbook

Sheet pokemon
A1: pokedex_number | B1: pokedex_name | C1: type_1 | D1: type_2 | E1: hp | F1: atk | G1: def | H1: sp_atk | I1: sp_def | J1: spd | K1: classification | L1: biome | M1: climate | N1: _initiative | O1: _health | P1: i_mod | Q1: h_mod | R1: initiative | S1: health | T1: total | U1: move_1 | V1: move_2 | W1: move_3 | X1: move_4 | Y1: evolve_into | Z1: evolve_cost | AA1: internal_name | AB1: description | AC1: move_name | AD1: move_type | AE1: move_attack_strength | AF1: move_effect | AG1: is_starter | AH1: is_legendary | AI1: is_shiny | AJ1: encounter_tier | AK1: trainer | AL1: evo_only | AM1: number_in_deck | AN1: uncapturable | AO1: state
A2: 1 | B2: Bulbasaur | C2: Grass | D2: Poison | E2: 45 | F2: 49 | G2: 49 | H2: 65 | I2: 65 | J2: 45 | K2: Seed Pokémon | L2: Forest | M2: Temperate | N2: 5.54 | O2: 5.22 | P2: -1 | R2: =MROUND(N2,1)+P2 -> 5 | S2: =MROUND(O2,1)+Q2 -> 5 | T2: =SUM(S2,R2) -> 10 | U2: Grass | V2: Poison | W2: Dark | X2: Ground | Y2: Ivysaur | Z2: {=IF(ISBLANK(AK2),_xlfn.LET( _xlpm.nameBeforeSlash, IF(ISNUMBER(SEARCH("/", Y2)), LEFT(Y2, SEARCH("/", Y2)-1), Y2), _xlpm.matchRow, IFERROR(MATCH(_xlpm.nameBeforeSlash, AA:AA, 0), ""), _xlpm.difference, IF(_xlpm.matchRow="", "", ABS((R2 + S2) - (INDEX(R:R, _xlpm.matchRow) + INDEX(S:S, _xlpm.matchRow)))), _xlpm.category, IF(_xlpm.matchRow="", "", INDEX(AJ:AJ, _xlpm.matchRow)), _xlpm.adjustment, IF(_xlpm.matchRow="", "", IF(_xlpm.category="weak", 2, IF(_xlpm.category="moderate", 4, IF(_xlpm.category="strong", 8, IF(_xlpm.category="legendary", _xlpm.difference + 12, IF(_xlpm.category="warp", _xlpm.difference + 12, 0)))))), _xlpm.result, IF(_xlpm.matchRow="", "", IF(_xlpm.category="legendary", _xlpm.adjustment, _xlpm.difference + _xlpm.adjustment)), _xlpm.result ),IF(ISBLANK(Y2),"","Hidden"))} -> 8 | AA2: Bulbasaur | AC2: Vine Whip | AD2: =_xlfn.XLOOKUP(AC2,moves!A:A,moves!B:B) -> grass | AE2: =_xlfn.XLOOKUP(AC2,moves!A:A,moves!D:D) -> 2 | AF2: =_xlfn.XLOOKUP(AC2,moves!A:A,moves!E:E) -> Status symbols deal +1 damage. | AG2: 1 | AH2: 0 | AI2: =IF(ISNUMBER(SEARCH("Shiny ", AA2)), 1, 0) -> 0 | AJ2: starter | AL2: 0 | AM2: {=IF(AL2=1,1, IF(ISTEXT(AK2),1, IF(AO2>1,AM1, IF(AI2=1, IF(SUMPRODUCT((LEN($Y$2:$Y$4096)-LEN(SUBSTITUTE($Y$2:$Y$4096,AA2,"")))/LEN(AA2))>0,2,1), IF( SUMPRODUCT((LEN($Y$2:$Y$4096)-LEN(SUBSTITUTE($Y$2:$Y$4096,AA2,"")))/LEN(AA2)) - SUMPRODUCT((LEN($Y$2:$Y$4096)-LEN(SUBSTITUTE($Y$2:$Y$4096,"Alolan "&AA2,"")))/LEN("Alolan "&AA2)) - SUMPRODUCT((LEN($Y$2:$Y$4096)-LEN(SUBSTITUTE($Y$2:$Y$4096,"Galarian "&AA2,"")))/LEN("Galarian "&AA2)) - SUMPRODUCT((LEN($Y$2:$Y$4096)-LEN(SUBSTITUTE($Y$2:$Y$4096,"Hisuian "&AA2,"")))/LEN("Hisuian "&AA2)) - SUMPRODUCT((LEN($Y$2:$Y$4096)-LEN(SUBSTITUTE($Y$2:$Y$4096,"Paldean "&AA2,"")))/LEN("Paldean "&AA2)) >0,2,1) ))))} -> 1 | AN2: 0 | AO2: 0
A3: 1 | B3: Bulbasaur | C3: Grass | D3: Poison | E3: 45 | F3: 49 | G3: 49 | H3: 65 | I3: 65 | J3: 45 | K3: Seed Pokémon | L3: Forest | M3: Temperate | N3: 5.54 | O3: 5.22 | P3: -1 | R3: =MROUND(N3,1)+P3 -> 5 | S3: =MROUND(O3,1)+Q3 -> 5 | T3: =SUM(S3,R3) -> 10 | U3: Grass | V3: Poison | W3: Dark | X3: Ground | Y3: Ivysaur | Z3: {=IF(ISBLANK(AK3),_xlfn.LET( _xlpm.nameBeforeSlash, IF(ISNUMBER(SEARCH("/", Y3)), LEFT(Y3, SEARCH("/", Y3)-1), Y3), _xlpm.matchRow, IFERROR(MATCH(_xlpm.nameBeforeSlash, AA:AA, 0), ""), _xlpm.difference, IF(_xlpm.matchRow="", "", ABS((R3 + S3) - (INDEX(R:R, _xlpm.matchRow) + INDEX(S:S, _xlpm.matchRow)))), _xlpm.category, IF(_xlpm.matchRow="", "", INDEX(AJ:AJ, _xlpm.matchRow)), _xlpm.adjustment, IF(_xlpm.matchRow="", "", IF(_xlpm.category="weak", 2, IF(_xlpm.category="moderate", 4, IF(_xlpm.category="strong", 8, IF(_xlpm.category="legendary", _xlpm.difference + 12, IF(_xlpm.category="warp", _xlpm.difference + 12, 0)))))), _xlpm.result, IF(_xlpm.matchRow="", "", IF(_xlpm.category="legendary", _xlpm.adjustment, _xlpm.difference + _xlpm.adjustment)), _xlpm.result ),IF(ISBLANK(Y3),"","Hidden"))} -> 8 | AA3: Bulbasaur | AC3: Vine Whip | AD3: =_xlfn.XLOOKUP(AC3,moves!A:A,moves!B:B) -> grass | AE3: =_xlfn.XLOOKUP(AC3,moves!A:A,moves!D:D) -> 2 | AF3: =_xlfn.XLOOKUP(AC3,moves!A:A,moves!E:E) -> Status symbols deal +1 damage. | AG3: 0 | AH3: 0 | AI3: =IF(ISNUMBER(SEARCH("Shiny ", AA3)), 1, 0) -> 0 | AJ3: weak | AL3: 0 | AM3: {=IF(AL3=1,1, IF(ISTEXT(AK3),1, IF(AO3>1,AM2, IF(AI3=1, IF(SUMPRODUCT((LEN($Y$2:$Y$4096)-LEN(SUBSTITUTE($Y$2:$Y$4096,AA3,"")))/LEN(AA3))>0,2,1), IF( SUMPRODUCT((LEN($Y$2:$Y$4096)-LEN(SUBSTITUTE($Y$2:$Y$4096,AA3,"")))/LEN(AA3)) - SUMPRODUCT((LEN($Y$2:$Y$4096)-LEN(SUBSTITUTE($Y$2:$Y$4096,"Alolan "&AA3,"")))/LEN("Alolan "&AA3)) - SUMPRODUCT((LEN($Y$2:$Y$4096)-LEN(SUBSTITUTE($Y$2:$Y$4096,"Galarian "&AA3,"")))/LEN("Galarian "&AA3)) - SUMPRODUCT((LEN($Y$2:$Y$4096)-LEN(SUBSTITUTE($Y$2:$Y$4096,"Hisuian "&AA3,"")))/LEN("Hisuian "&AA3)) - SUMPRODUCT((LEN($Y$2:$Y$4096)-LEN(SUBSTITUTE($Y$2:$Y$4096,"Paldean "&AA3,"")))/LEN("Paldean "&AA3)) >0,2,1) ))))} -> 1 | AN3: 0 | AO3: 0
A4: 1 | B4: Bulbasaur | C4: Grass | D4: Poison | E4: 45 | F4: 49 | G4: 49 | H4: 65 | I4: 65 | J4: 45 | K4: Seed Pokémon | L4: Forest | M4: Temperate | N4: 5.54 | O4: 5.22 | P4: -1 | R4: =MROUND(N4,1)+P4 -> 5 | S4: =MROUND(O4,1)+Q4 -> 5 | T4: =SUM(S4,R4) -> 10 | U4: Grass | V4: Poison | W4: Dark | X4: Ground | Y4: Ivysaur | Z4: {=IF(ISBLANK(AK4),_xlfn.LET( _xlpm.nameBeforeSlash, IF(ISNUMBER(SEARCH("/", Y4)), LEFT(Y4, SEARCH("/", Y4)-1), Y4), _xlpm.matchRow, IFERROR(MATCH(_xlpm.nameBeforeSlash, AA:AA, 0), ""), _xlpm.difference, IF(_xlpm.matchRow="", "", ABS((R4 + S4) - (INDEX(R:R, _xlpm.matchRow) + INDEX(S:S, _xlpm.matchRow)))), _xlpm.category, IF(_xlpm.matchRow="", "", INDEX(AJ:AJ, _xlpm.matchRow)), _xlpm.adjustment, IF(_xlpm.matchRow="", "", IF(_xlpm.category="weak", 2, IF(_xlpm.category="moderate", 4, IF(_xlpm.category="strong", 8, IF(_xlpm.category="legendary", _xlpm.difference + 12, IF(_xlpm.category="warp", _xlpm.difference + 12, 0)))))), _xlpm.result, IF(_xlpm.matchRow="", "", IF(_xlpm.category="legendary", _xlpm.adjustment, _xlpm.difference + _xlpm.adjustment)), _xlpm.result ),IF(ISBLANK(Y4),"","Hidden"))} -> 8 | AA4: Bulbasaur | AC4: Vine Whip | AD4: =_xlfn.XLOOKUP(AC4,moves!A:A,moves!B:B) -> grass | AE4: =_xlfn.XLOOKUP(AC4,moves!A:A,moves!D:D) -> 2 | AF4: =_xlfn.XLOOKUP(AC4,moves!A:A,moves!E:E) -> Status symbols deal +1 damage. | AG4: 0 | AH4: 0 | AI4: =IF(ISNUMBER(SEARCH("Shiny ", AA4)), 1, 0) -> 0 | AJ4: weak | AL4: 0 | AM4: {=IF(AL4=1,1, IF(ISTEXT(AK4),1, IF(AO4>1,AM3, IF(AI4=1, IF(SUMPRODUCT((LEN($Y$2:$Y$4096)-LEN(SUBSTITUTE($Y$2:$Y$4096,AA4,"")))/LEN(AA4))>0,2,1), IF( SUMPRODUCT((LEN($Y$2:$Y$4096)-LEN(SUBSTITUTE($Y$2:$Y$4096,AA4,"")))/LEN(AA4)) - SUMPRODUCT((LEN($Y$2:$Y$4096)-LEN(SUBSTITUTE($Y$2:$Y$4096,"Alolan "&AA4,"")))/LEN("Alolan "&AA4)) - SUMPRODUCT((LEN($Y$2:$Y$4096)-LEN(SUBSTITUTE($Y$2:$Y$4096,"Galarian "&AA4,"")))/LEN("Galarian "&AA4)) - SUMPRODUCT((LEN($Y$2:$Y$4096)-LEN(SUBSTITUTE($Y$2:$Y$4096,"Hisuian "&AA4,"")))/LEN("Hisuian "&AA4)) - SUMPRODUCT((LEN($Y$2:$Y$4096)-LEN(SUBSTITUTE($Y$2:$Y$4096,"Paldean "&AA4,"")))/LEN("Paldean "&AA4)) >0,2,1) ))))} -> 1 | AN4: 0 | AO4: 0
A5: 1 | B5: Bulbasaur | C5: Grass | D5: Poison | E5: 45 | F5: 49 | G5: 49 | H5: 65 | I5: 65 | J5: 45 | K5: Seed Pokémon | L5: Forest | M5: Temperate | N5: 5.54 | O5: 5.22 | P5: -1 | R5: =MROUND(N5,1)+P5 -> 5 | S5: =MROUND(O5,1)+Q5 -> 5 | T5: =SUM(S5,R5) -> 10 | U5: Grass | V5: Poison | W5: Dark | X5: Ground | Y5: Ivysaur | Z5: {=IF(ISBLANK(AK5),_xlfn.LET( _xlpm.nameBeforeSlash, IF(ISNUMBER(SEARCH("/", Y5)), LEFT(Y5, SEARCH("/", Y5)-1), Y5), _xlpm.matchRow, IFERROR(MATCH(_xlpm.nameBeforeSlash, AA:AA, 0), ""), _xlpm.difference, IF(_xlpm.matchRow="", "", ABS((R5 + S5) - (INDEX(R:R, _xlpm.matchRow) + INDEX(S:S, _xlpm.matchRow)))), _xlpm.category, IF(_xlpm.matchRow="", "", INDEX(AJ:AJ, _xlpm.matchRow)), _xlpm.adjustment, IF(_xlpm.matchRow="", "", IF(_xlpm.category="weak", 2, IF(_xlpm.category="moderate", 4, IF(_xlpm.category="strong", 8, IF(_xlpm.category="legendary", _xlpm.difference + 12, IF(_xlpm.category="warp", _xlpm.difference + 12, 0)))))), _xlpm.result, IF(_xlpm.matchRow="", "", IF(_xlpm.category="legendary", _xlpm.adjustment, _xlpm.difference + _xlpm.adjustment)), _xlpm.result ),IF(ISBLANK(Y5),"","Hidden"))} -> 8 | AA5: Bulbasaur | AC5: Vine Whip | AD5: =_xlfn.XLOOKUP(AC5,moves!A:A,moves!B:B) -> grass | AE5: =_xlfn.XLOOKUP(AC5,moves!A:A,moves!D:D) -> 2 | AF5: =_xlfn.XLOOKUP(AC5,moves!A:A,moves!E:E) -> Status symbols deal +1 damage. | AG5: 0 | AH5: 0 | AI5: =IF(ISNUMBER(SEARCH("Shiny ", AA5)), 1, 0) -> 0 | AJ5: weak | AL5: 0 | AM5: {=IF(AL5=1,1, IF(ISTEXT(AK5),1, IF(AO5>1,AM4, IF(AI5=1, IF(SUMPRODUCT((LEN($Y$2:$Y$4096)-LEN(SUBSTITUTE($Y$2:$Y$4096,AA5,"")))/LEN(AA5))>0,2,1), IF( SUMPRODUCT((LEN($Y$2:$Y$4096)-LEN(SUBSTITUTE($Y$2:$Y$4096,AA5,"")))/LEN(AA5)) - SUMPRODUCT((LEN($Y$2:$Y$4096)-LEN(SUBSTITUTE($Y$2:$Y$4096,"Alolan "&AA5,"")))/LEN("Alolan "&AA5)) - SUMPRODUCT((LEN($Y$2:$Y$4096)-LEN(SUBSTITUTE($Y$2:$Y$4096,"Galarian "&AA5,"")))/LEN("Galarian "&AA5)) - SUMPRODUCT((LEN($Y$2:$Y$4096)-LEN(SUBSTITUTE($Y$2:$Y$4096,"Hisuian "&AA5,"")))/LEN("Hisuian "&AA5)) - SUMPRODUCT((LEN($Y$2:$Y$4096)-LEN(SUBSTITUTE($Y$2:$Y$4096,"Paldean "&AA5,"")))/LEN("Paldean "&AA5)) >0,2,1) ))))} -> 1 | AN5: 0 | AO5: 0
A6: 1 | B6: Bulbasaur | C6: Grass | D6: Poison | E6: 45 | F6: 49 | G6: 49 | H6: 65 | I6: 65 | J6: 45 | K6: Seed Pokémon | L6: Forest | M6: Temperate | N6: 5.54 | O6: 5.22 | P6: -1 | R6: =MROUND(N6,1)+P6 -> 5 | S6: =MROUND(O6,1)+Q6 -> 5 | T6: =SUM(S6,R6) -> 10 | U6: Grass | V6: Poison | W6: Dark | X6: Ground | Y6: Ivysaur | Z6: {=IF(ISBLANK(AK6),_xlfn.LET( _xlpm.nameBeforeSlash, IF(ISNUMBER(SEARCH("/", Y6)), LEFT(Y6, SEARCH("/", Y6)-1), Y6), _xlpm.matchRow, IFERROR(MATCH(_xlpm.nameBeforeSlash, AA:AA, 0), ""), _xlpm.difference, IF(_xlpm.matchRow="", "", ABS((R6 + S6) - (INDEX(R:R, _xlpm.matchRow) + INDEX(S:S, _xlpm.matchRow)))), _xlpm.category, IF(_xlpm.matchRow="", "", INDEX(AJ:AJ, _xlpm.matchRow)), _xlpm.adjustment, IF(_xlpm.matchRow="", "", IF(_xlpm.category="weak", 2, IF(_xlpm.category="moderate", 4, IF(_xlpm.category="strong", 8, IF(_xlpm.category="legendary", _xlpm.difference + 12, IF(_xlpm.category="warp", _xlpm.difference + 12, 0)))))), _xlpm.result, IF(_xlpm.matchRow="", "", IF(_xlpm.category="legendary", _xlpm.adjustment, _xlpm.difference + _xlpm.adjustment)), _xlpm.result ),IF(ISBLANK(Y6),"","Hidden"))} -> 8 | AA6: Bulbasaur | AC6: Vine Whip | AD6: =_xlfn.XLOOKUP(AC6,moves!A:A,moves!B:B) -> grass | AE6: =_xlfn.XLOOKUP(AC6,moves!A:A,moves!D:D) -> 2 | AF6: =_xlfn.XLOOKUP(AC6,moves!A:A,moves!E:E) -> Status symbols deal +1 damage. | AG6: 0 | AH6: 0 | AI6: =IF(ISNUMBER(SEARCH("Shiny ", AA6)), 1, 0) -> 0 | AJ6: weak | AL6: 0 | AM6: {=IF(AL6=1,1, IF(ISTEXT(AK6),1, IF(AO6>1,AM5, IF(AI6=1, IF(SUMPRODUCT((LEN($Y$2:$Y$4096)-LEN(SUBSTITUTE($Y$2:$Y$4096,AA6,"")))/LEN(AA6))>0,2,1), IF( SUMPRODUCT((LEN($Y$2:$Y$4096)-LEN(SUBSTITUTE($Y$2:$Y$4096,AA6,"")))/LEN(AA6)) - SUMPRODUCT((LEN($Y$2:$Y$4096)-LEN(SUBSTITUTE($Y$2:$Y$4096,"Alolan "&AA6,"")))/LEN("Alolan "&AA6)) - SUMPRODUCT((LEN($Y$2:$Y$4096)-LEN(SUBSTITUTE($Y$2:$Y$4096,"Galarian "&AA6,"")))/LEN("Galarian "&AA6)) - SUMPRODUCT((LEN($Y$2:$Y$4096)-LEN(SUBSTITUTE($Y$2:$Y$4096,"Hisuian "&AA6,"")))/LEN("Hisuian "&AA6)) - SUMPRODUCT((LEN($Y$2:$Y$4096)-LEN(SUBSTITUTE($Y$2:$Y$4096,"Paldean "&AA6,"")))/LEN("Paldean "&AA6)) >0,2,1) ))))} -> 1 | AN6: 0 | AO6: 0
A7: 1 | B7: Bulbasaur | C7: Grass | D7: Poison | E7: 45 | F7: 49 | G7: 49 | H7: 65 | I7: 65 | J7: 45 | K7: Seed Pokémon | L7: Forest | M7: Temperate | N7: 5.54 | O7: 5.22 | P7: -1 | R7: =MROUND(N7,1)+P7 -> 5 | S7: =MROUND(O7,1)+Q7 -> 5 | T7: =SUM(S7,R7) -> 10 | U7: Grass | V7: Poison | W7: Dark | X7: Ground | Y7: Ivysaur | Z7: {=IF(ISBLANK(AK7),_xlfn.LET( _xlpm.nameBeforeSlash, IF(ISNUMBER(SEARCH("/", Y7)), LEFT(Y7, SEARCH("/", Y7)-1), Y7), _xlpm.matchRow, IFERROR(MATCH(_xlpm.nameBeforeSlash, AA:AA, 0), ""), _xlpm.difference, IF(_xlpm.matchRow="", "", ABS((R7 + S7) - (INDEX(R:R, _xlpm.matchRow) + INDEX(S:S, _xlpm.matchRow)))), _xlpm.category, IF(_xlpm.matchRow="", "", INDEX(AJ:AJ, _xlpm.matchRow)), _xlpm.adjustment, IF(_xlpm.matchRow="", "", IF(_xlpm.category="weak", 2, IF(_xlpm.category="moderate", 4, IF(_xlpm.category="strong", 8, IF(_xlpm.category="legendary", _xlpm.difference + 12, IF(_xlpm.category="warp", _xlpm.difference + 12, 0)))))), _xlpm.result, IF(_xlpm.matchRow="", "", IF(_xlpm.category="legendary", _xlpm.adjustment, _xlpm.difference + _xlpm.adjustment)), _xlpm.result ),IF(ISBLANK(Y7),"","Hidden"))} -> 8 | AA7: Bulbasaur | AC7: Vine Whip | AD7: =_xlfn.XLOOKUP(AC7,moves!A:A,moves!B:B) -> grass | AE7: =_xlfn.XLOOKUP(AC7,moves!A:A,moves!D:D) -> 2 | AF7: =_xlfn.XLOOKUP(AC7,moves!A:A,moves!E:E) -> Status symbols deal +1 damage. | AG7: 0 | AH7: 0 | AI7: =IF(ISNUMBER(SEARCH("Shiny ", AA7)), 1, 0) -> 0 | AJ7: weak | AL7: 0 | AM7: {=IF(AL7=1,1, IF(ISTEXT(AK7),1, IF(AO7>1,AM6, IF(AI7=1, IF(SUMPRODUCT((LEN($Y$2:$Y$4096)-LEN(SUBSTITUTE($Y$2:$Y$4096,AA7,"")))/LEN(AA7))>0,2,1), IF( SUMPRODUCT((LEN($Y$2:$Y$4096)-LEN(SUBSTITUTE($Y$2:$Y$4096,AA7,"")))/LEN(AA7)) - SUMPRODUCT((LEN($Y$2:$Y$4096)-LEN(SUBSTITUTE($Y$2:$Y$4096,"Alolan "&AA7,"")))/LEN("Alolan "&AA7)) - SUMPRODUCT((LEN($Y$2:$Y$4096)-LEN(SUBSTITUTE($Y$2:$Y$4096,"Galarian "&AA7,"")))/LEN("Galarian "&AA7)) - SUMPRODUCT((LEN($Y$2:$Y$4096)-LEN(SUBSTITUTE($Y$2:$Y$4096,"Hisuian "&AA7,"")))/LEN("Hisuian "&AA7)) - SUMPRODUCT((LEN($Y$2:$Y$4096)-LEN(SUBSTITUTE($Y$2:$Y$4096,"Paldean "&AA7,"")))/LEN("Paldean "&AA7)) >0,2,1) ))))} -> 1 | AN7: 0 | AO7: 0
A8: 1 | B8: Bulbasaur | C8: Grass | D8: Poison | E8: 45 | F8: 49 | G8: 49 | H8: 65 | I8: 65 | J8: 45 | K8: Seed Pokémon | L8: Forest | M8: Temperate | N8: 5.54 | O8: 5.22 | P8: -1 | R8: =MROUND(N8,1)+P8 -> 5 | S8: =MROUND(O8,1)+Q8 -> 5 | T8: =SUM(S8,R8) -> 10 | U8: Grass | V8: Poison | W8: Dark | X8: Ground | Y8: Ivysaur | Z8: {=IF(ISBLANK(AK8),_xlfn.LET( _xlpm.nameBeforeSlash, IF(ISNUMBER(SEARCH("/", Y8)), LEFT(Y8, SEARCH("/", Y8)-1), Y8), _xlpm.matchRow, IFERROR(MATCH(_xlpm.nameBeforeSlash, AA:AA, 0), ""), _xlpm.difference, IF(_xlpm.matchRow="", "", ABS((R8 + S8) - (INDEX(R:R, _xlpm.matchRow) + INDEX(S:S, _xlpm.matchRow)))), _xlpm.category, IF(_xlpm.matchRow="", "", INDEX(AJ:AJ, _xlpm.matchRow)), _xlpm.adjustment, IF(_xlpm.matchRow="", "", IF(_xlpm.category="weak", 2, IF(_xlpm.category="moderate", 4, IF(_xlpm.category="strong", 8, IF(_xlpm.category="legendary", _xlpm.difference + 12, IF(_xlpm.category="warp", _xlpm.difference + 12, 0)))))), _xlpm.result, IF(_xlpm.matchRow="", "", IF(_xlpm.category="legendary", _xlpm.adjustment, _xlpm.difference + _xlpm.adjustment)), _xlpm.result ),IF(ISBLANK(Y8),"","Hidden"))} -> 8 | AA8: Bulbasaur | AC8: Vine Whip | AD8: =_xlfn.XLOOKUP(AC8,moves!A:A,moves!B:B) -> grass | AE8: =_xlfn.XLOOKUP(AC8,moves!A:A,moves!D:D) -> 2 | AF8: =_xlfn.XLOOKUP(AC8,moves!A:A,moves!E:E) -> Status symbols deal +1 damage. | AG8: 0 | AH8: 0 | AI8: =IF(ISNUMBER(SEARCH("Shiny ", AA8)), 1, 0) -> 0 | AJ8: weak | AL8: 0 | AM8: {=IF(AL8=1,1, IF(ISTEXT(AK8),1, IF(AO8>1,AM7, IF(AI8=1, IF(SUMPRODUCT((LEN($Y$2:$Y$4096)-LEN(SUBSTITUTE($Y$2:$Y$4096,AA8,"")))/LEN(AA8))>0,2,1), IF( SUMPRODUCT((LEN($Y$2:$Y$4096)-LEN(SUBSTITUTE($Y$2:$Y$4096,AA8,"")))/LEN(AA8)) - SUMPRODUCT((LEN($Y$2:$Y$4096)-LEN(SUBSTITUTE($Y$2:$Y$4096,"Alolan "&AA8,"")))/LEN("Alolan "&AA8)) - SUMPRODUCT((LEN($Y$2:$Y$4096)-LEN(SUBSTITUTE($Y$2:$Y$4096,"Galarian "&AA8,"")))/LEN("Galarian "&AA8)) - SUMPRODUCT((LEN($Y$2:$Y$4096)-LEN(SUBSTITUTE($Y$2:$Y$4096,"Hisuian "&AA8,"")))/LEN("Hisuian "&AA8)) - SUMPRODUCT((LEN($Y$2:$Y$4096)-LEN(SUBSTITUTE($Y$2:$Y$4096,"Paldean "&AA8,"")))/LEN("Paldean "&AA8)) >0,2,1) ))))} -> 1 | AN8: 0 | AO8: 0
A9: 1 | B9: Bulbasaur | C9: Grass | D9: Poison | E9: 45 | F9: 49 | G9: 49 | H9: 65 | I9: 65 | J9: 45 | K9: Seed Pokémon | L9: Forest | M9: Temperate | N9: 5.54 | O9: 5.22 | P9: -1 | R9: =MROUND(N9,1)+P9 -> 5 | S9: =MROUND(O9,1)+Q9 -> 5 | T9: =SUM(S9,R9) -> 10 | U9: Grass | V9: Poison | W9: Dark | X9: Ground | Y9: Ivysaur | Z9: {=IF(ISBLANK(AK9),_xlfn.LET( _xlpm.nameBeforeSlash, IF(ISNUMBER(SEARCH("/", Y9)), LEFT(Y9, SEARCH("/", Y9)-1), Y9), _xlpm.matchRow, IFERROR(MATCH(_xlpm.nameBeforeSlash, AA:AA, 0), ""), _xlpm.difference, IF(_xlpm.matchRow="", "", ABS((R9 + S9) - (INDEX(R:R, _xlpm.matchRow) + INDEX(S:S, _xlpm.matchRow)))), _xlpm.category, IF(_xlpm.matchRow="", "", INDEX(AJ:AJ, _xlpm.matchRow)), _xlpm.adjustment, IF(_xlpm.matchRow="", "", IF(_xlpm.category="weak", 2, IF(_xlpm.category="moderate", 4, IF(_xlpm.category="strong", 8, IF(_xlpm.category="legendary", _xlpm.difference + 12, IF(_xlpm.category="warp", _xlpm.difference + 12, 0)))))), _xlpm.result, IF(_xlpm.matchRow="", "", IF(_xlpm.category="legendary", _xlpm.adjustment, _xlpm.difference + _xlpm.adjustment)), _xlpm.result ),IF(ISBLANK(Y9),"","Hidden"))} -> 8 | AA9: Bulbasaur | AC9: Vine Whip | AD9: =_xlfn.XLOOKUP(AC9,moves!A:A,moves!B:B) -> grass | AE9: =_xlfn.XLOOKUP(AC9,moves!A:A,moves!D:D) -> 2 | AF9: =_xlfn.XLOOKUP(AC9,moves!A:A,moves!E:E) -> Status symbols deal +1 damage. | AG9: 0 | AH9: 0 | AI9: =IF(ISNUMBER(SEARCH("Shiny ", AA9)), 1, 0) -> 0 | AJ9: weak | AL9: 0 | AM9: {=IF(AL9=1,1, IF(ISTEXT(AK9),1, IF(AO9>1,AM8, IF(AI9=1, IF(SUMPRODUCT((LEN($Y$2:$Y$4096)-LEN(SUBSTITUTE($Y$2:$Y$4096,AA9,"")))/LEN(AA9))>0,2,1), IF( SUMPRODUCT((LEN($Y$2:$Y$4096)-LEN(SUBSTITUTE($Y$2:$Y$4096,AA9,"")))/LEN(AA9)) - SUMPRODUCT((LEN($Y$2:$Y$4096)-LEN(SUBSTITUTE($Y$2:$Y$4096,"Alolan "&AA9,"")))/LEN("Alolan "&AA9)) - SUMPRODUCT((LEN($Y$2:$Y$4096)-LEN(SUBSTITUTE($Y$2:$Y$4096,"Galarian "&AA9,"")))/LEN("Galarian "&AA9)) - SUMPRODUCT((LEN($Y$2:$Y$4096)-LEN(SUBSTITUTE($Y$2:$Y$4096,"Hisuian "&AA9,"")))/LEN("Hisuian "&AA9)) - SUMPRODUCT((LEN($Y$2:$Y$4096)-LEN(SUBSTITUTE($Y$2:$Y$4096,"Paldean "&AA9,"")))/LEN("Paldean "&AA9)) >0,2,1) ))))} -> 1 | AN9: 0 | AO9: 0
A10: 1 | B10: Bulbasaur | C10: Grass | D10: Poison | E10: 45 | F10: 49 | G10: 49 | H10: 65 | I10: 65 | J10: 45 | K10: Seed Pokémon | L10: Forest | M10: Temperate | N10: 5.54 | O10: 5.22 | P10: -1 | R10: =MROUND(N10,1)+P10 -> 5 | S10: =MROUND(O10,1)+Q10 -> 5 | T10: =SUM(S10,R10) -> 10 | U10: Grass | V10: Poison | W10: Dark | X10: Ground | Y10: Ivysaur | Z10: {=IF(ISBLANK(AK10),_xlfn.LET( _xlpm.nameBeforeSlash, IF(ISNUMBER(SEARCH("/", Y10)), LEFT(Y10, SEARCH("/", Y10)-1), Y10), _xlpm.matchRow, IFERROR(MATCH(_xlpm.nameBeforeSlash, AA:AA, 0), ""), _xlpm.difference, IF(_xlpm.matchRow="", "", ABS((R10 + S10) - (INDEX(R:R, _xlpm.matchRow) + INDEX(S:S, _xlpm.matchRow)))), _xlpm.category, IF(_xlpm.matchRow="", "", INDEX(AJ:AJ, _xlpm.matchRow)), _xlpm.adjustment, IF(_xlpm.matchRow="", "", IF(_xlpm.category="weak", 2, IF(_xlpm.category="moderate", 4, IF(_xlpm.category="strong", 8, IF(_xlpm.category="legendary", _xlpm.difference + 12, IF(_xlpm.category="warp", _xlpm.difference + 12, 0)))))), _xlpm.result, IF(_xlpm.matchRow="", "", IF(_xlpm.category="legendary", _xlpm.adjustment, _xlpm.difference + _xlpm.adjustment)), _xlpm.result ),IF(ISBLANK(Y10),"","Hidden"))} -> 8 | AA10: Bulbasaur | AC10: Vine Whip | AD10: =_xlfn.XLOOKUP(AC10,moves!A:A,moves!B:B) -> grass | AE10: =_xlfn.XLOOKUP(AC10,moves!A:A,moves!D:D) -> 2 | AF10: =_xlfn.XLOOKUP(AC10,moves!A:A,moves!E:E) -> Status symbols deal +1 damage. | AG10: 0 | AH10: 0 | AI10: =IF(ISNUMBER(SEARCH("Shiny ", AA10)), 1, 0) -> 0 | AJ10: weak | AL10: 0 | AM10: {=IF(AL10=1,1, IF(ISTEXT(AK10),1, IF(AO10>1,AM9, IF(AI10=1, IF(SUMPRODUCT((LEN($Y$2:$Y$4096)-LEN(SUBSTITUTE($Y$2:$Y$4096,AA10,"")))/LEN(AA10))>0,2,1), IF( SUMPRODUCT((LEN($Y$2:$Y$4096)-LEN(SUBSTITUTE($Y$2:$Y$4096,AA10,"")))/LEN(AA10)) - SUMPRODUCT((LEN($Y$2:$Y$4096)-LEN(SUBSTITUTE($Y$2:$Y$4096,"Alolan "&AA10,"")))/LEN("Alolan "&AA10)) - SUMPRODUCT((LEN($Y$2:$Y$4096)-LEN(SUBSTITUTE($Y$2:$Y$4096,"Galarian "&AA10,"")))/LEN("Galarian "&AA10)) - SUMPRODUCT((LEN($Y$2:$Y$4096)-LEN(SUBSTITUTE($Y$2:$Y$4096,"Hisuian "&AA10,"")))/LEN("Hisuian "&AA10)) - SUMPRODUCT((LEN($Y$2:$Y$4096)-LEN(SUBSTITUTE($Y$2:$Y$4096,"Paldean "&AA10,"")))/LEN("Paldean "&AA10)) >0,2,1) ))))} -> 1 | AN10: 0 | AO10: 0
A11: 1 | B11: Bulbasaur | C11: Grass | D11: Poison | E11: 45 | F11: 49 | G11: 49 | H11: 65 | I11: 65 | J11: 45 | K11: Seed Pokémon | L11: Forest | M11: Temperate | N11: 5.54 | O11: 5.22 | P11: -1 | R11: =MROUND(N11,1)+P11 -> 5 | S11: =MROUND(O11,1)+Q11 -> 5 | T11: =SUM(S11,R11) -> 10 | U11: Grass | V11: Poison | W11: Dark | X11: Ground | Y11: Ivysaur | Z11: {=IF(ISBLANK(AK11),_xlfn.LET( _xlpm.nameBeforeSlash, IF(ISNUMBER(SEARCH("/", Y11)), LEFT(Y11, SEARCH("/", Y11)-1), Y11), _xlpm.matchRow, IFERROR(MATCH(_xlpm.nameBeforeSlash, AA:AA, 0), ""), _xlpm.difference, IF(_xlpm.matchRow="", "", ABS((R11 + S11) - (INDEX(R:R, _xlpm.matchRow) + INDEX(S:S, _xlpm.matchRow)))), _xlpm.category, IF(_xlpm.matchRow="", "", INDEX(AJ:AJ, _xlpm.matchRow)), _xlpm.adjustment, IF(_xlpm.matchRow="", "", IF(_xlpm.category="weak", 2, IF(_xlpm.category="moderate", 4, IF(_xlpm.category="strong", 8, IF(_xlpm.category="legendary", _xlpm.difference + 12, IF(_xlpm.category="warp", _xlpm.difference + 12, 0)))))), _xlpm.result, IF(_xlpm.matchRow="", "", IF(_xlpm.category="legendary", _xlpm.adjustment, _xlpm.difference + _xlpm.adjustment)), _xlpm.result ),IF(ISBLANK(Y11),"","Hidden"))} -> 8 | AA11: Bulbasaur | AC11: Vine Whip | AD11: =_xlfn.XLOOKUP(AC11,moves!A:A,moves!B:B) -> grass | AE11: =_xlfn.XLOOKUP(AC11,moves!A:A,moves!D:D) -> 2 | AF11: =_xlfn.XLOOKUP(AC11,moves!A:A,moves!E:E) -> Status symbols deal +1 damage. | AG11: 0 | AH11: 0 | AI11: =IF(ISNUMBER(SEARCH("Shiny ", AA11)), 1, 0) -> 0 | AJ11: weak | AL11: 0 | AM11: {=IF(AL11=1,1, IF(ISTEXT(AK11),1, IF(AO11>1,AM10, IF(AI11=1, IF(SUMPRODUCT((LEN($Y$2:$Y$4096)-LEN(SUBSTITUTE($Y$2:$Y$4096,AA11,"")))/LEN(AA11))>0,2,1), IF( SUMPRODUCT((LEN($Y$2:$Y$4096)-LEN(SUBSTITUTE($Y$2:$Y$4096,AA11,"")))/LEN(AA11)) - SUMPRODUCT((LEN($Y$2:$Y$4096)-LEN(SUBSTITUTE($Y$2:$Y$4096,"Alolan "&AA11,"")))/LEN("Alolan "&AA11)) - SUMPRODUCT((LEN($Y$2:$Y$4096)-LEN(SUBSTITUTE($Y$2:$Y$4096,"Galarian "&AA11,"")))/LEN("Galarian "&AA11)) - SUMPRODUCT((LEN($Y$2:$Y$4096)-LEN(SUBSTITUTE($Y$2:$Y$4096,"Hisuian "&AA11,"")))/LEN("Hisuian "&AA11)) - SUMPRODUCT((LEN($Y$2:$Y$4096)-LEN(SUBSTITUTE($Y$2:$Y$4096,"Paldean "&AA11,"")))/LEN("Paldean "&AA11)) >0,2,1) ))))} -> 1 | AN11: 0 | AO11: 0
A12: 1 | B12: Bulbasaur | C12: Grass | D12: Poison | E12: 45 | F12: 49 | G12: 49 | H12: 65 | I12: 65 | J12: 45 | K12: Seed Pokémon | L12: Forest | M12: Temperate | N12: 5.54 | O12: 5.22 | P12: -1 | R12: =MROUND(N12,1)+P12 -> 5 | S12: =MROUND(O12,1)+Q12 -> 5 | T12: =SUM(S12,R12) -> 10 | U12: Grass | V12: Poison | W12: Dark | X12: Ground | Y12: Ivysaur | Z12: {=IF(ISBLANK(AK12),_xlfn.LET( _xlpm.nameBeforeSlash, IF(ISNUMBER(SEARCH("/", Y12)), LEFT(Y12, SEARCH("/", Y12)-1), Y12), _xlpm.matchRow, IFERROR(MATCH(_xlpm.nameBeforeSlash, AA:AA, 0), ""), _xlpm.difference, IF(_xlpm.matchRow="", "", ABS((R12 + S12) - (INDEX(R:R, _xlpm.matchRow) + INDEX(S:S, _xlpm.matchRow)))), _xlpm.category, IF(_xlpm.matchRow="", "", INDEX(AJ:AJ, _xlpm.matchRow)), _xlpm.adjustment, IF(_xlpm.matchRow="", "", IF(_xlpm.category="weak", 2, IF(_xlpm.category="moderate", 4, IF(_xlpm.category="strong", 8, IF(_xlpm.category="legendary", _xlpm.difference + 12, IF(_xlpm.category="warp", _xlpm.difference + 12, 0)))))), _xlpm.result, IF(_xlpm.matchRow="", "", IF(_xlpm.category="legendary", _xlpm.adjustment, _xlpm.difference + _xlpm.adjustment)), _xlpm.result ),IF(ISBLANK(Y12),"","Hidden"))} -> 8 | AA12: Bulbasaur | AC12: Vine Whip | AD12: =_xlfn.XLOOKUP(AC12,moves!A:A,moves!B:B) -> grass | AE12: =_xlfn.XLOOKUP(AC12,moves!A:A,moves!D:D) -> 2 | AF12: =_xlfn.XLOOKUP(AC12,moves!A:A,moves!E:E) -> Status symbols deal +1 damage. | AG12: 0 | AH12: 0 | AI12: =IF(ISNUMBER(SEARCH("Shiny ", AA12)), 1, 0) -> 0 | AJ12: weak | AL12: 0 | AM12: {=IF(AL12=1,1, IF(ISTEXT(AK12),1, IF(AO12>1,AM11, IF(AI12=1, IF(SUMPRODUCT((LEN($Y$2:$Y$4096)-LEN(SUBSTITUTE($Y$2:$Y$4096,AA12,"")))/LEN(AA12))>0,2,1), IF( SUMPRODUCT((LEN($Y$2:$Y$4096)-LEN(SUBSTITUTE($Y$2:$Y$4096,AA12,"")))/LEN(AA12)) - SUMPRODUCT((LEN($Y$2:$Y$4096)-LEN(SUBSTITUTE($Y$2:$Y$4096,"Alolan "&AA12,"")))/LEN("Alolan "&AA12)) - SUMPRODUCT((LEN($Y$2:$Y$4096)-LEN(SUBSTITUTE($Y$2:$Y$4096,"Galarian "&AA12,"")))/LEN("Galarian "&AA12)) - SUMPRODUCT((LEN($Y$2:$Y$4096)-LEN(SUBSTITUTE($Y$2:$Y$4096,"Hisuian "&AA12,"")))/LEN("Hisuian "&AA12)) - SUMPRODUCT((LEN($Y$2:$Y$4096)-LEN(SUBSTITUTE($Y$2:$Y$4096,"Paldean "&AA12,"")))/LEN("Paldean "&AA12)) >0,2,1) ))))} -> 1 | AN12: 0 | AO12: 0
A13: 1-shiny | B13: Bulbasaur | C13: Grass | D13: Poison | E13: 45 | F13: 49 | G13: 49 | H13: 65 | I13: 65 | J13: 45 | K13: Seed Pokémon | L13: Forest | M13: Temperate | N13: 5.54 | O13: 5.22 | P13: -1 | R13: =MROUND(N13,1)+P13 -> 5 | S13: =MROUND(O13,1)+Q13 -> 5 | T13: =SUM(S13,R13) -> 10 | U13: Grass | V13: Poison | W13: Dark | X13: Ground | Y13: Shiny Ivysaur | Z13: {=IF(ISBLANK(AK13),_xlfn.LET( _xlpm.nameBeforeSlash, IF(ISNUMBER(SEARCH("/", Y13)), LEFT(Y13, SEARCH("/", Y13)-1), Y13), _xlpm.matchRow, IFERROR(MATCH(_xlpm.nameBeforeSlash, AA:AA, 0), ""), _xlpm.difference, IF(_xlpm.matchRow="", "", ABS((R13 + S13) - (INDEX(R:R, _xlpm.matchRow) + INDEX(S:S, _xlpm.matchRow)))), _xlpm.category, IF(_xlpm.matchRow="", "", INDEX(AJ:AJ, _xlpm.matchRow)), _xlpm.adjustment, IF(_xlpm.matchRow="", "", IF(_xlpm.category="weak", 2, IF(_xlpm.category="moderate", 4, IF(_xlpm.category="strong", 8, IF(_xlpm.category="legendary", _xlpm.difference + 12, IF(_xlpm.category="warp", _xlpm.difference + 12, 0)))))), _xlpm.result, IF(_xlpm.matchRow="", "", IF(_xlpm.category="legendary", _xlpm.adjustment, _xlpm.difference + _xlpm.adjustment)), _xlpm.result ),IF(ISBLANK(Y13),"","Hidden"))} -> 8 | AA13: Shiny Bulbasaur | AC13: Leech Seed | AD13: =_xlfn.XLOOKUP(AC13,moves!A:A,moves!B:B) -> grass | AE13: =_xlfn.XLOOKUP(AC13,moves!A:A,moves!D:D) -> 1 | AF13: =_xlfn.XLOOKUP(AC13,moves!A:A,moves!E:E) -> At the end of the target's turns: The target takes 1 damage and the user Heals 1. | AG13: 1 | AH13: 0 | AI13: =IF(ISNUMBER(SEARCH("Shiny ", AA13)), 1, 0) -> 1 | AJ13: weak | AL13: 0 | AM13: {=IF(AL13=1,1, IF(ISTEXT(AK13),1, IF(AO13>1,AM12, IF(AI13=1, IF(SUMPRODUCT((LEN($Y$2:$Y$4096)-LEN(SUBSTITUTE($Y$2:$Y$4096,AA13,"")))/LEN(AA13))>0,2,1), IF( SUMPRODUCT((LEN($Y$2:$Y$4096)-LEN(SUBSTITUTE($Y$2:$Y$4096,AA13,"")))/LEN(AA13)) - SUMPRODUCT((LEN($Y$2:$Y$4096)-LEN(SUBSTITUTE($Y$2:$Y$4096,"Alolan "&AA13,"")))/LEN("Alolan "&AA13)) - SUMPRODUCT((LEN($Y$2:$Y$4096)-LEN(SUBSTITUTE($Y$2:$Y$4096,"Galarian "&AA13,"")))/LEN("Galarian "&AA13)) - SUMPRODUCT((LEN($Y$2:$Y$4096)-LEN(SUBSTITUTE($Y$2:$Y$4096,"Hisuian "&AA13,"")))/LEN("Hisuian "&AA13)) - SUMPRODUCT((LEN($Y$2:$Y$4096)-LEN(SUBSTITUTE($Y$2:$Y$4096,"Paldean "&AA13,"")))/LEN("Paldean "&AA13)) >0,2,1) ))))} -> 1 | AN13: 0 | AO13: 0
A14: 2 | B14: Ivysaur | C14: Grass | D14: Poison | E14: 60 | F14: 62 | G14: 63 | H14: 80 | I14: 80 | J14: 60 | K14: Seed Pokémon | L14: Forest | M14: Temperate | N14: 7.02 | O14: 6.69 | R14: =MROUND(N14,1)+P14 -> 7 | S14: =MROUND(O14,1)+Q14 -> 7 | T14: =SUM(S14,R14) -> 14 | U14: Grass | V14: Poison | W14: Dark | X14: Ground | Y14: Venusaur | Z14: {=IF(ISBLANK(AK14),_xlfn.LET( _xlpm.nameBeforeSlash, IF(ISNUMBER(SEARCH("/", Y14)), LEFT(Y14, SEARCH("/", Y14)-1), Y14), _xlpm.matchRow, IFERROR(MATCH(_xlpm.nameBeforeSlash, AA:AA, 0), ""), _xlpm.difference, IF(_xlpm.matchRow="", "", ABS((R14 + S14) - (INDEX(R:R, _xlpm.matchRow) + INDEX(S:S, _xlpm.matchRow)))), _xlpm.category, IF(_xlpm.matchRow="", "", INDEX(AJ:AJ, _xlpm.matchRow)), _xlpm.adjustment, IF(_xlpm.matchRow="", "", IF(_xlpm.category="weak", 2, IF(_xlpm.category="moderate", 4, IF(_xlpm.category="strong", 8, IF(_xlpm.category="legendary", _xlpm.difference + 12, IF(_xlpm.category="warp", _xlpm.difference + 12, 0)))))), _xlpm.result, IF(_xlpm.matchRow="", "", IF(_xlpm.category="legendary", _xlpm.adjustment, _xlpm.difference + _xlpm.adjustment)), _xlpm.result ),IF(ISBLANK(Y14),"","Hidden"))} -> 14 | AA14: Ivysaur | AC14: Mud Bomb | AD14: =_xlfn.XLOOKUP(AC14,moves!A:A,moves!B:B) -> ground | AE14: =_xlfn.XLOOKUP(AC14,moves!A:A,moves!D:D) -> 3 | AF14: =_xlfn.XLOOKUP(AC14,moves!A:A,moves!E:E) -> When the target next attacks: Status symbols deal -1 damage. | AG14: 0 | AH14: 0 | AI14: =IF(ISNUMBER(SEARCH("Shiny ", AA14)), 1, 0) -> 0 | AJ14: moderate | AL14: 0 | AM14: {=IF(AL14=1,1, IF(ISTEXT(AK14),1, IF(AO14>1,AM13, IF(AI14=1, IF(SUMPRODUCT((LEN($Y$2:$Y$4096)-LEN(SUBSTITUTE($Y$2:$Y$4096,AA14,"")))/LEN(AA14))>0,2,1), IF( SUMPRODUCT((LEN($Y$2:$Y$4096)-LEN(SUBSTITUTE($Y$2:$Y$4096,AA14,"")))/LEN(AA14)) - SUMPRODUCT((LEN($Y$2:$Y$4096)-LEN(SUBSTITUTE($Y$2:$Y$4096,"Alolan "&AA14,"")))/LEN("Alolan "&AA14)) - SUMPRODUCT((LEN($Y$2:$Y$4096)-LEN(SUBSTITUTE($Y$2:$Y$4096,"Galarian "&AA14,"")))/LEN("Galarian "&AA14)) - SUMPRODUCT((LEN($Y$2:$Y$4096)-LEN(SUBSTITUTE($Y$2:$Y$4096,"Hisuian "&AA14,"")))/LEN("Hisuian "&AA14)) - SUMPRODUCT((LEN($Y$2:$Y$4096)-LEN(SUBSTITUTE($Y$2:$Y$4096,"Paldean "&AA14,"")))/LEN("Paldean "&AA14)) >0,2,1) ))))} -> 2 | AN14: 0 | AO14: 0
A15: 2-shiny | B15: Ivysaur | C15: Grass | D15: Poison | E15: 60 | F15: 62 | G15: 63 | H15: 80 | I15: 80 | J15: 60 | K15: Seed Pokémon | L15: Forest | M15: Temperate | N15: 7.02 | O15: 6.69 | R15: =MROUND(N15,1)+P15 -> 7 | S15: =MROUND(O15,1)+Q15 -> 7 | T15: =SUM(S15,R15) -> 14 | U15: Grass | V15: Poison | W15: Dark | X15: Ground | Y15: Shiny Venusaur | Z15: {=IF(ISBLANK(AK15),_xlfn.LET( _xlpm.nameBeforeSlash, IF(ISNUMBER(SEARCH("/", Y15)), LEFT(Y15, SEARCH("/", Y15)-1), Y15), _xlpm.matchRow, IFERROR(MATCH(_xlpm.nameBeforeSlash, AA:AA, 0), ""), _xlpm.difference, IF(_xlpm.matchRow="", "", ABS((R15 + S15) - (INDEX(R:R, _xlpm.matchRow) + INDEX(S:S, _xlpm.matchRow)))), _xlpm.category, IF(_xlpm.matchRow="", "", INDEX(AJ:AJ, _xlpm.matchRow)), _xlpm.adjustment, IF(_xlpm.matchRow="", "", IF(_xlpm.category="weak", 2, IF(_xlpm.category="moderate", 4, IF(_xlpm.category="strong", 8, IF(_xlpm.category="legendary", _xlpm.difference + 12, IF(_xlpm.category="warp", _xlpm.difference + 12, 0)))))), _xlpm.result, IF(_xlpm.matchRow="", "", IF(_xlpm.category="legendary", _xlpm.adjustment, _xlpm.difference + _xlpm.adjustment)), _xlpm.result ),IF(ISBLANK(Y15),"","Hidden"))} -> 14 | AA15: Shiny Ivysaur | AC15: Seed Bomb | AD15: =_xlfn.XLOOKUP(AC15,moves!A:A,moves!B:B) -> grass | AE15: =_xlfn.XLOOKUP(AC15,moves!A:A,moves!D:D) -> 4 | AF15: =_xlfn.XLOOKUP(AC15,moves!A:A,moves!E:E) -> Every 2 regular hits deal +1 damage. | AG15: 0 | AH15: 0 | AI15: =IF(ISNUMBER(SEARCH("Shiny ", AA15)), 1, 0) -> 1 | AJ15: moderate | AL15: 0 | AM15: {=IF(AL15=1,1, IF(ISTEXT(AK15),1, IF(AO15>1,AM14, IF(AI15=1, IF(SUMPRODUCT((LEN($Y$2:$Y$4096)-LEN(SUBSTITUTE($Y$2:$Y$4096,AA15,"")))/LEN(AA15))>0,2,1), IF( SUMPRODUCT((LEN($Y$2:$Y$4096)-LEN(SUBSTITUTE($Y$2:$Y$4096,AA15,"")))/LEN(AA15)) - SUMPRODUCT((LEN($Y$2:$Y$4096)-LEN(SUBSTITUTE($Y$2:$Y$4096,"Alolan "&AA15,"")))/LEN("Alolan "&AA15)) - SUMPRODUCT((LEN($Y$2:$Y$4096)-LEN(SUBSTITUTE($Y$2:$Y$4096,"Galarian "&AA15,"")))/LEN("Galarian "&AA15)) - SUMPRODUCT((LEN($Y$2:$Y$4096)-LEN(SUBSTITUTE($Y$2:$Y$4096,"Hisuian "&AA15,"")))/LEN("Hisuian "&AA15)) - SUMPRODUCT((LEN($Y$2:$Y$4096)-LEN(SUBSTITUTE($Y$2:$Y$4096,"Paldean "&AA15,"")))/LEN("Paldean "&AA15)) >0,2,1) ))))} -> 2 | AN15: 0 | AO15: 0
A16: 3 | B16: Venusaur | C16: Grass | D16: Poison | E16: 80 | F16: 82 | G16: 83 | H16: 100 | I16: 100 | J16: 80 | K16: Seed Pokémon | L16: Forest | M16: Temperate | N16: 9.02 | O16: 8.69 | Q16: 2 | R16: =MROUND(N16,1)+P16 -> 9 | S16: =MROUND(O16,1)+Q16 -> 11 | T16: =SUM(S16,R16) -> 20 | U16: Grass | V16: Poison | W16: Dark | X16: Ground | Z16: {=IF(ISBLANK(AK16),_xlfn.LET( _xlpm.nameBeforeSlash, IF(ISNUMBER(SEARCH("/", Y16)), LEFT(Y16, SEARCH("/", Y16)-1), Y16), _xlpm.matchRow, IFERROR(MATCH(_xlpm.nameBeforeSlash, AA:AA, 0), ""), _xlpm.difference, IF(_xlpm.matchRow="", "", ABS((R16 + S16) - (INDEX(R:R, _xlpm.matchRow) + INDEX(S:S, _xlpm.matchRow)))), _xlpm.category, IF(_xlpm.matchRow="", "", INDEX(AJ:AJ, _xlpm.matchRow)), _xlpm.adjustment, IF(_xlpm.matchRow="", "", IF(_xlpm.category="weak", 2, IF(_xlpm.category="moderate", 4, IF(_xlpm.category="strong", 8, IF(_xlpm.category="legendary", _xlpm.difference + 12, IF(_xlpm.category="warp", _xlpm.difference + 12, 0)))))), _xlpm.result, IF(_xlpm.matchRow="", "", IF(_xlpm.category="legendary", _xlpm.adjustment, _xlpm.difference + _xlpm.adjustment)), _xlpm.result ),IF(ISBLANK(Y16),"","Hidden"))} | AA16: Venusaur | AC16: Solar Beam | AD16: =_xlfn.XLOOKUP(AC16,moves!A:A,moves!B:B) -> grass | AE16: =_xlfn.XLOOKUP(AC16,moves!A:A,moves!D:D) -> 6 | AF16: =_xlfn.XLOOKUP(AC16,moves!A:A,moves!E:E) -> If this move is used during Harsh Sunlight: Ignore the delay. If this move is used during Rain, Hail, or Sandstorm: Decrease attack strength by 3. | AG16: 0 | AH16: 0 | AI16: =IF(ISNUMBER(SEARCH("Shiny ", AA16)), 1, 0) -> 0 | AJ16: strong | AL16: 0 | AM16: {=IF(AL16=1,1, IF(ISTEXT(AK16),1, IF(AO16>1,AM15, IF(AI16=1, IF(SUMPRODUCT((LEN($Y$2:$Y$4096)-LEN(SUBSTITUTE($Y$2:$Y$4096,AA16,"")))/LEN(AA16))>0,2,1), IF( SUMPRODUCT((LEN($Y$2:$Y$4096)-LEN(SUBSTITUTE($Y$2:$Y$4096,AA16,"")))/LEN(AA16)) - SUMPRODUCT((LEN($Y$2:$Y$4096)-LEN(SUBSTITUTE($Y$2:$Y$4096,"Alolan "&AA16,"")))/LEN("Alolan "&AA16)) - SUMPRODUCT((LEN($Y$2:$Y$4096)-LEN(SUBSTITUTE($Y$2:$Y$4096,"Galarian "&AA16,"")))/LEN("Galarian "&AA16)) - SUMPRODUCT((LEN($Y$2:$Y$4096)-LEN(SUBSTITUTE($Y$2:$Y$4096,"Hisuian "&AA16,"")))/LEN("Hisuian "&AA16)) - SUMPRODUCT((LEN($Y$2:$Y$4096)-LEN(SUBSTITUTE($Y$2:$Y$4096,"Paldean "&AA16,"")))/LEN("Paldean "&AA16)) >0,2,1) ))))} -> 2 | AN16: 0 | AO16: 1
A17: 3-m | B17: Venusaur | C17: Grass | D17: Poison | E17: 80 | F17: 100 | G17: 123 | H17: 122 | I17: 120 | J17: 80 | K17: Seed Pokémon | L17: blank | M17: Mega | N17: 10.3 | O17: 10.49 | P17: 1 | Q17: 3 | R17: =MROUND(N17,1)+P17 -> 11 | S17: =MROUND(O17,1)+Q17 -> 13 | T17: =SUM(S17,R17) -> 24 | U17: Grass | V17: Poison | W17: Dark | X17: Ground | Z17: {=IF(ISBLANK(AK17),_xlfn.LET( _xlpm.nameBeforeSlash, IF(ISNUMBER(SEARCH("/", Y17)), LEFT(Y17, SEARCH("/", Y17)-1), Y17), _xlpm.matchRow, IFERROR(MATCH(_xlpm.nameBeforeSlash, AA:AA, 0), ""), _xlpm.difference, IF(_xlpm.matchRow="", "", ABS((R17 + S17) - (INDEX(R:R, _xlpm.matchRow) + INDEX(S:S, _xlpm.matchRow)))), _xlpm.category, IF(_xlpm.matchRow="", "", INDEX(AJ:AJ, _xlpm.matchRow)), _xlpm.adjustment, IF(_xlpm.matchRow="", "", IF(_xlpm.category="weak", 2, IF(_xlpm.category="moderate", 4, IF(_xlpm.category="strong", 8, IF(_xlpm.category="legendary", _xlpm.difference + 12, IF(_xlpm.category="warp", _xlpm.difference + 12, 0)))))), _xlpm.result, IF(_xlpm.matchRow="", "", IF(_xlpm.category="legendary", _xlpm.adjustment, _xlpm.difference + _xlpm.adjustment)), _xlpm.result ),IF(ISBLANK(Y17),"","Hidden"))} | AA17: Mega Venusaur | AB17: Mega Form | AC17: Petal Blizzard | AD17: =_xlfn.XLOOKUP(AC17,moves!A:A,moves!B:B) -> grass | AE17: =_xlfn.XLOOKUP(AC17,moves!A:A,moves!D:D) -> 5 | AF17: =_xlfn.XLOOKUP(AC17,moves!A:A,moves!E:E) | AG17: 0 | AH17: 0 | AI17: =IF(ISNUMBER(SEARCH("Shiny ", AA17)), 1, 0) -> 0 | AJ17: strong | AL17: 0 | AM17: {=IF(AL17=1,1, IF(ISTEXT(AK17),1, IF(AO17>1,AM16, IF(AI17=1, IF(SUMPRODUCT((LEN($Y$2:$Y$4096)-LEN(SUBSTITUTE($Y$2:$Y$4096,AA17,"")))/LEN(AA17))>0,2,1), IF( SUMPRODUCT((LEN($Y$2:$Y$4096)-LEN(SUBSTITUTE($Y$2:$Y$4096,AA17,"")))/LEN(AA17)) - SUMPRODUCT((LEN($Y$2:$Y$4096)-LEN(SUBSTITUTE($Y$2:$Y$4096,"Alolan "&AA17,"")))/LEN("Alolan "&AA17)) - SUMPRODUCT((LEN($Y$2:$Y$4096)-LEN(SUBSTITUTE($Y$2:$Y$4096,"Galarian "&AA17,"")))/LEN("Galarian "&AA17)) - SUMPRODUCT((LEN($Y$2:$Y$4096)-LEN(SUBSTITUTE($Y$2:$Y$4096,"Hisuian "&AA17,"")))/LEN("Hisuian "&AA17)) - SUMPRODUCT((LEN($Y$2:$Y$4096)-LEN(SUBSTITUTE($Y$2:$Y$4096,"Paldean "&AA17,"")))/LEN("Paldean "&AA17)) >0,2,1) ))))} -> 2 | AN17: 0 | AO17: 2
A18: 3-gm | B18: Venusaur | C18: Grass | D18: Poison | E18: 80 | F18: 100 | G18: 123 | H18: 122 | I18: 120 | J18: 80 | K18: Seed Pokémon | L18: blank | M18: Gigantamax | N18: 10.3 | O18: 10.49 | P18: -1 | Q18: 11 | R18: =MROUND(N18,1)+P18 -> 9 | S18: =MROUND(O18,1)+Q18 -> 21 | T18: =SUM(S18,R18) -> 30 | U18: Grass | V18: Poison | W18: Dark | X18: Ground | Z18: {=IF(ISBLANK(AK18),_xlfn.LET( _xlpm.nameBeforeSlash, IF(ISNUMBER(SEARCH("/", Y18)), LEFT(Y18, SEARCH("/", Y18)-1), Y18), _xlpm.matchRow, IFERROR(MATCH(_xlpm.nameBeforeSlash, AA:AA, 0), ""), _xlpm.difference, IF(_xlpm.matchRow="", "", ABS((R18 + S18) - (INDEX(R:R, _xlpm.matchRow) + INDEX(S:S, _xlpm.matchRow)))), _xlpm.category, IF(_xlpm.matchRow="", "", INDEX(AJ:AJ, _xlpm.matchRow)), _xlpm.adjustment, IF(_xlpm.matchRow="", "", IF(_xlpm.category="weak", 2, IF(_xlpm.category="moderate", 4, IF(_xlpm.category="strong", 8, IF(_xlpm.category="legendary", _xlpm.difference + 12, IF(_xlpm.category="warp", _xlpm.difference + 12, 0)))))), _xlpm.result, IF(_xlpm.matchRow="", "", IF(_xlpm.category="legendary", _xlpm.adjustment, _xlpm.difference + _xlpm.adjustment)), _xlpm.result ),IF(ISBLANK(Y18),"","Hidden"))} | AA18: Gigantamax Venusaur | AB18: Gigantamax Form | AC18: G-Max Vine Lash | AD18: =_xlfn.XLOOKUP(AC18,moves!A:A,moves!B:B) -> grass | AE18: =_xlfn.XLOOKUP(AC18,moves!A:A,moves!D:D) -> 5 | AF18: =_xlfn.XLOOKUP(AC18,moves!A:A,moves!E:E) -> All opposing non Grass-type active Pokémon take 2 damage at the end of their turns. | AG18: 0 | AH18: 0 | AI18: =IF(ISNUMBER(SEARCH("Shiny ", AA18)), 1, 0) -> 0 | AJ18: strong | AL18: 0 | AM18: {=IF(AL18=1,1, IF(ISTEXT(AK18),1, IF(AO18>1,AM17, IF(AI18=1, IF(SUMPRODUCT((LEN($Y$2:$Y$4096)-LEN(SUBSTITUTE($Y$2:$Y$4096,AA18,"")))/LEN(AA18))>0,2,1), IF( SUMPRODUCT((LEN($Y$2:$Y$4096)-LEN(SUBSTITUTE($Y$2:$Y$4096,AA18,"")))/LEN(AA18)) - SUMPRODUCT((LEN($Y$2:$Y$4096)-LEN(SUBSTITUTE($Y$2:$Y$4096,"Alolan "&AA18,"")))/LEN("Alolan "&AA18)) - SUMPRODUCT((LEN($Y$2:$Y$4096)-LEN(SUBSTITUTE($Y$2:$Y$4096,"Galarian "&AA18,"")))/LEN("Galarian "&AA18)) - SUMPRODUCT((LEN($Y$2:$Y$4096)-LEN(SUBSTITUTE($Y$2:$Y$4096,"Hisuian "&AA18,"")))/LEN("Hisuian "&AA18)) - SUMPRODUCT((LEN($Y$2:$Y$4096)-LEN(SUBSTITUTE($Y$2:$Y$4096,"Paldean "&AA18,"")))/LEN("Paldean "&AA18)) >0,2,1) ))))} -> 2 | AN18: 0 | AO18: 3
A19: 3-shiny | B19: Venusaur | C19: Grass | D19: Poison | E19: 80 | F19: 82 | G19: 83 | H19: 100 | I19: 100 | J19: 80 | K19: Seed Pokémon | L19: Forest | M19: Temperate | N19: 9.02 | O19: 8.69 | Q19: 2 | R19: =MROUND(N19,1)+P19 -> 9 | S19: =MROUND(O19,1)+Q19 -> 11 | T19: =SUM(S19,R19) -> 20 | U19: Grass | V19: Poison | W19: Dark | X19: Ground | Z19: {=IF(ISBLANK(AK19),_xlfn.LET( _xlpm.nameBeforeSlash, IF(ISNUMBER(SEARCH("/", Y19)), LEFT(Y19, SEARCH("/", Y19)-1), Y19), _xlpm.matchRow, IFERROR(MATCH(_xlpm.nameBeforeSlash, AA:AA, 0), ""), _xlpm.difference, IF(_xlpm.matchRow="", "", ABS((R19 + S19) - (INDEX(R:R, _xlpm.matchRow) + INDEX(S:S, _xlpm.matchRow)))), _xlpm.category, IF(_xlpm.matchRow="", "", INDEX(AJ:AJ, _xlpm.matchRow)), _xlpm.adjustment, IF(_xlpm.matchRow="", "", IF(_xlpm.category="weak", 2, IF(_xlpm.category="moderate", 4, IF(_xlpm.category="strong", 8, IF(_xlpm.category="legendary", _xlpm.difference + 12, IF(_xlpm.category="warp", _xlpm.difference + 12, 0)))))), _xlpm.result, IF(_xlpm.matchRow="", "", IF(_xlpm.category="legendary", _xlpm.adjustment, _xlpm.difference + _xlpm.adjustment)), _xlpm.result ),IF(ISBLANK(Y19),"","Hidden"))} | AA19: Shiny Venusaur | AC19: Pollen Hazard | AD19: =_xlfn.XLOOKUP(AC19,moves!A:A,moves!B:B) -> grass | AE19: =_xlfn.XLOOKUP(AC19,moves!A:A,moves!D:D) -> 4 | AF19: =_xlfn.XLOOKUP(AC19,moves!A:A,moves!E:E) -> Inflict the Confused, Burned, and Poisoned status on the target, simultaneously. | AG19: 0 | AH19: 0 | AI19: =IF(ISNUMBER(SEARCH("Shiny ", AA19)), 1, 0) -> 1 | AJ19: strong | AL19: 0 | AM19: {=IF(AL19=1,1, IF(ISTEXT(AK19),1, IF(AO19>1,AM18, IF(AI19=1, IF(SUMPRODUCT((LEN($Y$2:$Y$4096)-LEN(SUBSTITUTE($Y$2:$Y$4096,AA19,"")))/LEN(AA19))>0,2,1), IF( SUMPRODUCT((LEN($Y$2:$Y$4096)-LEN(SUBSTITUTE($Y$2:$Y$4096,AA19,"")))/LEN(AA19)) - SUMPRODUCT((LEN($Y$2:$Y$4096)-LEN(SUBSTITUTE($Y$2:$Y$4096,"Alolan "&AA19,"")))/LEN("Alolan "&AA19)) - SUMPRODUCT((LEN($Y$2:$Y$4096)-LEN(SUBSTITUTE($Y$2:$Y$4096,"Galarian "&AA19,"")))/LEN("Galarian "&AA19)) - SUMPRODUCT((LEN($Y$2:$Y$4096)-LEN(SUBSTITUTE($Y$2:$Y$4096,"Hisuian "&AA19,"")))/LEN("Hisuian "&AA19)) - SUMPRODUCT((LEN($Y$2:$Y$4096)-LEN(SUBSTITUTE($Y$2:$Y$4096,"Paldean "&AA19,"")))/LEN("Paldean "&AA19)) >0,2,1) ))))} -> 2 | AN19: 0 | AO19: 1
A20: 3-m-shiny | B20: Venusaur | C20: Grass | D20: Poison | E20: 80 | F20: 100 | G20: 123 | H20: 122 | I20: 120 | J20: 80 | K20: Seed Pokémon | L20: blank | M20: Mega | N20: 10.3 | O20: 10.49 | P20: 1 | Q20: 3 | R20: =MROUND(N20,1)+P20 -> 11 | S20: =MROUND(O20,1)+Q20 -> 13 | T20: =SUM(S20,R20) -> 24 | U20: Grass | V20: Poison | W20: Dark | X20: Ground | Z20: {=IF(ISBLANK(AK20),_xlfn.LET( _xlpm.nameBeforeSlash, IF(ISNUMBER(SEARCH("/", Y20)), LEFT(Y20, SEARCH("/", Y20)-1), Y20), _xlpm.matchRow, IFERROR(MATCH(_xlpm.nameBeforeSlash, AA:AA, 0), ""), _xlpm.difference, IF(_xlpm.matchRow="", "", ABS((R20 + S20) - (INDEX(R:R, _xlpm.matchRow) + INDEX(S:S, _xlpm.matchRow)))), _xlpm.category, IF(_xlpm.matchRow="", "", INDEX(AJ:AJ, _xlpm.matchRow)), _xlpm.adjustment, IF(_xlpm.matchRow="", "", IF(_xlpm.category="weak", 2, IF(_xlpm.category="moderate", 4, IF(_xlpm.category="strong", 8, IF(_xlpm.category="legendary", _xlpm.difference + 12, IF(_xlpm.category="warp", _xlpm.difference + 12, 0)))))), _xlpm.result, IF(_xlpm.matchRow="", "", IF(_xlpm.category="legendary", _xlpm.adjustment, _xlpm.difference + _xlpm.adjustment)), _xlpm.result ),IF(ISBLANK(Y20),"","Hidden"))} | AA20: Shiny Mega Venusaur | AB20: Mega Form | AC20: Bloom Buster | AD20: =_xlfn.XLOOKUP(AC20,moves!A:A,moves!B:B) -> grass | AE20: =_xlfn.XLOOKUP(AC20,moves!A:A,moves!D:D) -> 5 | AF20: =_xlfn.XLOOKUP(AC20,moves!A:A,moves!E:E) -> If 2 or more status symbols are rolled: Deal 2 damage to all Pokémon in the target party that is not the target. | AG20: 0 | AH20: 0 | AI20: =IF(ISNUMBER(SEARCH("Shiny ", AA20)), 1, 0) -> 1 | AJ20: strong | AL20: 0 | AM20: {=IF(AL20=1,1, IF(ISTEXT(AK20),1, IF(AO20>1,AM19, IF(AI20=1, IF(SUMPRODUCT((LEN($Y$2:$Y$4096)-LEN(SUBSTITUTE($Y$2:$Y$4096,AA20,"")))/LEN(AA20))>0,2,1), IF( SUMPRODUCT((LEN($Y$2:$Y$4096)-LEN(SUBSTITUTE($Y$2:$Y$4096,AA20,"")))/LEN(AA20)) - SUMPRODUCT((LEN($Y$2:$Y$4096)-LEN(SUBSTITUTE($Y$2:$Y$4096,"Alolan "&AA20,"")))/LEN("Alolan "&AA20)) - SUMPRODUCT((LEN($Y$2:$Y$4096)-LEN(SUBSTITUTE($Y$2:$Y$4096,"Galarian "&AA20,"")))/LEN("Galarian "&AA20)) - SUMPRODUCT((LEN($Y$2:$Y$4096)-LEN(SUBSTITUTE($Y$2:$Y$4096,"Hisuian "&AA20,"")))/LEN("Hisuian "&AA20)) - SUMPRODUCT((LEN($Y$2:$Y$4096)-LEN(SUBSTITUTE($Y$2:$Y$4096,"Paldean "&AA20,"")))/LEN("Paldean "&AA20)) >0,2,1) ))))} -> 2 | AN20: 0 | AO20: 2
A21: 3-gm-shiny | B21: Venusaur | C21: Grass | D21: Poison | E21: 80 | F21: 100 | G21: 123 | H21: 122 | I21: 120 | J21: 80 | K21: Seed Pokémon | L21: blank | M21: Gigantamax | N21: 10.3 | O21: 10.49 | P21: -1 | Q21: 11 | R21: =MROUND(N21,1)+P21 -> 9 | S21: =MROUND(O21,1)+Q21 -> 21 | T21: =SUM(S21,R21) -> 30 | U21: Grass | V21: Poison | W21: Dark | X21: Ground | Z21: {=IF(ISBLANK(AK21),_xlfn.LET( _xlpm.nameBeforeSlash, IF(ISNUMBER(SEARCH("/", Y21)), LEFT(Y21, SEARCH("/", Y21)-1), Y21), _xlpm.matchRow, IFERROR(MATCH(_xlpm.nameBeforeSlash, AA:AA, 0), ""), _xlpm.difference, IF(_xlpm.matchRow="", "", ABS((R21 + S21) - (INDEX(R:R, _xlpm.matchRow) + INDEX(S:S, _xlpm.matchRow)))), _xlpm.category, IF(_xlpm.matchRow="", "", INDEX(AJ:AJ, _xlpm.matchRow)), _xlpm.adjustment, IF(_xlpm.matchRow="", "", IF(_xlpm.category="weak", 2, IF(_xlpm.category="moderate", 4, IF(_xlpm.category="strong", 8, IF(_xlpm.category="legendary", _xlpm.difference + 12, IF(_xlpm.category="warp", _xlpm.difference + 12, 0)))))), _xlpm.result, IF(_xlpm.matchRow="", "", IF(_xlpm.category="legendary", _xlpm.adjustment, _xlpm.difference + _xlpm.adjustment)), _xlpm.result ),IF(ISBLANK(Y21),"","Hidden"))} | AA21: Shiny Gigantamax Venusaur | AB21: Gigantamax Form | AC21: G-Max Bloom | AD21: =_xlfn.XLOOKUP(AC21,moves!A:A,moves!B:B) -> grass | AE21: =_xlfn.XLOOKUP(AC21,moves!A:A,moves!D:D) -> 5 | AF21: =_xlfn.XLOOKUP(AC21,moves!A:A,moves!E:E) -> Heal 4. | AG21: 0 | AH21: 0 | AI21: =IF(ISNUMBER(SEARCH("Shiny ", AA21)), 1, 0) -> 1 | AJ21: strong | AL21: 0 | AM21: {=IF(AL21=1,1, IF(ISTEXT(AK21),1, IF(AO21>1,AM20, IF(AI21=1, IF(SUMPRODUCT((LEN($Y$2:$Y$4096)-LEN(SUBSTITUTE($Y$2:$Y$4096,AA21,"")))/LEN(AA21))>0,2,1), IF( SUMPRODUCT((LEN($Y$2:$Y$4096)-LEN(SUBSTITUTE($Y$2:$Y$4096,AA21,"")))/LEN(AA21)) - SUMPRODUCT((LEN($Y$2:$Y$4096)-LEN(SUBSTITUTE($Y$2:$Y$4096,"Alolan "&AA21,"")))/LEN("Alolan "&AA21)) - SUMPRODUCT((LEN($Y$2:$Y$4096)-LEN(SUBSTITUTE($Y$2:$Y$4096,"Galarian "&AA21,"")))/LEN("Galarian "&AA21)) - SUMPRODUCT((LEN($Y$2:$Y$4096)-LEN(SUBSTITUTE($Y$2:$Y$4096,"Hisuian "&AA21,"")))/LEN("Hisuian "&AA21)) - SUMPRODUCT((LEN($Y$2:$Y$4096)-LEN(SUBSTITUTE($Y$2:$Y$4096,"Paldean "&AA21,"")))/LEN("Paldean "&AA21)) >0,2,1) ))))} -> 2 | AN21: 0 | AO21: 3
A22: 4 | B22: Charmander | C22: Fire | E22: 39 | F22: 52 | G22: 43 | H22: 60 | I22: 50 | J22: 65 | K22: Lizard Pokémon | L22: Mountain | M22: Warm | N22: 6.12 | O22: 4.35 | R22: =MROUND(N22,1)+P22 -> 6 | S22: =MROUND(O22,1)+Q22 -> 4 | T22: =SUM(S22,R22) -> 10 | U22: Fire | V22: Flying | W22: Dragon | X22: Ground | Y22: Charmeleon | Z22: {=IF(ISBLANK(AK22),_xlfn.LET( _xlpm.nameBeforeSlash, IF(ISNUMBER(SEARCH("/", Y22)), LEFT(Y22, SEARCH("/", Y22)-1), Y22), _xlpm.matchRow, IFERROR(MATCH(_xlpm.nameBeforeSlash, AA:AA, 0), ""), _xlpm.difference, IF(_xlpm.matchRow="", "", ABS((R22 + S22) - (INDEX(R:R, _xlpm.matchRow) + INDEX(S:S, _xlpm.matchRow)))), _xlpm.category, IF(_xlpm.matchRow="", "", INDEX(AJ:AJ, _xlpm.matchRow)), _xlpm.adjustment, IF(_xlpm.matchRow="", "", IF(_xlpm.category="weak", 2, IF(_xlpm.category="moderate", 4, IF(_xlpm.category="strong", 8, IF(_xlpm.category="legendary", _xlpm.difference + 12, IF(_xlpm.category="warp", _xlpm.difference + 12, 0)))))), _xlpm.result, IF(_xlpm.matchRow="", "", IF(_xlpm.category="legendary", _xlpm.adjustment, _xlpm.difference + _xlpm.adjustment)), _xlpm.result ),IF(ISBLANK(Y22),"","Hidden"))} -> 8 | AA22: Charmander | AC22: Ember | AD22: =_xlfn.XLOOKUP(AC22,moves!A:A,moves!B:B) -> fire | AE22: =_xlfn.XLOOKUP(AC22,moves!A:A,moves!D:D) -> 2 | AF22: =_xlfn.XLOOKUP(AC22,moves!A:A,moves!E:E) -> Inflict the Burned status on the target. | AG22: 1 | AH22: 0 | AI22: =IF(ISNUMBER(SEARCH("Shiny ", AA22)), 1, 0) -> 0 | AJ22: starter | AL22: 0 | AM22: {=IF(AL22=1,1, IF(ISTEXT(AK22),1, IF(AO22>1,AM21, IF(AI22=1, IF(SUMPRODUCT((LEN($Y$2:$Y$4096)-LEN(SUBSTITUTE($Y$2:$Y$4096,AA22,"")))/LEN(AA22))>0,2,1), IF( SUMPRODUCT((LEN($Y$2:$Y$4096)-LEN(SUBSTITUTE($Y$2:$Y$4096,AA22,"")))/LEN(AA22)) - SUMPRODUCT((LEN($Y$2:$Y$4096)-LEN(SUBSTITUTE($Y$2:$Y$4096,"Alolan "&AA22,"")))/LEN("Alolan "&AA22)) - SUMPRODUCT((LEN($Y$2:$Y$4096)-LEN(SUBSTITUTE($Y$2:$Y$4096,"Galarian "&AA22,"")))/LEN("Galarian "&AA22)) - SUMPRODUCT((LEN($Y$2:$Y$4096)-LEN(SUBSTITUTE($Y$2:$Y$4096,"Hisuian "&AA22,"")))/LEN("Hisuian "&AA22)) - SUMPRODUCT((LEN($Y$2:$Y$4096)-LEN(SUBSTITUTE($Y$2:$Y$4096,"Paldean "&AA22,"")))/LEN("Paldean "&AA22)) >0,2,1) ))))} -> 1 | AN22: 0 | AO22: 0
A23: 4-shiny | B23: Charmander | C23: Fire | E23: 39 | F23: 52 | G23: 43 | H23: 60 | I23: 50 | J23: 65 | K23: Lizard Pokémon | L23: Mountain | M23: Warm | N23: 6.12 | O23: 4.35 | R23: =MROUND(N23,1)+P23 -> 6 | S23: =MROUND(O23,1)+Q23 -> 4 | T23: =SUM(S23,R23) -> 10 | U23: Fire | V23: Flying | W23: Dragon | X23: Ground | Y23: Shiny Charmeleon | Z23: {=IF(ISBLANK(AK23),_xlfn.LET( _xlpm.nameBeforeSlash, IF(ISNUMBER(SEARCH("/", Y23)), LEFT(Y23, SEARCH("/", Y23)-1), Y23), _xlpm.matchRow, IFERROR(MATCH(_xlpm.nameBeforeSlash, AA:AA, 0), ""), _xlpm.difference, IF(_xlpm.matchRow="", "", ABS((R23 + S23) - (INDEX(R:R, _xlpm.matchRow) + INDEX(S:S, _xlpm.matchRow)))), _xlpm.category, IF(_xlpm.matchRow="", "", INDEX(AJ:AJ, _xlpm.matchRow)), _xlpm.adjustment, IF(_xlpm.matchRow="", "", IF(_xlpm.category="weak", 2, IF(_xlpm.category="moderate", 4, IF(_xlpm.category="strong", 8, IF(_xlpm.category="legendary", _xlpm.difference + 12, IF(_xlpm.category="warp", _xlpm.difference + 12, 0)))))), _xlpm.result, IF(_xlpm.matchRow="", "", IF(_xlpm.category="legendary", _xlpm.adjustment, _xlpm.difference + _xlpm.adjustment)), _xlpm.result ),IF(ISBLANK(Y23),"","Hidden"))} -> 8 | AA23: Shiny Charmander | AC23: Fire Fang | AD23: =_xlfn.XLOOKUP(AC23,moves!A:A,moves!B:B) -> fire | AE23: =_xlfn.XLOOKUP(AC23,moves!A:A,moves!D:D) -> 3 | AF23: =_xlfn.XLOOKUP(AC23,moves!A:A,moves!E:E) -> If any status symbols are rolled: Inflict the Burned status on the target. | AG23: 1 | AH23: 0 | AI23: =IF(ISNUMBER(SEARCH("Shiny ", AA23)), 1, 0) -> 1 | AJ23: weak | AL23: 0 | AM23: {=IF(AL23=1,1, IF(ISTEXT(AK23),1, IF(AO23>1,AM22, IF(AI23=1, IF(SUMPRODUCT((LEN($Y$2:$Y$4096)-LEN(SUBSTITUTE($Y$2:$Y$4096,AA23,"")))/LEN(AA23))>0,2,1), IF( SUMPRODUCT((LEN($Y$2:$Y$4096)-LEN(SUBSTITUTE($Y$2:$Y$4096,AA23,"")))/LEN(AA23)) - SUMPRODUCT((LEN($Y$2:$Y$4096)-LEN(SUBSTITUTE($Y$2:$Y$4096,"Alolan "&AA23,"")))/LEN("Alolan "&AA23)) - SUMPRODUCT((LEN($Y$2:$Y$4096)-LEN(SUBSTITUTE($Y$2:$Y$4096,"Galarian "&AA23,"")))/LEN("Galarian "&AA23)) - SUMPRODUCT((LEN($Y$2:$Y$4096)-LEN(SUBSTITUTE($Y$2:$Y$4096,"Hisuian "&AA23,"")))/LEN("Hisuian "&AA23)) - SUMPRODUCT((LEN($Y$2:$Y$4096)-LEN(SUBSTITUTE($Y$2:$Y$4096,"Paldean "&AA23,"")))/LEN("Paldean "&AA23)) >0,2,1) ))))} -> 1 | AN23: 0 | AO23: 0
A24: 5 | B24: Charmeleon | C24: Fire | E24: 58 | F24: 64 | G24: 58 | H24: 80 | I24: 65 | J24: 80 | K24: Flame Pokémon | L24: Mountain | M24: Warm | N24: 7.84 | O24: 6.01 | R24: =MROUND(N24,1)+P24 -> 8 | S24: =MROUND(O24,1)+Q24 -> 6 | T24: =SUM(S24,R24) -> 14 | U24: Fire | V24: Flying | W24: Dragon | X24: Ground | Y24: Charizard | Z24: {=IF(ISBLANK(AK24),_xlfn.LET( _xlpm.nameBeforeSlash, IF(ISNUMBER(SEARCH("/", Y24)), LEFT(Y24, SEARCH("/", Y24)-1), Y24), _xlpm.matchRow, IFERROR(MATCH(_xlpm.nameBeforeSlash, AA:AA, 0), ""), _xlpm.difference, IF(_xlpm.matchRow="", "", ABS((R24 + S24) - (INDEX(R:R, _xlpm.matchRow) + INDEX(S:S, _xlpm.matchRow)))), _xlpm.category, IF(_xlpm.matchRow="", "", INDEX(AJ:AJ, _xlpm.matchRow)), _xlpm.adjustment, IF(_xlpm.matchRow="", "", IF(_xlpm.category="weak", 2, IF(_xlpm.category="moderate", 4, IF(_xlpm.category="strong", 8, IF(_xlpm.category="legendary", _xlpm.difference + 12, IF(_xlpm.category="warp", _xlpm.difference + 12, 0)))))), _xlpm.result, IF(_xlpm.matchRow="", "", IF(_xlpm.category="legendary", _xlpm.adjustment, _xlpm.difference + _xlpm.adjustment)), _xlpm.result ),IF(ISBLANK(Y24),"","Hidden"))} -> 14 | AA24: Charmeleon | AC24: Dragon Breath | AD24: =_xlfn.XLOOKUP(AC24,moves!A:A,moves!B:B) -> dragon | AE24: =_xlfn.XLOOKUP(AC24,moves!A:A,moves!D:D) -> 3 | AF24: =_xlfn.XLOOKUP(AC24,moves!A:A,moves!E:E) -> If any status symbols are rolled: Inflict the Paralyzed status on the target. | AG24: 0 | AH24: 0 | AI24: =IF(ISNUMBER(SEARCH("Shiny ", AA24)), 1, 0) -> 0 | AJ24: moderate | AL24: 0 | AM24: {=IF(AL24=1,1, IF(ISTEXT(AK24),1, IF(AO24>1,AM23, IF(AI24=1, IF(SUMPRODUCT((LEN($Y$2:$Y$4096)-LEN(SUBSTITUTE($Y$2:$Y$4096,AA24,"")))/LEN(AA24))>0,2,1), IF( SUMPRODUCT((LEN($Y$2:$Y$4096)-LEN(SUBSTITUTE($Y$2:$Y$4096,AA24,"")))/LEN(AA24)) - SUMPRODUCT((LEN($Y$2:$Y$4096)-LEN(SUBSTITUTE($Y$2:$Y$4096,"Alolan "&AA24,"")))/LEN("Alolan "&AA24)) - SUMPRODUCT((LEN($Y$2:$Y$4096)-LEN(SUBSTITUTE($Y$2:$Y$4096,"Galarian "&AA24,"")))/LEN("Galarian "&AA24)) - SUMPRODUCT((LEN($Y$2:$Y$4096)-LEN(SUBSTITUTE($Y$2:$Y$4096,"Hisuian "&AA24,"")))/LEN("Hisuian "&AA24)) - SUMPRODUCT((LEN($Y$2:$Y$4096)-LEN(SUBSTITUTE($Y$2:$Y$4096,"Paldean "&AA24,"")))/LEN("Paldean "&AA24)) >0,2,1) ))))} -> 2 | AN24: 0 | AO24: 0
A25: 5-shiny | B25: Charmeleon | C25: Fire | E25: 58 | F25: 64 | G25: 58 | H25: 80 | I25: 65 | J25: 80 | K25: Flame Pokémon | L25: Mountain | M25: Warm | N25: 7.84 | O25: 6.01 | R25: =MROUND(N25,1)+P25 -> 8 | S25: =MROUND(O25,1)+Q25 -> 6 | T25: =SUM(S25,R25) -> 14 | U25: Fire | V25: Flying | W25: Dragon | X25: Ground | Y25: Shiny Charizard | Z25: {=IF(ISBLANK(AK25),_xlfn.LET( _xlpm.nameBeforeSlash, IF(ISNUMBER(SEARCH("/", Y25)), LEFT(Y25, SEARCH("/", Y25)-1), Y25), _xlpm.matchRow, IFERROR(MATCH(_xlpm.nameBeforeSlash, AA:AA, 0), ""), _xlpm.difference, IF(_xlpm.matchRow="", "", ABS((R25 + S25) - (INDEX(R:R, _xlpm.matchRow) + INDEX(S:S, _xlpm.matchRow)))), _xlpm.category, IF(_xlpm.matchRow="", "", INDEX(AJ:AJ, _xlpm.matchRow)), _xlpm.adjustment, IF(_xlpm.matchRow="", "", IF(_xlpm.category="weak", 2, IF(_xlpm.category="moderate", 4, IF(_xlpm.category="strong", 8, IF(_xlpm.category="legendary", _xlpm.difference + 12, IF(_xlpm.category="warp", _xlpm.difference + 12, 0)))))), _xlpm.result, IF(_xlpm.matchRow="", "", IF(_xlpm.category="legendary", _xlpm.adjustment, _xlpm.difference + _xlpm.adjustment)), _xlpm.result ),IF(ISBLANK(Y25),"","Hidden"))} -> 14 | AA25: Shiny Charmeleon | AC25: Scorching Sands | AD25: =_xlfn.XLOOKUP(AC25,moves!A:A,moves!B:B) -> ground | AE25: =_xlfn.XLOOKUP(AC25,moves!A:A,moves!D:D) -> 3 | AF25: =_xlfn.XLOOKUP(AC25,moves!A:A,moves!E:E) -> If any status symbols are rolled: Inflict the Burned status on the target | AG25: 0 | AH25: 0 | AI25: =IF(ISNUMBER(SEARCH("Shiny ", AA25)), 1, 0) -> 1 | AJ25: moderate | AL25: 0 | AM25: {=IF(AL25=1,1, IF(ISTEXT(AK25),1, IF(AO25>1,AM24, IF(AI25=1, IF(SUMPRODUCT((LEN($Y$2:$Y$4096)-LEN(SUBSTITUTE($Y$2:$Y$4096,AA25,"")))/LEN(AA25))>0,2,1), IF( SUMPRODUCT((LEN($Y$2:$Y$4096)-LEN(SUBSTITUTE($Y$2:$Y$4096,AA25,"")))/LEN(AA25)) - SUMPRODUCT((LEN($Y$2:$Y$4096)-LEN(SUBSTITUTE($Y$2:$Y$4096,"Alolan "&AA25,"")))/LEN("Alolan "&AA25)) - SUMPRODUCT((LEN($Y$2:$Y$4096)-LEN(SUBSTITUTE($Y$2:$Y$4096,"Galarian "&AA25,"")))/LEN("Galarian "&AA25)) - SUMPRODUCT((LEN($Y$2:$Y$4096)-LEN(SUBSTITUTE($Y$2:$Y$4096,"Hisuian "&AA25,"")))/LEN("Hisuian "&AA25)) - SUMPRODUCT((LEN($Y$2:$Y$4096)-LEN(SUBSTITUTE($Y$2:$Y$4096,"Paldean "&AA25,"")))/LEN("Paldean "&AA25)) >0,2,1) ))))} -> 2 | AN25: 0 | AO25: 0
A26: 6 | B26: Charizard | C26: Fire | D26: Flying | E26: 78 | F26: 84 | G26: 78 | H26: 109 | I26: 85 | J26: 100 | K26: Flame Pokémon | L26: Mountain | M26: Warm | N26: 10.29 | O26: 8.01 | P26: 1 | Q26: 1 | R26: =MROUND(N26,1)+P26 -> 11 | S26: =MROUND(O26,1)+Q26 -> 9 | T26: =SUM(S26,R26) -> 20 | U26: Fire | V26: Flying | W26: Dragon | X26: Ground | Z26: {=IF(ISBLANK(AK26),_xlfn.LET( _xlpm.nameBeforeSlash, IF(ISNUMBER(SEARCH("/", Y26)), LEFT(Y26, SEARCH("/", Y26)-1), Y26), _xlpm.matchRow, IFERROR(MATCH(_xlpm.nameBeforeSlash, AA:AA, 0), ""), _xlpm.difference, IF(_xlpm.matchRow="", "", ABS((R26 + S26) - (INDEX(R:R, _xlpm.matchRow) + INDEX(S:S, _xlpm.matchRow)))), _xlpm.category, IF(_xlpm.matchRow="", "", INDEX(AJ:AJ, _xlpm.matchRow)), _xlpm.adjustment, IF(_xlpm.matchRow="", "", IF(_xlpm.category="weak", 2, IF(_xlpm.category="moderate", 4, IF(_xlpm.category="strong", 8, IF(_xlpm.category="legendary", _xlpm.difference + 12, IF(_xlpm.category="warp", _xlpm.difference + 12, 0)))))), _xlpm.result, IF(_xlpm.matchRow="", "", IF(_xlpm.category="legendary", _xlpm.adjustment, _xlpm.difference + _xlpm.adjustment)), _xlpm.result ),IF(ISBLANK(Y26),"","Hidden"))} | AA26: Charizard | AC26: Flamethrower | AD26: =_xlfn.XLOOKUP(AC26,moves!A:A,moves!B:B) -> fire | AE26: =_xlfn.XLOOKUP(AC26,moves!A:A,moves!D:D) -> 4 | AF26: =_xlfn.XLOOKUP(AC26,moves!A:A,moves!E:E) -> If any status symbols are rolled: Inflict the Burned status on the target. | AG26: 0 | AH26: 0 | AI26: =IF(ISNUMBER(SEARCH("Shiny ", AA26)), 1, 0) -> 0 | AJ26: strong | AL26: 0 | AM26: {=IF(AL26=1,1, IF(ISTEXT(AK26),1, IF(AO26>1,AM25, IF(AI26=1, IF(SUMPRODUCT((LEN($Y$2:$Y$4096)-LEN(SUBSTITUTE($Y$2:$Y$4096,AA26,"")))/LEN(AA26))>0,2,1), IF( SUMPRODUCT((LEN($Y$2:$Y$4096)-LEN(SUBSTITUTE($Y$2:$Y$4096,AA26,"")))/LEN(AA26)) - SUMPRODUCT((LEN($Y$2:$Y$4096)-LEN(SUBSTITUTE($Y$2:$Y$4096,"Alolan "&AA26,"")))/LEN("Alolan "&AA26)) - SUMPRODUCT((LEN($Y$2:$Y$4096)-LEN(SUBSTITUTE($Y$2:$Y$4096,"Galarian "&AA26,"")))/LEN("Galarian "&AA26)) - SUMPRODUCT((LEN($Y$2:$Y$4096)-LEN(SUBSTITUTE($Y$2:$Y$4096,"Hisuian "&AA26,"")))/LEN("Hisuian "&AA26)) - SUMPRODUCT((LEN($Y$2:$Y$4096)-LEN(SUBSTITUTE($Y$2:$Y$4096,"Paldean "&AA26,"")))/LEN("Paldean "&AA26)) >0,2,1) ))))} -> 2 | AN26: 0 | AO26: 1
A27: 6-mx | B27: Charizard | C27: Fire | D27: Dragon | E27: 78 | F27: 130 | G27: 111 | H27: 130 | I27: 85 | J27: 100 | K27: Flame Pokémon | L27: blank | M27: Mega | N27: 11.8 | O27: 9 | P27: 1 | Q27: 2 | R27: =MROUND(N27,1)+P27 -> 13 | S27: =MROUND(O27,1)+Q27 -> 11 | T27: =SUM(S27,R27) -> 24 | U27: Fire | V27: Dragon | W27: Flying | X27: Ground | Z27: {=IF(ISBLANK(AK27),_xlfn.LET( _xlpm.nameBeforeSlash, IF(ISNUMBER(SEARCH("/", Y27)), LEFT(Y27, SEARCH("/", Y27)-1), Y27), _xlpm.matchRow, IFERROR(MATCH(_xlpm.nameBeforeSlash, AA:AA, 0), ""), _xlpm.difference, IF(_xlpm.matchRow="", "", ABS((R27 + S27) - (INDEX(R:R, _xlpm.matchRow) + INDEX(S:S, _xlpm.matchRow)))), _xlpm.category, IF(_xlpm.matchRow="", "", INDEX(AJ:AJ, _xlpm.matchRow)), _xlpm.adjustment, IF(_xlpm.matchRow="", "", IF(_xlpm.category="weak", 2, IF(_xlpm.category="moderate", 4, IF(_xlpm.category="strong", 8, IF(_xlpm.category="legendary", _xlpm.difference + 12, IF(_xlpm.category="warp", _xlpm.difference + 12, 0)))))), _xlpm.result, IF(_xlpm.matchRow="", "", IF(_xlpm.category="legendary", _xlpm.adjustment, _xlpm.difference + _xlpm.adjustment)), _xlpm.result ),IF(ISBLANK(Y27),"","Hidden"))} | AA27: Mega Charizard X | AB27: Mega Form X | AC27: Blast Burn | AD27: =_xlfn.XLOOKUP(AC27,moves!A:A,moves!B:B) -> fire | AE27: =_xlfn.XLOOKUP(AC27,moves!A:A,moves!D:D) -> 8 | AF27: =_xlfn.XLOOKUP(AC27,moves!A:A,moves!E:E) | AG27: 0 | AH27: 0 | AI27: =IF(ISNUMBER(SEARCH("Shiny ", AA27)), 1, 0) -> 0 | AJ27: strong | AL27: 0 | AM27: {=IF(AL27=1,1, IF(ISTEXT(AK27),1, IF(AO27>1,AM26, IF(AI27=1, IF(SUMPRODUCT((LEN($Y$2:$Y$4096)-LEN(SUBSTITUTE($Y$2:$Y$4096,AA27,"")))/LEN(AA27))>0,2,1), IF( SUMPRODUCT((LEN($Y$2:$Y$4096)-LEN(SUBSTITUTE($Y$2:$Y$4096,AA27,"")))/LEN(AA27)) - SUMPRODUCT((LEN($Y$2:$Y$4096)-LEN(SUBSTITUTE($Y$2:$Y$4096,"Alolan "&AA27,"")))/LEN("Alolan "&AA27)) - SUMPRODUCT((LEN($Y$2:$Y$4096)-LEN(SUBSTITUTE($Y$2:$Y$4096,"Galarian "&AA27,"")))/LEN("Galarian "&AA27)) - SUMPRODUCT((LEN($Y$2:$Y$4096)-LEN(SUBSTITUTE($Y$2:$Y$4096,"Hisuian "&AA27,"")))/LEN("Hisuian "&AA27)) - SUMPRODUCT((LEN($Y$2:$Y$4096)-LEN(SUBSTITUTE($Y$2:$Y$4096,"Paldean "&AA27,"")))/LEN("Paldean "&AA27)) >0,2,1) ))))} -> 2 | AN27: 0 | AO27: 2
A28: 6-my | B28: Charizard | C28: Fire | D28: Flying | E28: 78 | F28: 104 | G28: 78 | H28: 159 | I28: 115 | J28: 100 | K28: Flame Pokémon | L28: blank | M28: Mega | N28: 12.99 | O28: 8.91 | P28: 1 | Q28: 1 | R28: =MROUND(N28,1)+P28 -> 14 | S28: =MROUND(O28,1)+Q28 -> 10 | T28: =SUM(S28,R28) -> 24 | U28: Fire | V28: Flying | W28: Dragon | X28: Ground | Z28: {=IF(ISBLANK(AK28),_xlfn.LET( _xlpm.nameBeforeSlash, IF(ISNUMBER(SEARCH("/", Y28)), LEFT(Y28, SEARCH("/", Y28)-1), Y28), _xlpm.matchRow, IFERROR(MATCH(_xlpm.nameBeforeSlash, AA:AA, 0), ""), _xlpm.difference, IF(_xlpm.matchRow="", "", ABS((R28 + S28) - (INDEX(R:R, _xlpm.matchRow) + INDEX(S:S, _xlpm.matchRow)))), _xlpm.category, IF(_xlpm.matchRow="", "", INDEX(AJ:AJ, _xlpm.matchRow)), _xlpm.adjustment, IF(_xlpm.matchRow="", "", IF(_xlpm.category="weak", 2, IF(_xlpm.category="moderate", 4, IF(_xlpm.category="strong", 8, IF(_xlpm.category="legendary", _xlpm.difference + 12, IF(_xlpm.category="warp", _xlpm.difference + 12, 0)))))), _xlpm.result, IF(_xlpm.matchRow="", "", IF(_xlpm.category="legendary", _xlpm.adjustment, _xlpm.difference + _xlpm.adjustment)), _xlpm.result ),IF(ISBLANK(Y28),"","Hidden"))} | AA28: Mega Charizard Y | AB28: Mega Form Y | AC28: Sky Drop | AD28: =_xlfn.XLOOKUP(AC28,moves!A:A,moves!B:B) -> flying | AE28: =_xlfn.XLOOKUP(AC28,moves!A:A,moves!D:D) -> 3 | AF28: =_xlfn.XLOOKUP(AC28,moves!A:A,moves!E:E) -> The target (after being damaged by this move) and user receive the effect of PROTECT. The target cannot perform an action anymore this round. | AG28: 0 | AH28: 0 | AI28: =IF(ISNUMBER(SEARCH("Shiny ", AA28)), 1, 0) -> 0 | AJ28: strong | AL28: 0 | AM28: {=IF(AL28=1,1, IF(ISTEXT(AK28),1, IF(AO28>1,AM27, IF(AI28=1, IF(SUMPRODUCT((LEN($Y$2:$Y$4096)-LEN(SUBSTITUTE($Y$2:$Y$4096,AA28,"")))/LEN(AA28))>0,2,1), IF( SUMPRODUCT((LEN($Y$2:$Y$4096)-LEN(SUBSTITUTE($Y$2:$Y$4096,AA28,"")))/LEN(AA28)) - SUMPRODUCT((LEN($Y$2:$Y$4096)-LEN(SUBSTITUTE($Y$2:$Y$4096,"Alolan "&AA28,"")))/LEN("Alolan "&AA28)) - SUMPRODUCT((LEN($Y$2:$Y$4096)-LEN(SUBSTITUTE($Y$2:$Y$4096,"Galarian "&AA28,"")))/LEN("Galarian "&AA28)) - SUMPRODUCT((LEN($Y$2:$Y$4096)-LEN(SUBSTITUTE($Y$2:$Y$4096,"Hisuian "&AA28,"")))/LEN("Hisuian "&AA28)) - SUMPRODUCT((LEN($Y$2:$Y$4096)-LEN(SUBSTITUTE($Y$2:$Y$4096,"Paldean "&AA28,"")))/LEN("Paldean "&AA28)) >0,2,1) ))))} -> 2 | AN28: 0 | AO28: 3
A29: 6-gm | B29: Charizard | C29: Fire | D29: Flying | E29: 78 | F29: 130 | G29: 111 | H29: 130 | I29: 85 | J29: 100 | K29: Flame Pokémon | L29: blank | M29: Gigantamax | N29: 11.8 | O29: 9 | P29: -1 | Q29: 10 | R29: =MROUND(N29,1)+P29 -> 11 | S29: =MROUND(O29,1)+Q29 -> 19 | T29: =SUM(S29,R29) -> 30 | U29: Fire | V29: Dragon | W29: Flying | X29: Ground | Z29: {=IF(ISBLANK(AK29),_xlfn.LET( _xlpm.nameBeforeSlash, IF(ISNUMBER(SEARCH("/", Y29)), LEFT(Y29, SEARCH("/", Y29)-1), Y29), _xlpm.matchRow, IFERROR(MATCH(_xlpm.nameBeforeSlash, AA:AA, 0), ""), _xlpm.difference, IF(_xlpm.matchRow="", "", ABS((R29 + S29) - (INDEX(R:R, _xlpm.matchRow) + INDEX(S:S, _xlpm.matchRow)))), _xlpm.category, IF(_xlpm.matchRow="", "", INDEX(AJ:AJ, _xlpm.matchRow)), _xlpm.adjustment, IF(_xlpm.matchRow="", "", IF(_xlpm.category="weak", 2, IF(_xlpm.category="moderate", 4, IF(_xlpm.category="strong", 8, IF(_xlpm.category="legendary", _xlpm.difference + 12, IF(_xlpm.category="warp", _xlpm.difference + 12, 0)))))), _xlpm.result, IF(_xlpm.matchRow="", "", IF(_xlpm.category="legendary", _xlpm.adjustment, _xlpm.difference + _xlpm.adjustment)), _xlpm.result ),IF(ISBLANK(Y29),"","Hidden"))} | AA29: Gigantamax Charizard | AB29: Gigantamax Form | AC29: G-Max Wildfire | AD29: =_xlfn.XLOOKUP(AC29,moves!A:A,moves!B:B) -> fire | AE29: =_xlfn.XLOOKUP(AC29,moves!A:A,moves!D:D) -> 5 | AF29: =_xlfn.XLOOKUP(AC29,moves!A:A,moves!E:E) -> All opposing non Fire-type active Pokémon take 2 damage at the end of their turns. | AG29: 0 | AH29: 0 | AI29: =IF(ISNUMBER(SEARCH("Shiny ", AA29)), 1, 0) -> 0 | AJ29: strong | AL29: 0 | AM29: {=IF(AL29=1,1, IF(ISTEXT(AK29),1, IF(AO29>1,AM28, IF(AI29=1, IF(SUMPRODUCT((LEN($Y$2:$Y$4096)-LEN(SUBSTITUTE($Y$2:$Y$4096,AA29,"")))/LEN(AA29))>0,2,1), IF( SUMPRODUCT((LEN($Y$2:$Y$4096)-LEN(SUBSTITUTE($Y$2:$Y$4096,AA29,"")))/LEN(AA29)) - SUMPRODUCT((LEN($Y$2:$Y$4096)-LEN(SUBSTITUTE($Y$2:$Y$4096,"Alolan "&AA29,"")))/LEN("Alolan "&AA29)) - SUMPRODUCT((LEN($Y$2:$Y$4096)-LEN(SUBSTITUTE($Y$2:$Y$4096,"Galarian "&AA29,"")))/LEN("Galarian "&AA29)) - SUMPRODUCT((LEN($Y$2:$Y$4096)-LEN(SUBSTITUTE($Y$2:$Y$4096,"Hisuian "&AA29,"")))/LEN("Hisuian "&AA29)) - SUMPRODUCT((LEN($Y$2:$Y$4096)-LEN(SUBSTITUTE($Y$2:$Y$4096,"Paldean "&AA29,"")))/LEN("Paldean "&AA29)) >0,2,1) ))))} -> 2 | AN29: 0 | AO29: 4
A30: 6-shiny | B30: Charizard | C30: Fire | D30: Flying | E30: 78 | F30: 84 | G30: 78 | H30: 109 | I30: 85 | J30: 100 | K30: Flame Pokémon | L30: Mountain | M30: Warm | N30: 10.29 | O30: 8.01 | P30: 1 | Q30: 1 | R30: =MROUND(N30,1)+P30 -> 11 | S30: =MROUND(O30,1)+Q30 -> 9 | T30: =SUM(S30,R30) -> 20 | U30: Fire | V30: Flying | W30: Dragon | X30: Ground | Z30: {=IF(ISBLANK(AK30),_xlfn.LET( _xlpm.nameBeforeSlash, IF(ISNUMBER(SEARCH("/", Y30)), LEFT(Y30, SEARCH("/", Y30)-1), Y30), _xlpm.matchRow, IFERROR(MATCH(_xlpm.nameBeforeSlash, AA:AA, 0), ""), _xlpm.difference, IF(_xlpm.matchRow="", "", ABS((R30 + S30) - (INDEX(R:R, _xlpm.matchRow) + INDEX(S:S, _xlpm.matchRow)))), _xlpm.category, IF(_xlpm.matchRow="", "", INDEX(AJ:AJ, _xlpm.matchRow)), _xlpm.adjustment, IF(_xlpm.matchRow="", "", IF(_xlpm.category="weak", 2, IF(_xlpm.category="moderate", 4, IF(_xlpm.category="strong", 8, IF(_xlpm.category="legendary", _xlpm.difference + 12, IF(_xlpm.category="warp", _xlpm.difference + 12, 0)))))), _xlpm.result, IF(_xlpm.matchRow="", "", IF(_xlpm.category="legendary", _xlpm.adjustment, _xlpm.difference + _xlpm.adjustment)), _xlpm.result ),IF(ISBLANK(Y30),"","Hidden"))} | AA30: Shiny Charizard | AC30: Air Slash | AD30: =_xlfn.XLOOKUP(AC30,moves!A:A,moves!B:B) -> flying | AE30: =_xlfn.XLOOKUP(AC30,moves!A:A,moves!D:D) -> 4 | AF30: =_xlfn.XLOOKUP(AC30,moves!A:A,moves!E:E) -> Critical hits deal +1 damage. | AG30: 0 | AH30: 0 | AI30: =IF(ISNUMBER(SEARCH("Shiny ", AA30)), 1, 0) -> 1 | AJ30: strong | AL30: 0 | AM30: {=IF(AL30=1,1, IF(ISTEXT(AK30),1, IF(AO30>1,AM29, IF(AI30=1, IF(SUMPRODUCT((LEN($Y$2:$Y$4096)-LEN(SUBSTITUTE($Y$2:$Y$4096,AA30,"")))/LEN(AA30))>0,2,1), IF( SUMPRODUCT((LEN($Y$2:$Y$4096)-LEN(SUBSTITUTE($Y$2:$Y$4096,AA30,"")))/LEN(AA30)) - SUMPRODUCT((LEN($Y$2:$Y$4096)-LEN(SUBSTITUTE($Y$2:$Y$4096,"Alolan "&AA30,"")))/LEN("Alolan "&AA30)) - SUMPRODUCT((LEN($Y$2:$Y$4096)-LEN(SUBSTITUTE($Y$2:$Y$4096,"Galarian "&AA30,"")))/LEN("Galarian "&AA30)) - SUMPRODUCT((LEN($Y$2:$Y$4096)-LEN(SUBSTITUTE($Y$2:$Y$4096,"Hisuian "&AA30,"")))/LEN("Hisuian "&AA30)) - SUMPRODUCT((LEN($Y$2:$Y$4096)-LEN(SUBSTITUTE($Y$2:$Y$4096,"Paldean "&AA30,"")))/LEN("Paldean "&AA30)) >0,2,1) ))))} -> 2 | AN30: 0 | AO30: 1
A31: 6-mx-shiny | B31: Charizard | C31: Fire | D31: Dragon | E31: 78 | F31: 130 | G31: 111 | H31: 130 | I31: 85 | J31: 100 | K31: Flame Pokémon | L31: blank | M31: Mega | N31: 11.8 | O31: 9 | P31: 1 | Q31: 2 | R31: =MROUND(N31,1)+P31 -> 13 | S31: =MROUND(O31,1)+Q31 -> 11 | T31: =SUM(S31,R31) -> 24 | U31: Fire | V31: Dragon | W31: Flying | X31: Ground | Z31: {=IF(ISBLANK(AK31),_xlfn.LET( _xlpm.nameBeforeSlash, IF(ISNUMBER(SEARCH("/", Y31)), LEFT(Y31, SEARCH("/", Y31)-1), Y31), _xlpm.matchRow, IFERROR(MATCH(_xlpm.nameBeforeSlash, AA:AA, 0), ""), _xlpm.difference, IF(_xlpm.matchRow="", "", ABS((R31 + S31) - (INDEX(R:R, _xlpm.matchRow) + INDEX(S:S, _xlpm.matchRow)))), _xlpm.category, IF(_xlpm.matchRow="", "", INDEX(AJ:AJ, _xlpm.matchRow)), _xlpm.adjustment, IF(_xlpm.matchRow="", "", IF(_xlpm.category="weak", 2, IF(_xlpm.category="moderate", 4, IF(_xlpm.category="strong", 8, IF(_xlpm.category="legendary", _xlpm.difference + 12, IF(_xlpm.category="warp", _xlpm.difference + 12, 0)))))), _xlpm.result, IF(_xlpm.matchRow="", "", IF(_xlpm.category="legendary", _xlpm.adjustment, _xlpm.difference + _xlpm.adjustment)), _xlpm.result ),IF(ISBLANK(Y31),"","Hidden"))} | AA31: Shiny Mega Charizard X | AB31: Mega Form X | AC31: Wild Blaze | AD31: =_xlfn.XLOOKUP(AC31,moves!A:A,moves!B:B) -> fire | AE31: =_xlfn.XLOOKUP(AC31,moves!A:A,moves!D:D) -> 8 | AF31: =_xlfn.XLOOKUP(AC31,moves!A:A,moves!E:E) -> You may discard a battle card. If you do not: This move gains RECHARGE 5 this turn. | AG31: 0 | AH31: 0 | AI31: =IF(ISNUMBER(SEARCH("Shiny ", AA31)), 1, 0) -> 1 | AJ31: strong | AL31: 0 | AM31: {=IF(AL31=1,1, IF(ISTEXT(AK31),1, IF(AO31>1,AM30, IF(AI31=1, IF(SUMPRODUCT((LEN($Y$2:$Y$4096)-LEN(SUBSTITUTE($Y$2:$Y$4096,AA31,"")))/LEN(AA31))>0,2,1), IF( SUMPRODUCT((LEN($Y$2:$Y$4096)-LEN(SUBSTITUTE($Y$2:$Y$4096,AA31,"")))/LEN(AA31)) - SUMPRODUCT((LEN($Y$2:$Y$4096)-LEN(SUBSTITUTE($Y$2:$Y$4096,"Alolan "&AA31,"")))/LEN("Alolan "&AA31)) - SUMPRODUCT((LEN($Y$2:$Y$4096)-LEN(SUBSTITUTE($Y$2:$Y$4096,"Galarian "&AA31,"")))/LEN("Galarian "&AA31)) - SUMPRODUCT((LEN($Y$2:$Y$4096)-LEN(SUBSTITUTE($Y$2:$Y$4096,"Hisuian "&AA31,"")))/LEN("Hisuian "&AA31)) - SUMPRODUCT((LEN($Y$2:$Y$4096)-LEN(SUBSTITUTE($Y$2:$Y$4096,"Paldean "&AA31,"")))/LEN("Paldean "&AA31)) >0,2,1) ))))} -> 2 | AN31: 0 | AO31: 2
A32: 6-my-shiny | B32: Charizard | C32: Fire | D32: Flying | E32: 78 | F32: 104 | G32: 78 | H32: 159 | I32: 115 | J32: 100 | K32: Flame Pokémon | L32: blank | M32: Mega | N32: 12.99 | O32: 8.91 | P32: 1 | Q32: 1 | R32: =MROUND(N32,1)+P32 -> 14 | S32: =MROUND(O32,1)+Q32 -> 10 | T32: =SUM(S32,R32) -> 24 | U32: Fire | V32: Flying | W32: Dragon | X32: Ground | Z32: {=IF(ISBLANK(AK32),_xlfn.LET( _xlpm.nameBeforeSlash, IF(ISNUMBER(SEARCH("/", Y32)), LEFT(Y32, SEARCH("/", Y32)-1), Y32), _xlpm.matchRow, IFERROR(MATCH(_xlpm.nameBeforeSlash, AA:AA, 0), ""), _xlpm.difference, IF(_xlpm.matchRow="", "", ABS((R32 + S32) - (INDEX(R:R, _xlpm.matchRow) + INDEX(S:S, _xlpm.matchRow)))), _xlpm.category, IF(_xlpm.matchRow="", "", INDEX(AJ:AJ, _xlpm.matchRow)), _xlpm.adjustment, IF(_xlpm.matchRow="", "", IF(_xlpm.category="weak", 2, IF(_xlpm.category="moderate", 4, IF(_xlpm.category="strong", 8, IF(_xlpm.category="legendary", _xlpm.difference + 12, IF(_xlpm.category="warp", _xlpm.difference + 12, 0)))))), _xlpm.result, IF(_xlpm.matchRow="", "", IF(_xlpm.category="legendary", _xlpm.adjustment, _xlpm.difference + _xlpm.adjustment)), _xlpm.result ),IF(ISBLANK(Y32),"","Hidden"))} | AA32: Shiny Mega Charizard Y | AB32: Mega Form Y | AC32: Crimson Dive | AD32: =_xlfn.XLOOKUP(AC32,moves!A:A,moves!B:B) -> fire | AE32: =_xlfn.XLOOKUP(AC32,moves!A:A,moves!D:D) -> 8 | AF32: =_xlfn.XLOOKUP(AC32,moves!A:A,moves!E:E) -> The user takes damage equal to 1/3 of its base health, rounded up. | AG32: 0 | AH32: 0 | AI32: =IF(ISNUMBER(SEARCH("Shiny ", AA32)), 1, 0) -> 1 | AJ32: strong | AL32: 0 | AM32: {=IF(AL32=1,1, IF(ISTEXT(AK32),1, IF(AO32>1,AM31, IF(AI32=1, IF(SUMPRODUCT((LEN($Y$2:$Y$4096)-LEN(SUBSTITUTE($Y$2:$Y$4096,AA32,"")))/LEN(AA32))>0,2,1), IF( SUMPRODUCT((LEN($Y$2:$Y$4096)-LEN(SUBSTITUTE($Y$2:$Y$4096,AA32,"")))/LEN(AA32)) - SUMPRODUCT((LEN($Y$2:$Y$4096)-LEN(SUBSTITUTE($Y$2:$Y$4096,"Alolan "&AA32,"")))/LEN("Alolan "&AA32)) - SUMPRODUCT((LEN($Y$2:$Y$4096)-LEN(SUBSTITUTE($Y$2:$Y$4096,"Galarian "&AA32,"")))/LEN("Galarian "&AA32)) - SUMPRODUCT((LEN($Y$2:$Y$4096)-LEN(SUBSTITUTE($Y$2:$Y$4096,"Hisuian "&AA32,"")))/LEN("Hisuian "&AA32)) - SUMPRODUCT((LEN($Y$2:$Y$4096)-LEN(SUBSTITUTE($Y$2:$Y$4096,"Paldean "&AA32,"")))/LEN("Paldean "&AA32)) >0,2,1) ))))} -> 2 | AN32: 0 | AO32: 3
A33: 6-gm-shiny | B33: Charizard | C33: Fire | D33: Flying | E33: 78 | F33: 130 | G33: 111 | H33: 130 | I33: 85 | J33: 100 | K33: Flame Pokémon | L33: blank | M33: Gigantamax | N33: 11.8 | O33: 9 | P33: -1 | Q33: 10 | R33: =MROUND(N33,1)+P33 -> 11 | S33: =MROUND(O33,1)+Q33 -> 19 | T33: =SUM(S33,R33) -> 30 | U33: Fire | V33: Dragon | W33: Flying | X33: Ground | Z33: {=IF(ISBLANK(AK33),_xlfn.LET( _xlpm.nameBeforeSlash, IF(ISNUMBER(SEARCH("/", Y33)), LEFT(Y33, SEARCH("/", Y33)-1), Y33), _xlpm.matchRow, IFERROR(MATCH(_xlpm.nameBeforeSlash, AA:AA, 0), ""), _xlpm.difference, IF(_xlpm.matchRow="", "", ABS((R33 + S33) - (INDEX(R:R, _xlpm.matchRow) + INDEX(S:S, _xlpm.matchRow)))), _xlpm.category, IF(_xlpm.matchRow="", "", INDEX(AJ:AJ, _xlpm.matchRow)), _xlpm.adjustment, IF(_xlpm.matchRow="", "", IF(_xlpm.category="weak", 2, IF(_xlpm.category="moderate", 4, IF(_xlpm.category="strong", 8, IF(_xlpm.category="legendary", _xlpm.difference + 12, IF(_xlpm.category="warp", _xlpm.difference + 12, 0)))))), _xlpm.result, IF(_xlpm.matchRow="", "", IF(_xlpm.category="legendary", _xlpm.adjustment, _xlpm.difference + _xlpm.adjustment)), _xlpm.result ),IF(ISBLANK(Y33),"","Hidden"))} | AA33: Shiny Gigantamax Charizard | AB33: Gigantamax Form | AC33: G-Max Blaze | AD33: =_xlfn.XLOOKUP(AC33,moves!A:A,moves!B:B) -> fire | AE33: =_xlfn.XLOOKUP(AC33,moves!A:A,moves!D:D) -> 5 | AF33: =_xlfn.XLOOKUP(AC33,moves!A:A,moves!E:E) -> Inflict the Burned Status on all opposing active Pokémon. | AG33: 0 | AH33: 0 | AI33: =IF(ISNUMBER(SEARCH("Shiny ", AA33)), 1, 0) -> 1 | AJ33: strong | AL33: 0 | AM33: {=IF(AL33=1,1, IF(ISTEXT(AK33),1, IF(AO33>1,AM32, IF(AI33=1, IF(SUMPRODUCT((LEN($Y$2:$Y$4096)-LEN(SUBSTITUTE($Y$2:$Y$4096,AA33,"")))/LEN(AA33))>0,2,1), IF( SUMPRODUCT((LEN($Y$2:$Y$4096)-LEN(SUBSTITUTE($Y$2:$Y$4096,AA33,"")))/LEN(AA33)) - SUMPRODUCT((LEN($Y$2:$Y$4096)-LEN(SUBSTITUTE($Y$2:$Y$4096,"Alolan "&AA33,"")))/LEN("Alolan "&AA33)) - SUMPRODUCT((LEN($Y$2:$Y$4096)-LEN(SUBSTITUTE($Y$2:$Y$4096,"Galarian "&AA33,"")))/LEN("Galarian "&AA33)) - SUMPRODUCT((LEN($Y$2:$Y$4096)-LEN(SUBSTITUTE($Y$2:$Y$4096,"Hisuian "&AA33,"")))/LEN("Hisuian "&AA33)) - SUMPRODUCT((LEN($Y$2:$Y$4096)-LEN(SUBSTITUTE($Y$2:$Y$4096,"Paldean "&AA33,"")))/LEN("Paldean "&AA33)) >0,2,1) ))))} -> 2 | AN33: 0 | AO33: 4
A34: 7 | B34: Squirtle | C34: Water | E34: 44 | F34: 48 | G34: 65 | H34: 60 | I34: 54 | J34: 43 | K34: Tiny Turtle Pokémon | L34: Ocean | M34: Temperate | N34: 5.2 | O34: 5.33 | R34: =MROUND(N34,1)+P34 -> 5 | S34: =MROUND(O34,1)+Q34 -> 5 | T34: =SUM(S34,R34) -> 10 | U34: Water | V34: Dark | W34: Ice | X34: Fighting | Y34: Wartortle | Z34: {=IF(ISBLANK(AK34),_xlfn.LET( _xlpm.nameBeforeSlash, IF(ISNUMBER(SEARCH("/", Y34)), LEFT(Y34, SEARCH("/", Y34)-1), Y34), _xlpm.matchRow, IFERROR(MATCH(_xlpm.nameBeforeSlash, AA:AA, 0), ""), _xlpm.difference, IF(_xlpm.matchRow="", "", ABS((R34 + S34) - (INDEX(R:R, _xlpm.matchRow) + INDEX(S:S, _xlpm.matchRow)))), _xlpm.category, IF(_xlpm.matchRow="", "", INDEX(AJ:AJ, _xlpm.matchRow)), _xlpm.adjustment, IF(_xlpm.matchRow="", "", IF(_xlpm.category="weak", 2, IF(_xlpm.category="moderate", 4, IF(_xlpm.category="strong", 8, IF(_xlpm.category="legendary", _xlpm.difference + 12, IF(_xlpm.category="warp", _xlpm.difference + 12, 0)))))), _xlpm.result, IF(_xlpm.matchRow="", "", IF(_xlpm.category="legendary", _xlpm.adjustment, _xlpm.difference + _xlpm.adjustment)), _xlpm.result ),IF(ISBLANK(Y34),"","Hidden"))} -> 8 | AA34: Squirtle | AC34: Withdraw | AD34: =_xlfn.XLOOKUP(AC34,moves!A:A,moves!B:B) -> water | AE34: =_xlfn.XLOOKUP(AC34,moves!A:A,moves!D:D) -> 1 | AF34: =_xlfn.XLOOKUP(AC34,moves!A:A,moves!E:E) -> Each time this move is used: Remove 1 regular hit from incoming attack rolls. | AG34: 1 | AH34: 0 | AI34: =IF(ISNUMBER(SEARCH("Shiny ", AA34)), 1, 0) -> 0 | AJ34: starter | AL34: 0 | AM34: {=IF(AL34=1,1, IF(ISTEXT(AK34),1, IF(AO34>1,AM33, IF(AI34=1, IF(SUMPRODUCT((LEN($Y$2:$Y$4096)-LEN(SUBSTITUTE($Y$2:$Y$4096,AA34,"")))/LEN(AA34))>0,2,1), IF( SUMPRODUCT((LEN($Y$2:$Y$4096)-LEN(SUBSTITUTE($Y$2:$Y$4096,AA34,"")))/LEN(AA34)) - SUMPRODUCT((LEN($Y$2:$Y$4096)-LEN(SUBSTITUTE($Y$2:$Y$4096,"Alolan "&AA34,"")))/LEN("Alolan "&AA34)) - SUMPRODUCT((LEN($Y$2:$Y$4096)-LEN(SUBSTITUTE($Y$2:$Y$4096,"Galarian "&AA34,"")))/LEN("Galarian "&AA34)) - SUMPRODUCT((LEN($Y$2:$Y$4096)-LEN(SUBSTITUTE($Y$2:$Y$4096,"Hisuian "&AA34,"")))/LEN("Hisuian "&AA34)) - SUMPRODUCT((LEN($Y$2:$Y$4096)-LEN(SUBSTITUTE($Y$2:$Y$4096,"Paldean "&AA34,"")))/LEN("Paldean "&AA34)) >0,2,1) ))))} -> 1 | AN34: 0 | AO34: 0
A35: 7-shiny | B35: Squirtle | C35: Water | E35: 44 | F35: 48 | G35: 65 | H35: 60 | I35: 54 | J35: 43 | K35: Tiny Turtle Pokémon | L35: Ocean | M35: Temperate | N35: 5.2 | O35: 5.33 | R35: =MROUND(N35,1)+P35 -> 5 | S35: =MROUND(O35,1)+Q35 -> 5 | T35: =SUM(S35,R35) -> 10 | U35: Water | V35: Dark | W35: Ice | X35: Fighting | Y35: Shiny Wartortle | Z35: {=IF(ISBLANK(AK35),_xlfn.LET( _xlpm.nameBeforeSlash, IF(ISNUMBER(SEARCH("/", Y35)), LEFT(Y35, SEARCH("/", Y35)-1), Y35), _xlpm.matchRow, IFERROR(MATCH(_xlpm.nameBeforeSlash, AA:AA, 0), ""), _xlpm.difference, IF(_xlpm.matchRow="", "", ABS((R35 + S35) - (INDEX(R:R, _xlpm.matchRow) + INDEX(S:S, _xlpm.matchRow)))), _xlpm.category, IF(_xlpm.matchRow="", "", INDEX(AJ:AJ, _xlpm.matchRow)), _xlpm.adjustment, IF(_xlpm.matchRow="", "", IF(_xlpm.category="weak", 2, IF(_xlpm.category="moderate", 4, IF(_xlpm.category="strong", 8, IF(_xlpm.category="legendary", _xlpm.difference + 12, IF(_xlpm.category="warp", _xlpm.difference + 12, 0)))))), _xlpm.result, IF(_xlpm.matchRow="", "", IF(_xlpm.category="legendary", _xlpm.adjustment, _xlpm.difference + _xlpm.adjustment)), _xlpm.result ),IF(ISBLANK(Y35),"","Hidden"))} -> 8 | AA35: Shiny Squirtle | AC35: Water Gun | AD35: =_xlfn.XLOOKUP(AC35,moves!A:A,moves!B:B) -> water | AE35: =_xlfn.XLOOKUP(AC35,moves!A:A,moves!D:D) -> 2 | AF35: =_xlfn.XLOOKUP(AC35,moves!A:A,moves!E:E) -> When the target next attacks: Remove 1 regular hit from the roll. | AG35: 1 | AH35: 0 | AI35: =IF(ISNUMBER(SEARCH("Shiny ", AA35)), 1, 0) -> 1 | AJ35: weak | AL35: 0 | AM35: {=IF(AL35=1,1, IF(ISTEXT(AK35),1, IF(AO35>1,AM34, IF(AI35=1, IF(SUMPRODUCT((LEN($Y$2:$Y$4096)-LEN(SUBSTITUTE($Y$2:$Y$4096,AA35,"")))/LEN(AA35))>0,2,1), IF( SUMPRODUCT((LEN($Y$2:$Y$4096)-LEN(SUBSTITUTE($Y$2:$Y$4096,AA35,"")))/LEN(AA35)) - SUMPRODUCT((LEN($Y$2:$Y$4096)-LEN(SUBSTITUTE($Y$2:$Y$4096,"Alolan "&AA35,"")))/LEN("Alolan "&AA35)) - SUMPRODUCT((LEN($Y$2:$Y$4096)-LEN(SUBSTITUTE($Y$2:$Y$4096,"Galarian "&AA35,"")))/LEN("Galarian "&AA35)) - SUMPRODUCT((LEN($Y$2:$Y$4096)-LEN(SUBSTITUTE($Y$2:$Y$4096,"Hisuian "&AA35,"")))/LEN("Hisuian "&AA35)) - SUMPRODUCT((LEN($Y$2:$Y$4096)-LEN(SUBSTITUTE($Y$2:$Y$4096,"Paldean "&AA35,"")))/LEN("Paldean "&AA35)) >0,2,1) ))))} -> 1 | AN35: 0 | AO35: 0
A36: 8 | B36: Wartortle | C36: Water | E36: 59 | F36: 63 | G36: 80 | H36: 65 | I36: 80 | J36: 58 | K36: Turtle Pokémon | L36: Ocean | M36: Temperate | N36: 6.2 | O36: 7.16 | Q36: 1 | R36: =MROUND(N36,1)+P36 -> 6 | S36: =MROUND(O36,1)+Q36 -> 8 | T36: =SUM(S36,R36) -> 14 | U36: Water | V36: Dark | W36: Ice | X36: Fighting | Y36: Blastoise | Z36: {=IF(ISBLANK(AK36),_xlfn.LET( _xlpm.nameBeforeSlash, IF(ISNUMBER(SEARCH("/", Y36)), LEFT(Y36, SEARCH("/", Y36)-1), Y36), _xlpm.matchRow, IFERROR(MATCH(_xlpm.nameBeforeSlash, AA:AA, 0), ""), _xlpm.difference, IF(_xlpm.matchRow="", "", ABS((R36 + S36) - (INDEX(R:R, _xlpm.matchRow) + INDEX(S:S, _xlpm.matchRow)))), _xlpm.category, IF(_xlpm.matchRow="", "", INDEX(AJ:AJ, _xlpm.matchRow)), _xlpm.adjustment, IF(_xlpm.matchRow="", "", IF(_xlpm.category="weak", 2, IF(_xlpm.category="moderate", 4, IF(_xlpm.category="strong", 8, IF(_xlpm.category="legendary", _xlpm.difference + 12, IF(_xlpm.category="warp", _xlpm.difference + 12, 0)))))), _xlpm.result, IF(_xlpm.matchRow="", "", IF(_xlpm.category="legendary", _xlpm.adjustment, _xlpm.difference + _xlpm.adjustment)), _xlpm.result ),IF(ISBLANK(Y36),"","Hidden"))} -> 14 | AA36: Wartortle | AC36: Bite | AD36: =_xlfn.XLOOKUP(AC36,moves!A:A,moves!B:B) -> dark | AE36: =_xlfn.XLOOKUP(AC36,moves!A:A,moves!D:D) -> 3 | AF36: =_xlfn.XLOOKUP(AC36,moves!A:A,moves!E:E) -> When the target is next attacked: Add 1 regular hit to the roll. | AG36: 0 | AH36: 0 | AI36: =IF(ISNUMBER(SEARCH("Shiny ", AA36)), 1, 0) -> 0 | AJ36: moderate | AL36: 0 | AM36: {=IF(AL36=1,1, IF(ISTEXT(AK36),1, IF(AO36>1,AM35, IF(AI36=1, IF(SUMPRODUCT((LEN($Y$2:$Y$4096)-LEN(SUBSTITUTE($Y$2:$Y$4096,AA36,"")))/LEN(AA36))>0,2,1), IF( SUMPRODUCT((LEN($Y$2:$Y$4096)-LEN(SUBSTITUTE($Y$2:$Y$4096,AA36,"")))/LEN(AA36)) - SUMPRODUCT((LEN($Y$2:$Y$4096)-LEN(SUBSTITUTE($Y$2:$Y$4096,"Alolan "&AA36,"")))/LEN("Alolan "&AA36)) - SUMPRODUCT((LEN($Y$2:$Y$4096)-LEN(SUBSTITUTE($Y$2:$Y$4096,"Galarian "&AA36,"")))/LEN("Galarian "&AA36)) - SUMPRODUCT((LEN($Y$2:$Y$4096)-LEN(SUBSTITUTE($Y$2:$Y$4096,"Hisuian "&AA36,"")))/LEN("Hisuian "&AA36)) - SUMPRODUCT((LEN($Y$2:$Y$4096)-LEN(SUBSTITUTE($Y$2:$Y$4096,"Paldean "&AA36,"")))/LEN("Paldean "&AA36)) >0,2,1) ))))} -> 2 | AN36: 0 | AO36: 0
A37: 8-shiny | B37: Wartortle | C37: Water | E37: 59 | F37: 63 | G37: 80 | H37: 65 | I37: 80 | J37: 58 | K37: Turtle Pokémon | L37: Ocean | M37: Temperate | N37: 6.2 | O37: 7.16 | Q37: 1 | R37: =MROUND(N37,1)+P37 -> 6 | S37: =MROUND(O37,1)+Q37 -> 8 | T37: =SUM(S37,R37) -> 14 | U37: Water | V37: Dark | W37: Ice | X37: Fighting | Y37: Shiny Blastoise | Z37: {=IF(ISBLANK(AK37),_xlfn.LET( _xlpm.nameBeforeSlash, IF(ISNUMBER(SEARCH("/", Y37)), LEFT(Y37, SEARCH("/", Y37)-1), Y37), _xlpm.matchRow, IFERROR(MATCH(_xlpm.nameBeforeSlash, AA:AA, 0), ""), _xlpm.difference, IF(_xlpm.matchRow="", "", ABS((R37 + S37) - (INDEX(R:R, _xlpm.matchRow) + INDEX(S:S, _xlpm.matchRow)))), _xlpm.category, IF(_xlpm.matchRow="", "", INDEX(AJ:AJ, _xlpm.matchRow)), _xlpm.adjustment, IF(_xlpm.matchRow="", "", IF(_xlpm.category="weak", 2, IF(_xlpm.category="moderate", 4, IF(_xlpm.category="strong", 8, IF(_xlpm.category="legendary", _xlpm.difference + 12, IF(_xlpm.category="warp", _xlpm.difference + 12, 0)))))), _xlpm.result, IF(_xlpm.matchRow="", "", IF(_xlpm.category="legendary", _xlpm.adjustment, _xlpm.difference + _xlpm.adjustment)), _xlpm.result ),IF(ISBLANK(Y37),"","Hidden"))} -> 14 | AA37: Shiny Wartortle | AC37: Water Pulse | AD37: =_xlfn.XLOOKUP(AC37,moves!A:A,moves!B:B) -> water | AE37: =_xlfn.XLOOKUP(AC37,moves!A:A,moves!D:D) -> 3 | AF37: =_xlfn.XLOOKUP(AC37,moves!A:A,moves!E:E) -> If any status symbols are rolled: Inflict the Confused status on the target. | AG37: 0 | AH37: 0 | AI37: =IF(ISNUMBER(SEARCH("Shiny ", AA37)), 1, 0) -> 1 | AJ37: moderate | AL37: 0 | AM37: {=IF(AL37=1,1, IF(ISTEXT(AK37),1, IF(AO37>1,AM36, IF(AI37=1, IF(SUMPRODUCT((LEN($Y$2:$Y$4096)-LEN(SUBSTITUTE($Y$2:$Y$4096,AA37,"")))/LEN(AA37))>0,2,1), IF( SUMPRODUCT((LEN($Y$2:$Y$4096)-LEN(SUBSTITUTE($Y$2:$Y$4096,AA37,"")))/LEN(AA37)) - SUMPRODUCT((LEN($Y$2:$Y$4096)-LEN(SUBSTITUTE($Y$2:$Y$4096,"Alolan "&AA37,"")))/LEN("Alolan "&AA37)) - SUMPRODUCT((LEN($Y$2:$Y$4096)-LEN(SUBSTITUTE($Y$2:$Y$4096,"Galarian "&AA37,"")))/LEN("Galarian "&AA37)) - SUMPRODUCT((LEN($Y$2:$Y$4096)-LEN(SUBSTITUTE($Y$2:$Y$4096,"Hisuian "&AA37,"")))/LEN("Hisuian "&AA37)) - SUMPRODUCT((LEN($Y$2:$Y$4096)-LEN(SUBSTITUTE($Y$2:$Y$4096,"Paldean "&AA37,"")))/LEN("Paldean "&AA37)) >0,2,1) ))))} -> 2 | AN37: 0 | AO37: 0
A38: 9 | B38: Blastoise | C38: Water | E38: 79 | F38: 83 | G38: 100 | H38: 85 | I38: 105 | J38: 78 | K38: Shellfish Pokémon | L38: Ocean | M38: Temperate | N38: 8.2 | O38: 9.31 | Q38: 3 | R38: =MROUND(N38,1)+P38 -> 8 | S38: =MROUND(O38,1)+Q38 -> 12 | T38: =SUM(S38,R38) -> 20 | U38: Water | V38: Dark | W38: Ice | X38: Fighting | Z38: {=IF(ISBLANK(AK38),_xlfn.LET( _xlpm.nameBeforeSlash, IF(ISNUMBER(SEARCH("/", Y38)), LEFT(Y38, SEARCH("/", Y38)-1), Y38), _xlpm.matchRow, IFERROR(MATCH(_xlpm.nameBeforeSlash, AA:AA, 0), ""), _xlpm.difference, IF(_xlpm.matchRow="", "", ABS((R38 + S38) - (INDEX(R:R, _xlpm.matchRow) + INDEX(S:S, _xlpm.matchRow)))), _xlpm.category, IF(_xlpm.matchRow="", "", INDEX(AJ:AJ, _xlpm.matchRow)), _xlpm.adjustment, IF(_xlpm.matchRow="", "", IF(_xlpm.category="weak", 2, IF(_xlpm.category="moderate", 4, IF(_xlpm.category="strong", 8, IF(_xlpm.category="legendary", _xlpm.difference + 12, IF(_xlpm.category="warp", _xlpm.difference + 12, 0)))))), _xlpm.result, IF(_xlpm.matchRow="", "", IF(_xlpm.category="legendary", _xlpm.adjustment, _xlpm.difference + _xlpm.adjustment)), _xlpm.result ),IF(ISBLANK(Y38),"","Hidden"))} | AA38: Blastoise | AC38: Hydro Pump | AD38: =_xlfn.XLOOKUP(AC38,moves!A:A,moves!B:B) -> water | AE38: =_xlfn.XLOOKUP(AC38,moves!A:A,moves!D:D) -> 5 | AF38: =_xlfn.XLOOKUP(AC38,moves!A:A,moves!E:E) -> If 2 or more status symbols are rolled: Inflict the Confused status on the target. | AG38: 0 | AH38: 0 | AI38: =IF(ISNUMBER(SEARCH("Shiny ", AA38)), 1, 0) -> 0 | AJ38: strong | AL38: 0 | AM38: {=IF(AL38=1,1, IF(ISTEXT(AK38),1, IF(AO38>1,AM37, IF(AI38=1, IF(SUMPRODUCT((LEN($Y$2:$Y$4096)-LEN(SUBSTITUTE($Y$2:$Y$4096,AA38,"")))/LEN(AA38))>0,2,1), IF( SUMPRODUCT((LEN($Y$2:$Y$4096)-LEN(SUBSTITUTE($Y$2:$Y$4096,AA38,"")))/LEN(AA38)) - SUMPRODUCT((LEN($Y$2:$Y$4096)-LEN(SUBSTITUTE($Y$2:$Y$4096,"Alolan "&AA38,"")))/LEN("Alolan "&AA38)) - SUMPRODUCT((LEN($Y$2:$Y$4096)-LEN(SUBSTITUTE($Y$2:$Y$4096,"Galarian "&AA38,"")))/LEN("Galarian "&AA38)) - SUMPRODUCT((LEN($Y$2:$Y$4096)-LEN(SUBSTITUTE($Y$2:$Y$4096,"Hisuian "&AA38,"")))/LEN("Hisuian "&AA38)) - SUMPRODUCT((LEN($Y$2:$Y$4096)-LEN(SUBSTITUTE($Y$2:$Y$4096,"Paldean "&AA38,"")))/LEN("Paldean "&AA38)) >0,2,1) ))))} -> 2 | AN38: 0 | AO38: 1
A39: 9-m | B39: Blastoise | C39: Water | E39: 79 | F39: 103 | G39: 120 | H39: 135 | I39: 115 | J39: 78 | K39: Shellfish Pokémon | L39: blank | M39: Mega | N39: 10.9 | O39: 10.21 | P39: 1 | Q39: 2 | R39: =MROUND(N39,1)+P39 -> 12 | S39: =MROUND(O39,1)+Q39 -> 12 | T39: =SUM(S39,R39) -> 24 | U39: Water | V39: Dark | W39: Ice | X39: Fighting | Z39: {=IF(ISBLANK(AK39),_xlfn.LET( _xlpm.nameBeforeSlash, IF(ISNUMBER(SEARCH("/", Y39)), LEFT(Y39, SEARCH("/", Y39)-1), Y39), _xlpm.matchRow, IFERROR(MATCH(_xlpm.nameBeforeSlash, AA:AA, 0), ""), _xlpm.difference, IF(_xlpm.matchRow="", "", ABS((R39 + S39) - (INDEX(R:R, _xlpm.matchRow) + INDEX(S:S, _xlpm.matchRow)))), _xlpm.category, IF(_xlpm.matchRow="", "", INDEX(AJ:AJ, _xlpm.matchRow)), _xlpm.adjustment, IF(_xlpm.matchRow="", "", IF(_xlpm.category="weak", 2, IF(_xlpm.category="moderate", 4, IF(_xlpm.category="strong", 8, IF(_xlpm.category="legendary", _xlpm.difference + 12, IF(_xlpm.category="warp", _xlpm.difference + 12, 0)))))), _xlpm.result, IF(_xlpm.matchRow="", "", IF(_xlpm.category="legendary", _xlpm.adjustment, _xlpm.difference + _xlpm.adjustment)), _xlpm.result ),IF(ISBLANK(Y39),"","Hidden"))} | AA39: Mega Blastoise | AB39: Mega Form | AC39: Water Spout | AD39: =_xlfn.XLOOKUP(AC39,moves!A:A,moves!B:B) -> water | AE39: =_xlfn.XLOOKUP(AC39,moves!A:A,moves!D:D) -> ? | AF39: =_xlfn.XLOOKUP(AC39,moves!A:A,moves!E:E) -> Attack strength is equal to the current health of the user (Max 7 attack strength). | AG39: 0 | AH39: 0 | AI39: =IF(ISNUMBER(SEARCH("Shiny ", AA39)), 1, 0) -> 0 | AJ39: strong | AL39: 0 | AM39: {=IF(AL39=1,1, IF(ISTEXT(AK39),1, IF(AO39>1,AM38, IF(AI39=1, IF(SUMPRODUCT((LEN($Y$2:$Y$4096)-LEN(SUBSTITUTE($Y$2:$Y$4096,AA39,"")))/LEN(AA39))>0,2,1), IF( SUMPRODUCT((LEN($Y$2:$Y$4096)-LEN(SUBSTITUTE($Y$2:$Y$4096,AA39,"")))/LEN(AA39)) - SUMPRODUCT((LEN($Y$2:$Y$4096)-LEN(SUBSTITUTE($Y$2:$Y$4096,"Alolan "&AA39,"")))/LEN("Alolan "&AA39)) - SUMPRODUCT((LEN($Y$2:$Y$4096)-LEN(SUBSTITUTE($Y$2:$Y$4096,"Galarian "&AA39,"")))/LEN("Galarian "&AA39)) - SUMPRODUCT((LEN($Y$2:$Y$4096)-LEN(SUBSTITUTE($Y$2:$Y$4096,"Hisuian "&AA39,"")))/LEN("Hisuian "&AA39)) - SUMPRODUCT((LEN($Y$2:$Y$4096)-LEN(SUBSTITUTE($Y$2:$Y$4096,"Paldean "&AA39,"")))/LEN("Paldean "&AA39)) >0,2,1) ))))} -> 2 | AN39: 0 | AO39: 2
A40: 9-gm | B40: Blastoise | C40: Water | E40: 79 | F40: 103 | G40: 120 | H40: 135 | I40: 115 | J40: 78 | K40: Shellfish Pokémon | L40: blank | M40: Gigantamax | N40: 10.9 | O40: 10.21 | P40: -3 | Q40: 12 | R40: =MROUND(N40,1)+P40 -> 8 | S40: =MROUND(O40,1)+Q40 -> 22 | T40: =SUM(S40,R40) -> 30 | U40: Water | V40: Dark | W40: Ice | X40: Fighting | Z40: {=IF(ISBLANK(AK40),_xlfn.LET( _xlpm.nameBeforeSlash, IF(ISNUMBER(SEARCH("/", Y40)), LEFT(Y40, SEARCH("/", Y40)-1), Y40), _xlpm.matchRow, IFERROR(MATCH(_xlpm.nameBeforeSlash, AA:AA, 0), ""), _xlpm.difference, IF(_xlpm.matchRow="", "", ABS((R40 + S40) - (INDEX(R:R, _xlpm.matchRow) + INDEX(S:S, _xlpm.matchRow)))), _xlpm.category, IF(_xlpm.matchRow="", "", INDEX(AJ:AJ, _xlpm.matchRow)), _xlpm.adjustment, IF(_xlpm.matchRow="", "", IF(_xlpm.category="weak", 2, IF(_xlpm.category="moderate", 4, IF(_xlpm.category="strong", 8, IF(_xlpm.category="legendary", _xlpm.difference + 12, IF(_xlpm.category="warp", _xlpm.difference + 12, 0)))))), _xlpm.result, IF(_xlpm.matchRow="", "", IF(_xlpm.category="legendary", _xlpm.adjustment, _xlpm.difference + _xlpm.adjustment)), _xlpm.result ),IF(ISBLANK(Y40),"","Hidden"))} | AA40: Gigantamax Blastoise | AB40: Gigantamax Form | AC40: G-Max Cannonade | AD40: =_xlfn.XLOOKUP(AC40,moves!A:A,moves!B:B) -> water | AE40: =_xlfn.XLOOKUP(AC40,moves!A:A,moves!D:D) -> 5 | AF40: =_xlfn.XLOOKUP(AC40,moves!A:A,moves!E:E) -> All opposing non Water-type active Pokémon take 2 damage at the end of their turns. | AG40: 0 | AH40: 0 | AI40: =IF(ISNUMBER(SEARCH("Shiny ", AA40)), 1, 0) -> 0 | AJ40: strong | AL40: 0 | AM40: {=IF(AL40=1,1, IF(ISTEXT(AK40),1, IF(AO40>1,AM39, IF(AI40=1, IF(SUMPRODUCT((LEN($Y$2:$Y$4096)-LEN(SUBSTITUTE($Y$2:$Y$4096,AA40,"")))/LEN(AA40))>0,2,1), IF( SUMPRODUCT((LEN($Y$2:$Y$4096)-LEN(SUBSTITUTE($Y$2:$Y$4096,AA40,"")))/LEN(AA40)) - SUMPRODUCT((LEN($Y$2:$Y$4096)-LEN(SUBSTITUTE($Y$2:$Y$4096,"Alolan "&AA40,"")))/LEN("Alolan "&AA40)) - SUMPRODUCT((LEN($Y$2:$Y$4096)-LEN(SUBSTITUTE($Y$2:$Y$4096,"Galarian "&AA40,"")))/LEN("Galarian "&AA40)) - SUMPRODUCT((LEN($Y$2:$Y$4096)-LEN(SUBSTITUTE($Y$2:$Y$4096,"Hisuian "&AA40,"")))/LEN("Hisuian "&AA40)) - SUMPRODUCT((LEN($Y$2:$Y$4096)-LEN(SUBSTITUTE($Y$2:$Y$4096,"Paldean "&AA40,"")))/LEN("Paldean "&AA40)) >0,2,1) ))))} -> 2 | AN40: 0 | AO40: 3
A41: 9-shiny | B41: Blastoise | C41: Water | E41: 79 | F41: 83 | G41: 100 | H41: 85 | I41: 105 | J41: 78 | K41: Shellfish Pokémon | L41: Ocean | M41: Temperate | N41: 8.2 | O41: 9.31 | Q41: 3 | R41: =MROUND(N41,1)+P41 -> 8 | S41: =MROUND(O41,1)+Q41 -> 12 | T41: =SUM(S41,R41) -> 20 | U41: Water | V41: Dark | W41: Ice | X41: Fighting | Z41: {=IF(ISBLANK(AK41),_xlfn.LET( _xlpm.nameBeforeSlash, IF(ISNUMBER(SEARCH("/", Y41)), LEFT(Y41, SEARCH("/", Y41)-1), Y41), _xlpm.matchRow, IFERROR(MATCH(_xlpm.nameBeforeSlash, AA:AA, 0), ""), _xlpm.difference, IF(_xlpm.matchRow="", "", ABS((R41 + S41) - (INDEX(R:R, _xlpm.matchRow) + INDEX(S:S, _xlpm.matchRow)))), _xlpm.category, IF(_xlpm.matchRow="", "", INDEX(AJ:AJ, _xlpm.matchRow)), _xlpm.adjustment, IF(_xlpm.matchRow="", "", IF(_xlpm.category="weak", 2, IF(_xlpm.category="moderate", 4, IF(_xlpm.category="strong", 8, IF(_xlpm.category="legendary", _xlpm.difference + 12, IF(_xlpm.category="warp", _xlpm.difference + 12, 0)))))), _xlpm.result, IF(_xlpm.matchRow="", "", IF(_xlpm.category="legendary", _xlpm.adjustment, _xlpm.difference + _xlpm.adjustment)), _xlpm.result ),IF(ISBLANK(Y41),"","Hidden"))} | AA41: Shiny Blastoise | AC41: Twin Cannon | AD41: =_xlfn.XLOOKUP(AC41,moves!A:A,moves!B:B) -> water | AE41: =_xlfn.XLOOKUP(AC41,moves!A:A,moves!D:D) -> 5 | AF41: =_xlfn.XLOOKUP(AC41,moves!A:A,moves!E:E) -> The user may consume a Tier 3 Apricorn. If so: This move gains MULTI this turn. | AG41: 0 | AH41: 0 | AI41: =IF(ISNUMBER(SEARCH("Shiny ", AA41)), 1, 0) -> 1 | AJ41: strong | AL41: 0 | AM41: {=IF(AL41=1,1, IF(ISTEXT(AK41),1, IF(AO41>1,AM40, IF(AI41=1, IF(SUMPRODUCT((LEN($Y$2:$Y$4096)-LEN(SUBSTITUTE($Y$2:$Y$4096,AA41,"")))/LEN(AA41))>0,2,1), IF( SUMPRODUCT((LEN($Y$2:$Y$4096)-LEN(SUBSTITUTE($Y$2:$Y$4096,AA41,"")))/LEN(AA41)) - SUMPRODUCT((LEN($Y$2:$Y$4096)-LEN(SUBSTITUTE($Y$2:$Y$4096,"Alolan "&AA41,"")))/LEN("Alolan "&AA41)) - SUMPRODUCT((LEN($Y$2:$Y$4096)-LEN(SUBSTITUTE($Y$2:$Y$4096,"Galarian "&AA41,"")))/LEN("Galarian "&AA41)) - SUMPRODUCT((LEN($Y$2:$Y$4096)-LEN(SUBSTITUTE($Y$2:$Y$4096,"Hisuian "&AA41,"")))/LEN("Hisuian "&AA41)) - SUMPRODUCT((LEN($Y$2:$Y$4096)-LEN(SUBSTITUTE($Y$2:$Y$4096,"Paldean "&AA41,"")))/LEN("Paldean "&AA41)) >0,2,1) ))))} -> 2 | AN41: 0 | AO41: 1
A42: 9-m-shiny | B42: Blastoise | C42: Water | E42: 79 | F42: 103 | G42: 120 | H42: 135 | I42: 115 | J42: 78 | K42: Shellfish Pokémon | L42: blank | M42: Mega | N42: 10.9 | O42: 10.21 | P42: 1 | Q42: 2 | R42: =MROUND(N42,1)+P42 -> 12 | S42: =MROUND(O42,1)+Q42 -> 12 | T42: =SUM(S42,R42) -> 24 | U42: Water | V42: Dark | W42: Ice | X42: Fighting | Z42: {=IF(ISBLANK(AK42),_xlfn.LET( _xlpm.nameBeforeSlash, IF(ISNUMBER(SEARCH("/", Y42)), LEFT(Y42, SEARCH("/", Y42)-1), Y42), _xlpm.matchRow, IFERROR(MATCH(_xlpm.nameBeforeSlash, AA:AA, 0), ""), _xlpm.difference, IF(_xlpm.matchRow="", "", ABS((R42 + S42) - (INDEX(R:R, _xlpm.matchRow) + INDEX(S:S, _xlpm.matchRow)))), _xlpm.category, IF(_xlpm.matchRow="", "", INDEX(AJ:AJ, _xlpm.matchRow)), _xlpm.adjustment, IF(_xlpm.matchRow="", "", IF(_xlpm.category="weak", 2, IF(_xlpm.category="moderate", 4, IF(_xlpm.category="strong", 8, IF(_xlpm.category="legendary", _xlpm.difference + 12, IF(_xlpm.category="warp", _xlpm.difference + 12, 0)))))), _xlpm.result, IF(_xlpm.matchRow="", "", IF(_xlpm.category="legendary", _xlpm.adjustment, _xlpm.difference + _xlpm.adjustment)), _xlpm.result ),IF(ISBLANK(Y42),"","Hidden"))} | AA42: Shiny Mega Blastoise | AB42: Mega Form | AC42: Hydro Bombard | AD42: =_xlfn.XLOOKUP(AC42,moves!A:A,moves!B:B) -> water | AE42: =_xlfn.XLOOKUP(AC42,moves!A:A,moves!D:D) -> 5 | AF42: =_xlfn.XLOOKUP(AC42,moves!A:A,moves!E:E) -> For each status symbol rolled: The user may deal 2 damage to one Pokémon in the target party other than the target, ignoring resistance and weakness. Each target must be different. | AG42: 0 | AH42: 0 | AI42: =IF(ISNUMBER(SEARCH("Shiny ", AA42)), 1, 0) -> 1 | AJ42: strong | AL42: 0 | AM42: {=IF(AL42=1,1, IF(ISTEXT(AK42),1, IF(AO42>1,AM41, IF(AI42=1, IF(SUMPRODUCT((LEN($Y$2:$Y$4096)-LEN(SUBSTITUTE($Y$2:$Y$4096,AA42,"")))/LEN(AA42))>0,2,1), IF( SUMPRODUCT((LEN($Y$2:$Y$4096)-LEN(SUBSTITUTE($Y$2:$Y$4096,AA42,"")))/LEN(AA42)) - SUMPRODUCT((LEN($Y$2:$Y$4096)-LEN(SUBSTITUTE($Y$2:$Y$4096,"Alolan "&AA42,"")))/LEN("Alolan "&AA42)) - SUMPRODUCT((LEN($Y$2:$Y$4096)-LEN(SUBSTITUTE($Y$2:$Y$4096,"Galarian "&AA42,"")))/LEN("Galarian "&AA42)) - SUMPRODUCT((LEN($Y$2:$Y$4096)-LEN(SUBSTITUTE($Y$2:$Y$4096,"Hisuian "&AA42,"")))/LEN("Hisuian "&AA42)) - SUMPRODUCT((LEN($Y$2:$Y$4096)-LEN(SUBSTITUTE($Y$2:$Y$4096,"Paldean "&AA42,"")))/LEN("Paldean "&AA42)) >0,2,1) ))))} -> 2 | AN42: 0 | AO42: 2
A43: 9-gm-shiny | B43: Blastoise | C43: Water | E43: 79 | F43: 103 | G43: 120 | H43: 135 | I43: 115 | J43: 78 | K43: Shellfish Pokémon | L43: blank | M43: Gigantamax | N43: 10.9 | O43: 10.21 | P43: -3 | Q43: 12 | R43: =MROUND(N43,1)+P43 -> 8 | S43: =MROUND(O43,1)+Q43 -> 22 | T43: =SUM(S43,R43) -> 30 | U43: Water | V43: Dark | W43: Ice | X43: Fighting | Z43: {=IF(ISBLANK(AK43),_xlfn.LET( _xlpm.nameBeforeSlash, IF(ISNUMBER(SEARCH("/", Y43)), LEFT(Y43, SEARCH("/", Y43)-1), Y43), _xlpm.matchRow, IFERROR(MATCH(_xlpm.nameBeforeSlash, AA:AA, 0), ""), _xlpm.difference, IF(_xlpm.matchRow="", "", ABS((R43 + S43) - (INDEX(R:R, _xlpm.matchRow) + INDEX(S:S, _xlpm.matchRow)))), _xlpm.category, IF(_xlpm.matchRow="", "", INDEX(AJ:AJ, _xlpm.matchRow)), _xlpm.adjustment, IF(_xlpm.matchRow="", "", IF(_xlpm.category="weak", 2, IF(_xlpm.category="moderate", 4, IF(_xlpm.category="strong", 8, IF(_xlpm.category="legendary", _xlpm.difference + 12, IF(_xlpm.category="warp", _xlpm.difference + 12, 0)))))), _xlpm.result, IF(_xlpm.matchRow="", "", IF(_xlpm.category="legendary", _xlpm.adjustment, _xlpm.difference + _xlpm.adjustment)), _xlpm.result ),IF(ISBLANK(Y43),"","Hidden"))} | AA43: Shiny Gigantamax Blastoise | AB43: Gigantamax Form | AC43: G-Max Bombard | AD43: =_xlfn.XLOOKUP(AC43,moves!A:A,moves!B:B) -> water | AE43: =_xlfn.XLOOKUP(AC43,moves!A:A,moves!D:D) -> 6 | AF43: =_xlfn.XLOOKUP(AC43,moves!A:A,moves!E:E) -> For each status symbol rolled: The user may deal 2 damage to one Pokémon in the target party other than the target, ignoring resistance and weakness. Each target must be different. | AG43: 0 | AH43: 0 | AI43: =IF(ISNUMBER(SEARCH("Shiny ", AA43)), 1, 0) -> 1 | AJ43: strong | AL43: 0 | AM43: {=IF(AL43=1,1, IF(ISTEXT(AK43),1, IF(AO43>1,AM42, IF(AI43=1, IF(SUMPRODUCT((LEN($Y$2:$Y$4096)-LEN(SUBSTITUTE($Y$2:$Y$4096,AA43,"")))/LEN(AA43))>0,2,1), IF( SUMPRODUCT((LEN($Y$2:$Y$4096)-LEN(SUBSTITUTE($Y$2:$Y$4096,AA43,"")))/LEN(AA43)) - SUMPRODUCT((LEN($Y$2:$Y$4096)-LEN(SUBSTITUTE($Y$2:$Y$4096,"Alolan "&AA43,"")))/LEN("Alolan "&AA43)) - SUMPRODUCT((LEN($Y$2:$Y$4096)-LEN(SUBSTITUTE($Y$2:$Y$4096,"Galarian "&AA43,"")))/LEN("Galarian "&AA43)) - SUMPRODUCT((LEN($Y$2:$Y$4096)-LEN(SUBSTITUTE($Y$2:$Y$4096,"Hisuian "&AA43,"")))/LEN("Hisuian "&AA43)) - SUMPRODUCT((LEN($Y$2:$Y$4096)-LEN(SUBSTITUTE($Y$2:$Y$4096,"Paldean "&AA43,"")))/LEN("Paldean "&AA43)) >0,2,1) ))))} -> 2 | AN43: 0 | AO43: 3
A44: 10 | B44: Caterpie | C44: Bug | E44: 45 | F44: 30 | G44: 35 | H44: 20 | I44: 20 | J44: 45 | K44: Worm Pokémon | L44: Forest | M44: Temperate | N44: 3.5 | O44: 3.45 | R44: =MROUND(N44,1)+P44 -> 4 | S44: =MROUND(O44,1)+Q44 -> 3 | T44: =SUM(S44,R44) -> 7 | U44: Bug | V44: Flying | W44: Grass | X44: Psychic | Y44: Metapod | Z44: {=IF(ISBLANK(AK44),_xlfn.LET( _xlpm.nameBeforeSlash, IF(ISNUMBER(SEARCH("/", Y44)), LEFT(Y44, SEARCH("/", Y44)-1), Y44), _xlpm.matchRow, IFERROR(MATCH(_xlpm.nameBeforeSlash, AA:AA, 0), ""), _xlpm.difference, IF(_xlpm.matchRow="", "", ABS((R44 + S44) - (INDEX(R:R, _xlpm.matchRow) + INDEX(S:S, _xlpm.matchRow)))), _xlpm.category, IF(_xlpm.matchRow="", "", INDEX(AJ:AJ, _xlpm.matchRow)), _xlpm.adjustment, IF(_xlpm.matchRow="", "", IF(_xlpm.category="weak", 2, IF(_xlpm.category="moderate", 4, IF(_xlpm.category="strong", 8, IF(_xlpm.category="legendary", _xlpm.difference + 12, IF(_xlpm.category="warp", _xlpm.difference + 12, 0)))))), _xlpm.result, IF(_xlpm.matchRow="", "", IF(_xlpm.category="legendary", _xlpm.adjustment, _xlpm.difference + _xlpm.adjustment)), _xlpm.result ),IF(ISBLANK(Y44),"","Hidden"))} -> 3 | AA44: Caterpie | AC44: String Shot | AD44: =_xlfn.XLOOKUP(AC44,moves!A:A,moves!B:B) -> bug | AE44: =_xlfn.XLOOKUP(AC44,moves!A:A,moves!D:D) -> 1 | AF44: =_xlfn.XLOOKUP(AC44,moves!A:A,moves!E:E) -> Each time this move is used: Decrease the target's initiative by 2. | AG44: 0 | AH44: 0 | AI44: =IF(ISNUMBER(SEARCH("Shiny ", AA44)), 1, 0) -> 0 | AJ44: weak | AL44: 0 | AM44: {=IF(AL44=1,1, IF(ISTEXT(AK44),1, IF(AO44>1,AM43, IF(AI44=1, IF(SUMPRODUCT((LEN($Y$2:$Y$4096)-LEN(SUBSTITUTE($Y$2:$Y$4096,AA44,"")))/LEN(AA44))>0,2,1), IF( SUMPRODUCT((LEN($Y$2:$Y$4096)-LEN(SUBSTITUTE($Y$2:$Y$4096,AA44,"")))/LEN(AA44)) - SUMPRODUCT((LEN($Y$2:$Y$4096)-LEN(SUBSTITUTE($Y$2:$Y$4096,"Alolan "&AA44,"")))/LEN("Alolan "&AA44)) - SUMPRODUCT((LEN($Y$2:$Y$4096)-LEN(SUBSTITUTE($Y$2:$Y$4096,"Galarian "&AA44,"")))/LEN("Galarian "&AA44)) - SUMPRODUCT((LEN($Y$2:$Y$4096)-LEN(SUBSTITUTE($Y$2:$Y$4096,"Hisuian "&AA44,"")))/LEN("Hisuian "&AA44)) - SUMPRODUCT((LEN($Y$2:$Y$4096)-LEN(SUBSTITUTE($Y$2:$Y$4096,"Paldean "&AA44,"")))/LEN("Paldean "&AA44)) >0,2,1) ))))} -> 1 | AN44: 0 | AO44: 0
A45: 10-shiny | B45: Caterpie | C45: Bug | E45: 45 | F45: 30 | G45: 35 | H45: 20 | I45: 20 | J45: 45 | K45: Worm Pokémon | L45: Forest | M45: Temperate | N45: 3.5 | O45: 3.45 | R45: =MROUND(N45,1)+P45 -> 4 | S45: =MROUND(O45,1)+Q45 -> 3 | T45: =SUM(S45,R45) -> 7 | U45: Bug | V45: Flying | W45: Grass | X45: Psychic | Y45: Shiny Metapod | Z45: {=IF(ISBLANK(AK45),_xlfn.LET( _xlpm.nameBeforeSlash, IF(ISNUMBER(SEARCH("/", Y45)), LEFT(Y45, SEARCH("/", Y45)-1), Y45), _xlpm.matchRow, IFERROR(MATCH(_xlpm.nameBeforeSlash, AA:AA, 0), ""), _xlpm.difference, IF(_xlpm.matchRow="", "", ABS((R45 + S45) - (INDEX(R:R, _xlpm.matchRow) + INDEX(S:S, _xlpm.matchRow)))), _xlpm.category, IF(_xlpm.matchRow="", "", INDEX(AJ:AJ, _xlpm.matchRow)), _xlpm.adjustment, IF(_xlpm.matchRow="", "", IF(_xlpm.category="weak", 2, IF(_xlpm.category="moderate", 4, IF(_xlpm.category="strong", 8, IF(_xlpm.category="legendary", _xlpm.difference + 12, IF(_xlpm.category="warp", _xlpm.difference + 12, 0)))))), _xlpm.result, IF(_xlpm.matchRow="", "", IF(_xlpm.category="legendary", _xlpm.adjustment, _xlpm.difference + _xlpm.adjustment)), _xlpm.result ),IF(ISBLANK(Y45),"","Hidden"))} -> 3 | AA45: Shiny Caterpie | AC45: Bug Bite | AD45: =_xlfn.XLOOKUP(AC45,moves!A:A,moves!B:B) -> bug | AE45: =_xlfn.XLOOKUP(AC45,moves!A:A,moves!D:D) -> 3 | AF45: =_xlfn.XLOOKUP(AC45,moves!A:A,moves!E:E) -> Consume an Apricorn from the bag of the target. The target decides which one. | AG45: 0 | AH45: 0 | AI45: =IF(ISNUMBER(SEARCH("Shiny ", AA45)), 1, 0) -> 1 | AJ45: weak | AL45: 0 | AM45: {=IF(AL45=1,1, IF(ISTEXT(AK45),1, IF(AO45>1,AM44, IF(AI45=1, IF(SUMPRODUCT((LEN($Y$2:$Y$4096)-LEN(SUBSTITUTE($Y$2:$Y$4096,AA45,"")))/LEN(AA45))>0,2,1), IF( SUMPRODUCT((LEN($Y$2:$Y$4096)-LEN(SUBSTITUTE($Y$2:$Y$4096,AA45,"")))/LEN(AA45)) - SUMPRODUCT((LEN($Y$2:$Y$4096)-LEN(SUBSTITUTE($Y$2:$Y$4096,"Alolan "&AA45,"")))/LEN("Alolan "&AA45)) - SUMPRODUCT((LEN($Y$2:$Y$4096)-LEN(SUBSTITUTE($Y$2:$Y$4096,"Galarian "&AA45,"")))/LEN("Galarian "&AA45)) - SUMPRODUCT((LEN($Y$2:$Y$4096)-LEN(SUBSTITUTE($Y$2:$Y$4096,"Hisuian "&AA45,"")))/LEN("Hisuian "&AA45)) - SUMPRODUCT((LEN($Y$2:$Y$4096)-LEN(SUBSTITUTE($Y$2:$Y$4096,"Paldean "&AA45,"")))/LEN("Paldean "&AA45)) >0,2,1) ))))} -> 1 | AN45: 0 | AO45: 0
A46: 11 | B46: Metapod | C46: Bug | E46: 50 | F46: 20 | G46: 55 | H46: 25 | I46: 25 | J46: 30 | K46: Cocoon Pokémon | L46: Forest | M46: Temperate | N46: 2.65 | O46: 4.4 | Q46: 1 | R46: =MROUND(N46,1)+P46 -> 3 | S46: =MROUND(O46,1)+Q46 -> 5 | T46: =SUM(S46,R46) -> 8 | U46: Bug | V46: Flying | W46: Grass | X46: Psychic | Y46: Butterfree | Z46: {=IF(ISBLANK(AK46),_xlfn.LET( _xlpm.nameBeforeSlash, IF(ISNUMBER(SEARCH("/", Y46)), LEFT(Y46, SEARCH("/", Y46)-1), Y46), _xlpm.matchRow, IFERROR(MATCH(_xlpm.nameBeforeSlash, AA:AA, 0), ""), _xlpm.difference, IF(_xlpm.matchRow="", "", ABS((R46 + S46) - (INDEX(R:R, _xlpm.matchRow) + INDEX(S:S, _xlpm.matchRow)))), _xlpm.category, IF(_xlpm.matchRow="", "", INDEX(AJ:AJ, _xlpm.matchRow)), _xlpm.adjustment, IF(_xlpm.matchRow="", "", IF(_xlpm.category="weak", 2, IF(_xlpm.category="moderate", 4, IF(_xlpm.category="strong", 8, IF(_xlpm.category="legendary", _xlpm.difference + 12, IF(_xlpm.category="warp", _xlpm.difference + 12, 0)))))), _xlpm.result, IF(_xlpm.matchRow="", "", IF(_xlpm.category="legendary", _xlpm.adjustment, _xlpm.difference + _xlpm.adjustment)), _xlpm.result ),IF(ISBLANK(Y46),"","Hidden"))} -> 11 | AA46: Metapod | AC46: Harden | AD46: =_xlfn.XLOOKUP(AC46,moves!A:A,moves!B:B) -> bug | AE46: =_xlfn.XLOOKUP(AC46,moves!A:A,moves!D:D) -> 1 | AF46: =_xlfn.XLOOKUP(AC46,moves!A:A,moves!E:E) -> When the user is next attacked: Remove 2 regular hits from the roll. | AG46: 0 | AH46: 0 | AI46: =IF(ISNUMBER(SEARCH("Shiny ", AA46)), 1, 0) -> 0 | AJ46: weak | AL46: 0 | AM46: {=IF(AL46=1,1, IF(ISTEXT(AK46),1, IF(AO46>1,AM45, IF(AI46=1, IF(SUMPRODUCT((LEN($Y$2:$Y$4096)-LEN(SUBSTITUTE($Y$2:$Y$4096,AA46,"")))/LEN(AA46))>0,2,1), IF( SUMPRODUCT((LEN($Y$2:$Y$4096)-LEN(SUBSTITUTE($Y$2:$Y$4096,AA46,"")))/LEN(AA46)) - SUMPRODUCT((LEN($Y$2:$Y$4096)-LEN(SUBSTITUTE($Y$2:$Y$4096,"Alolan "&AA46,"")))/LEN("Alolan "&AA46)) - SUMPRODUCT((LEN($Y$2:$Y$4096)-LEN(SUBSTITUTE($Y$2:$Y$4096,"Galarian "&AA46,"")))/LEN("Galarian "&AA46)) - SUMPRODUCT((LEN($Y$2:$Y$4096)-LEN(SUBSTITUTE($Y$2:$Y$4096,"Hisuian "&AA46,"")))/LEN("Hisuian "&AA46)) - SUMPRODUCT((LEN($Y$2:$Y$4096)-LEN(SUBSTITUTE($Y$2:$Y$4096,"Paldean "&AA46,"")))/LEN("Paldean "&AA46)) >0,2,1) ))))} -> 2 | AN46: 0 | AO46: 0
A47: 11-shiny | B47: Metapod | C47: Bug | E47: 50 | F47: 20 | G47: 55 | H47: 25 | I47: 25 | J47: 30 | K47: Cocoon Pokémon | L47: Forest | M47: Temperate | N47: 2.65 | O47: 4.4 | Q47: 1 | R47: =MROUND(N47,1)+P47 -> 3 | S47: =MROUND(O47,1)+Q47 -> 5 | T47: =SUM(S47,R47) -> 8 | U47: Bug | V47: Flying | W47: Grass | X47: Psychic | Y47: Shiny Butterfree | Z47: {=IF(ISBLANK(AK47),_xlfn.LET( _xlpm.nameBeforeSlash, IF(ISNUMBER(SEARCH("/", Y47)), LEFT(Y47, SEARCH("/", Y47)-1), Y47), _xlpm.matchRow, IFERROR(MATCH(_xlpm.nameBeforeSlash, AA:AA, 0), ""), _xlpm.difference, IF(_xlpm.matchRow="", "", ABS((R47 + S47) - (INDEX(R:R, _xlpm.matchRow) + INDEX(S:S, _xlpm.matchRow)))), _xlpm.category, IF(_xlpm.matchRow="", "", INDEX(AJ:AJ, _xlpm.matchRow)), _xlpm.adjustment, IF(_xlpm.matchRow="", "", IF(_xlpm.category="weak", 2, IF(_xlpm.category="moderate", 4, IF(_xlpm.category="strong", 8, IF(_xlpm.category="legendary", _xlpm.difference + 12, IF(_xlpm.category="warp", _xlpm.difference + 12, 0)))))), _xlpm.result, IF(_xlpm.matchRow="", "", IF(_xlpm.category="legendary", _xlpm.adjustment, _xlpm.difference + _xlpm.adjustment)), _xlpm.result ),IF(ISBLANK(Y47),"","Hidden"))} -> 11 | AA47: Shiny Metapod | AC47: Harden | AD47: =_xlfn.XLOOKUP(AC47,moves!A:A,moves!B:B) -> bug | AE47: =_xlfn.XLOOKUP(AC47,moves!A:A,moves!D:D) -> 1 | AF47: =_xlfn.XLOOKUP(AC47,moves!A:A,moves!E:E) -> When the user is next attacked: Remove 2 regular hits from the roll. | AG47: 0 | AH47: 0 | AI47: =IF(ISNUMBER(SEARCH("Shiny ", AA47)), 1, 0) -> 1 | AJ47: weak | AL47: 0 | AM47: {=IF(AL47=1,1, IF(ISTEXT(AK47),1, IF(AO47>1,AM46, IF(AI47=1, IF(SUMPRODUCT((LEN($Y$2:$Y$4096)-LEN(SUBSTITUTE($Y$2:$Y$4096,AA47,"")))/LEN(AA47))>0,2,1), IF( SUMPRODUCT((LEN($Y$2:$Y$4096)-LEN(SUBSTITUTE($Y$2:$Y$4096,AA47,"")))/LEN(AA47)) - SUMPRODUCT((LEN($Y$2:$Y$4096)-LEN(SUBSTITUTE($Y$2:$Y$4096,"Alolan "&AA47,"")))/LEN("Alolan "&AA47)) - SUMPRODUCT((LEN($Y$2:$Y$4096)-LEN(SUBSTITUTE($Y$2:$Y$4096,"Galarian "&AA47,"")))/LEN("Galarian "&AA47)) - SUMPRODUCT((LEN($Y$2:$Y$4096)-LEN(SUBSTITUTE($Y$2:$Y$4096,"Hisuian "&AA47,"")))/LEN("Hisuian "&AA47)) - SUMPRODUCT((LEN($Y$2:$Y$4096)-LEN(SUBSTITUTE($Y$2:$Y$4096,"Paldean "&AA47,"")))/LEN("Paldean "&AA47)) >0,2,1) ))))} -> 2 | AN47: 0 | AO47: 0
A48: 12 | B48: Butterfree | C48: Bug | D48: Flying | E48: 60 | F48: 45 | G48: 50 | H48: 90 | I48: 80 | J48: 70 | K48: Butterfly Pokémon | L48: Forest | M48: Temperate | N48: 7.75 | O48: 6.3 | Q48: 1 | R48: =MROUND(N48,1)+P48 -> 8 | S48: =MROUND(O48,1)+Q48 -> 7 | T48: =SUM(S48,R48) -> 15 | U48: Bug | V48: Flying | W48: Grass | X48: Psychic | Z48: {=IF(ISBLANK(AK48),_xlfn.LET( _xlpm.nameBeforeSlash, IF(ISNUMBER(SEARCH("/", Y48)), LEFT(Y48, SEARCH("/", Y48)-1), Y48), _xlpm.matchRow, IFERROR(MATCH(_xlpm.nameBeforeSlash, AA:AA, 0), ""), _xlpm.difference, IF(_xlpm.matchRow="", "", ABS((R48 + S48) - (INDEX(R:R, _xlpm.matchRow) + INDEX(S:S, _xlpm.matchRow)))), _xlpm.category, IF(_xlpm.matchRow="", "", INDEX(AJ:AJ, _xlpm.matchRow)), _xlpm.adjustment, IF(_xlpm.matchRow="", "", IF(_xlpm.category="weak", 2, IF(_xlpm.category="moderate", 4, IF(_xlpm.category="strong", 8, IF(_xlpm.category="legendary", _xlpm.difference + 12, IF(_xlpm.category="warp", _xlpm.difference + 12, 0)))))), _xlpm.result, IF(_xlpm.matchRow="", "", IF(_xlpm.category="legendary", _xlpm.adjustment, _xlpm.difference + _xlpm.adjustment)), _xlpm.result ),IF(ISBLANK(Y48),"","Hidden"))} | AA48: Butterfree | AC48: Bug Buzz | AD48: =_xlfn.XLOOKUP(AC48,moves!A:A,moves!B:B) -> bug | AE48: =_xlfn.XLOOKUP(AC48,moves!A:A,moves!D:D) -> 4 | AF48: =_xlfn.XLOOKUP(AC48,moves!A:A,moves!E:E) -> If any status symbols are rolled: Inflict the Paralyzed status on the target. | AG48: 0 | AH48: 0 | AI48: =IF(ISNUMBER(SEARCH("Shiny ", AA48)), 1, 0) -> 0 | AJ48: moderate | AL48: 0 | AM48: {=IF(AL48=1,1, IF(ISTEXT(AK48),1, IF(AO48>1,AM47, IF(AI48=1, IF(SUMPRODUCT((LEN($Y$2:$Y$4096)-LEN(SUBSTITUTE($Y$2:$Y$4096,AA48,"")))/LEN(AA48))>0,2,1), IF( SUMPRODUCT((LEN($Y$2:$Y$4096)-LEN(SUBSTITUTE($Y$2:$Y$4096,AA48,"")))/LEN(AA48)) - SUMPRODUCT((LEN($Y$2:$Y$4096)-LEN(SUBSTITUTE($Y$2:$Y$4096,"Alolan "&AA48,"")))/LEN("Alolan "&AA48)) - SUMPRODUCT((LEN($Y$2:$Y$4096)-LEN(SUBSTITUTE($Y$2:$Y$4096,"Galarian "&AA48,"")))/LEN("Galarian "&AA48)) - SUMPRODUCT((LEN($Y$2:$Y$4096)-LEN(SUBSTITUTE($Y$2:$Y$4096,"Hisuian "&AA48,"")))/LEN("Hisuian "&AA48)) - SUMPRODUCT((LEN($Y$2:$Y$4096)-LEN(SUBSTITUTE($Y$2:$Y$4096,"Paldean "&AA48,"")))/LEN("Paldean "&AA48)) >0,2,1) ))))} -> 2 | AN48: 0 | AO48: 1
A49: 12-gm | B49: Butterfree | C49: Bug | D49: Flying | E49: 60 | F49: 45 | G49: 50 | H49: 90 | I49: 80 | J49: 70 | K49: Butterfly Pokémon | L49: blank | M49: Gigantamax | N49: 7.75 | O49: 6.3 | Q49: 16 | R49: =MROUND(N49,1)+P49 -> 8 | S49: =MROUND(O49,1)+Q49 -> 22 | T49: =SUM(S49,R49) -> 30 | U49: Bug | V49: Flying | W49: Grass | X49: Psychic | Z49: {=IF(ISBLANK(AK49),_xlfn.LET( _xlpm.nameBeforeSlash, IF(ISNUMBER(SEARCH("/", Y49)), LEFT(Y49, SEARCH("/", Y49)-1), Y49), _xlpm.matchRow, IFERROR(MATCH(_xlpm.nameBeforeSlash, AA:AA, 0), ""), _xlpm.difference, IF(_xlpm.matchRow="", "", ABS((R49 + S49) - (INDEX(R:R, _xlpm.matchRow) + INDEX(S:S, _xlpm.matchRow)))), _xlpm.category, IF(_xlpm.matchRow="", "", INDEX(AJ:AJ, _xlpm.matchRow)), _xlpm.adjustment, IF(_xlpm.matchRow="", "", IF(_xlpm.category="weak", 2, IF(_xlpm.category="moderate", 4, IF(_xlpm.category="strong", 8, IF(_xlpm.category="legendary", _xlpm.difference + 12, IF(_xlpm.category="warp", _xlpm.difference + 12, 0)))))), _xlpm.result, IF(_xlpm.matchRow="", "", IF(_xlpm.category="legendary", _xlpm.adjustment, _xlpm.difference + _xlpm.adjustment)), _xlpm.result ),IF(ISBLANK(Y49),"","Hidden"))} | AA49: Gigantamax Butterfree | AB49: Gigantamax Form | AC49: G-Max Befuddle | AD49: =_xlfn.XLOOKUP(AC49,moves!A:A,moves!B:B) -> bug | AE49: =_xlfn.XLOOKUP(AC49,moves!A:A,moves!D:D) -> 5 | AF49: =_xlfn.XLOOKUP(AC49,moves!A:A,moves!E:E) -> Roll 3 status dice. Inflict all status conditions rolled on the target, simultaneously | AG49: 0 | AH49: 0 | AI49: =IF(ISNUMBER(SEARCH("Shiny ", AA49)), 1, 0) -> 0 | AJ49: moderate | AL49: 0 | AM49: {=IF(AL49=1,1, IF(ISTEXT(AK49),1, IF(AO49>1,AM48, IF(AI49=1, IF(SUMPRODUCT((LEN($Y$2:$Y$4096)-LEN(SUBSTITUTE($Y$2:$Y$4096,AA49,"")))/LEN(AA49))>0,2,1), IF( SUMPRODUCT((LEN($Y$2:$Y$4096)-LEN(SUBSTITUTE($Y$2:$Y$4096,AA49,"")))/LEN(AA49)) - SUMPRODUCT((LEN($Y$2:$Y$4096)-LEN(SUBSTITUTE($Y$2:$Y$4096,"Alolan "&AA49,"")))/LEN("Alolan "&AA49)) - SUMPRODUCT((LEN($Y$2:$Y$4096)-LEN(SUBSTITUTE($Y$2:$Y$4096,"Galarian "&AA49,"")))/LEN("Galarian "&AA49)) - SUMPRODUCT((LEN($Y$2:$Y$4096)-LEN(SUBSTITUTE($Y$2:$Y$4096,"Hisuian "&AA49,"")))/LEN("Hisuian "&AA49)) - SUMPRODUCT((LEN($Y$2:$Y$4096)-LEN(SUBSTITUTE($Y$2:$Y$4096,"Paldean "&AA49,"")))/LEN("Paldean "&AA49)) >0,2,1) ))))} -> 2 | AN49: 0 | AO49: 2
A50: 12-shiny | B50: Butterfree | C50: Bug | D50: Flying | E50: 60 | F50: 45 | G50: 50 | H50: 90 | I50: 80 | J50: 70 | K50: Butterfly Pokémon | L50: Forest | M50: Temperate | N50: 7.75 | O50: 6.3 | Q50: 1 | R50: =MROUND(N50,1)+P50 -> 8 | S50: =MROUND(O50,1)+Q50 -> 7 | T50: =SUM(S50,R50) -> 15 | U50: Bug | V50: Flying | W50: Grass | X50: Psychic | Z50: {=IF(ISBLANK(AK50),_xlfn.LET( _xlpm.nameBeforeSlash, IF(ISNUMBER(SEARCH("/", Y50)), LEFT(Y50, SEARCH("/", Y50)-1), Y50), _xlpm.matchRow, IFERROR(MATCH(_xlpm.nameBeforeSlash, AA:AA, 0), ""), _xlpm.difference, IF(_xlpm.matchRow="", "", ABS((R50 + S50) - (INDEX(R:R, _xlpm.matchRow) + INDEX(S:S, _xlpm.matchRow)))), _xlpm.category, IF(_xlpm.matchRow="", "", INDEX(AJ:AJ, _xlpm.matchRow)), _xlpm.adjustment, IF(_xlpm.matchRow="", "", IF(_xlpm.category="weak", 2, IF(_xlpm.category="moderate", 4, IF(_xlpm.category="strong", 8, IF(_xlpm.category="legendary", _xlpm.difference + 12, IF(_xlpm.category="warp", _xlpm.difference + 12, 0)))))), _xlpm.result, IF(_xlpm.matchRow="", "", IF(_xlpm.category="legendary", _xlpm.adjustment, _xlpm.difference + _xlpm.adjustment)), _xlpm.result ),IF(ISBLANK(Y50),"","Hidden"))} | AA50: Shiny Butterfree | AC50: Whirlwind | AD50: =_xlfn.XLOOKUP(AC50,moves!A:A,moves!B:B) -> flying | AE50: =_xlfn.XLOOKUP(AC50,moves!A:A,moves!D:D) -> 1 | AF50: =_xlfn.XLOOKUP(AC50,moves!A:A,moves!E:E) -> The target must switch out. | AG50: 0 | AH50: 0 | AI50: =IF(ISNUMBER(SEARCH("Shiny ", AA50)), 1, 0) -> 1 | AJ50: moderate | AL50: 0 | AM50: {=IF(AL50=1,1, IF(ISTEXT(AK50),1, IF(AO50>1,AM49, IF(AI50=1, IF(SUMPRODUCT((LEN($Y$2:$Y$4096)-LEN(SUBSTITUTE($Y$2:$Y$4096,AA50,"")))/LEN(AA50))>0,2,1), IF( SUMPRODUCT((LEN($Y$2:$Y$4096)-LEN(SUBSTITUTE($Y$2:$Y$4096,AA50,"")))/LEN(AA50)) - SUMPRODUCT((LEN($Y$2:$Y$4096)-LEN(SUBSTITUTE($Y$2:$Y$4096,"Alolan "&AA50,"")))/LEN("Alolan "&AA50)) - SUMPRODUCT((LEN($Y$2:$Y$4096)-LEN(SUBSTITUTE($Y$2:$Y$4096,"Galarian "&AA50,"")))/LEN("Galarian "&AA50)) - SUMPRODUCT((LEN($Y$2:$Y$4096)-LEN(SUBSTITUTE($Y$2:$Y$4096,"Hisuian "&AA50,"")))/LEN("Hisuian "&AA50)) - SUMPRODUCT((LEN($Y$2:$Y$4096)-LEN(SUBSTITUTE($Y$2:$Y$4096,"Paldean "&AA50,"")))/LEN("Paldean "&AA50)) >0,2,1) ))))} -> 2 | AN50: 0 | AO50: 1
A51: 12-gm-shiny | B51: Butterfree | C51: Bug | D51: Flying | E51: 60 | F51: 45 | G51: 50 | H51: 90 | I51: 80 | J51: 70 | K51: Butterfly Pokémon | L51: blank | M51: Gigantamax | N51: 7.75 | O51: 6.3 | Q51: 16 | R51: =MROUND(N51,1)+P51 -> 8 | S51: =MROUND(O51,1)+Q51 -> 22 | T51: =SUM(S51,R51) -> 30 | U51: Bug | V51: Flying | W51: Grass | X51: Psychic | Z51: {=IF(ISBLANK(AK51),_xlfn.LET( _xlpm.nameBeforeSlash, IF(ISNUMBER(SEARCH("/", Y51)), LEFT(Y51, SEARCH("/", Y51)-1), Y51), _xlpm.matchRow, IFERROR(MATCH(_xlpm.nameBeforeSlash, AA:AA, 0), ""), _xlpm.difference, IF(_xlpm.matchRow="", "", ABS((R51 + S51) - (INDEX(R:R, _xlpm.matchRow) + INDEX(S:S, _xlpm.matchRow)))), _xlpm.category, IF(_xlpm.matchRow="", "", INDEX(AJ:AJ, _xlpm.matchRow)), _xlpm.adjustment, IF(_xlpm.matchRow="", "", IF(_xlpm.category="weak", 2, IF(_xlpm.category="moderate", 4, IF(_xlpm.category="strong", 8, IF(_xlpm.category="legendary", _xlpm.difference + 12, IF(_xlpm.category="warp", _xlpm.difference + 12, 0)))))), _xlpm.result, IF(_xlpm.matchRow="", "", IF(_xlpm.category="legendary", _xlpm.adjustment, _xlpm.difference + _xlpm.adjustment)), _xlpm.result ),IF(ISBLANK(Y51),"","Hidden"))} | AA51: Shiny Gigantamax Butterfree | AB51: Gigantamax Form | AC51: G-Max Toxbreeze | AD51: =_xlfn.XLOOKUP(AC51,moves!A:A,moves!B:B) -> bug | AE51: =_xlfn.XLOOKUP(AC51,moves!A:A,moves!D:D) -> 4 | AF51: =_xlfn.XLOOKUP(AC51,moves!A:A,moves!E:E) -> Inflict the Poisoned and Confused status on the target, simultaneously. | AG51: 0 | AH51: 0 | AI51: =IF(ISNUMBER(SEARCH("Shiny ", AA51)), 1, 0) -> 1 | AJ51: moderate | AL51: 0 | AM51: {=IF(AL51=1,1, IF(ISTEXT(AK51),1, IF(AO51>1,AM50, IF(AI51=1, IF(SUMPRODUCT((LEN($Y$2:$Y$4096)-LEN(SUBSTITUTE($Y$2:$Y$4096,AA51,"")))/LEN(AA51))>0,2,1), IF( SUMPRODUCT((LEN($Y$2:$Y$4096)-LEN(SUBSTITUTE($Y$2:$Y$4096,AA51,"")))/LEN(AA51)) - SUMPRODUCT((LEN($Y$2:$Y$4096)-LEN(SUBSTITUTE($Y$2:$Y$4096,"Alolan "&AA51,"")))/LEN("Alolan "&AA51)) - SUMPRODUCT((LEN($Y$2:$Y$4096)-LEN(SUBSTITUTE($Y$2:$Y$4096,"Galarian "&AA51,"")))/LEN("Galarian "&AA51)) - SUMPRODUCT((LEN($Y$2:$Y$4096)-LEN(SUBSTITUTE($Y$2:$Y$4096,"Hisuian "&AA51,"")))/LEN("Hisuian "&AA51)) - SUMPRODUCT((LEN($Y$2:$Y$4096)-LEN(SUBSTITUTE($Y$2:$Y$4096,"Paldean "&AA51,"")))/LEN("Paldean "&AA51)) >0,2,1) ))))} -> 2 | AN51: 0 | AO51: 2
A52: 13 | B52: Weedle | C52: Bug | D52: Poison | E52: 40 | F52: 35 | G52: 30 | H52: 20 | I52: 20 | J52: 50 | K52: Hairy Bug Pokémon | L52: Forest | M52: Temperate | N52: 3.95 | O52: 3.1 | R52: =MROUND(N52,1)+P52 -> 4 | S52: =MROUND(O52,1)+Q52 -> 3 | T52: =SUM(S52,R52) -> 7 | U52: Bug | V52: Poison | W52: Flying | X52: Dark | Y52: Kakuna | Z52: {=IF(ISBLANK(AK52),_xlfn.LET( _xlpm.nameBeforeSlash, IF(ISNUMBER(SEARCH("/", Y52)), LEFT(Y52, SEARCH("/", Y52)-1), Y52), _xlpm.matchRow, IFERROR(MATCH(_xlpm.nameBeforeSlash, AA:AA, 0), ""), _xlpm.difference, IF(_xlpm.matchRow="", "", ABS((R52 + S52) - (INDEX(R:R, _xlpm.matchRow) + INDEX(S:S, _xlpm.matchRow)))), _xlpm.category, IF(_xlpm.matchRow="", "", INDEX(AJ:AJ, _xlpm.matchRow)), _xlpm.adjustment, IF(_xlpm.matchRow="", "", IF(_xlpm.category="weak", 2, IF(_xlpm.category="moderate", 4, IF(_xlpm.category="strong", 8, IF(_xlpm.category="legendary", _xlpm.difference + 12, IF(_xlpm.category="warp", _xlpm.difference + 12, 0)))))), _xlpm.result, IF(_xlpm.matchRow="", "", IF(_xlpm.category="legendary", _xlpm.adjustment, _xlpm.difference + _xlpm.adjustment)), _xlpm.result ),IF(ISBLANK(Y52),"","Hidden"))} -> 3 | AA52: Weedle | AC52: Poison Sting | AD52: =_xlfn.XLOOKUP(AC52,moves!A:A,moves!B:B) -> poison | AE52: =_xlfn.XLOOKUP(AC52,moves!A:A,moves!D:D) -> 1 | AF52: =_xlfn.XLOOKUP(AC52,moves!A:A,moves!E:E) -> If any status symbols are rolled: Inflict the Poisoned status on the target. When the user is next attacked: Remove 2 regular hits from the roll. | AG52: 1 | AH52: 0 | AI52: =IF(ISNUMBER(SEARCH("Shiny ", AA52)), 1, 0) -> 0 | AJ52: starter | AL52: 0 | AM52: {=IF(AL52=1,1, IF(ISTEXT(AK52),1, IF(AO52>1,AM51, IF(AI52=1, IF(SUMPRODUCT((LEN($Y$2:$Y$4096)-LEN(SUBSTITUTE($Y$2:$Y$4096,AA52,"")))/LEN(AA52))>0,2,1), IF( SUMPRODUCT((LEN($Y$2:$Y$4096)-LEN(SUBSTITUTE($Y$2:$Y$4096,AA52,"")))/LEN(AA52)) - SUMPRODUCT((LEN($Y$2:$Y$4096)-LEN(SUBSTITUTE($Y$2:$Y$4096,"Alolan "&AA52,"")))/LEN("Alolan "&AA52)) - SUMPRODUCT((LEN($Y$2:$Y$4096)-LEN(SUBSTITUTE($Y$2:$Y$4096,"Galarian "&AA52,"")))/LEN("Galarian "&AA52)) - SUMPRODUCT((LEN($Y$2:$Y$4096)-LEN(SUBSTITUTE($Y$2:$Y$4096,"Hisuian "&AA52,"")))/LEN("Hisuian "&AA52)) - SUMPRODUCT((LEN($Y$2:$Y$4096)-LEN(SUBSTITUTE($Y$2:$Y$4096,"Paldean "&AA52,"")))/LEN("Paldean "&AA52)) >0,2,1) ))))} -> 1 | AN52: 0 | AO52: 0
A53: 13-shiny | B53: Weedle | C53: Bug | D53: Poison | E53: 40 | F53: 35 | G53: 30 | H53: 20 | I53: 20 | J53: 50 | K53: Hairy Bug Pokémon | L53: Forest | M53: Temperate | N53: 3.95 | O53: 3.1 | R53: =MROUND(N53,1)+P53 -> 4 | S53: =MROUND(O53,1)+Q53 -> 3 | T53: =SUM(S53,R53) -> 7 | U53: Bug | V53: Poison | W53: Flying | X53: Dark | Y53: Shiny Kakuna | Z53: {=IF(ISBLANK(AK53),_xlfn.LET( _xlpm.nameBeforeSlash, IF(ISNUMBER(SEARCH("/", Y53)), LEFT(Y53, SEARCH("/", Y53)-1), Y53), _xlpm.matchRow, IFERROR(MATCH(_xlpm.nameBeforeSlash, AA:AA, 0), ""), _xlpm.difference, IF(_xlpm.matchRow="", "", ABS((R53 + S53) - (INDEX(R:R, _xlpm.matchRow) + INDEX(S:S, _xlpm.matchRow)))), _xlpm.category, IF(_xlpm.matchRow="", "", INDEX(AJ:AJ, _xlpm.matchRow)), _xlpm.adjustment, IF(_xlpm.matchRow="", "", IF(_xlpm.category="weak", 2, IF(_xlpm.category="moderate", 4, IF(_xlpm.category="strong", 8, IF(_xlpm.category="legendary", _xlpm.difference + 12, IF(_xlpm.category="warp", _xlpm.difference + 12, 0)))))), _xlpm.result, IF(_xlpm.matchRow="", "", IF(_xlpm.category="legendary", _xlpm.adjustment, _xlpm.difference + _xlpm.adjustment)), _xlpm.result ),IF(ISBLANK(Y53),"","Hidden"))} -> 3 | AA53: Shiny Weedle | AC53: Bug Bite | AD53: =_xlfn.XLOOKUP(AC53,moves!A:A,moves!B:B) -> bug | AE53: =_xlfn.XLOOKUP(AC53,moves!A:A,moves!D:D) -> 3 | AF53: =_xlfn.XLOOKUP(AC53,moves!A:A,moves!E:E) -> Consume an Apricorn from the bag of the target. The target decides which one. | AG53: 1 | AH53: 0 | AI53: =IF(ISNUMBER(SEARCH("Shiny ", AA53)), 1, 0) -> 1 | AJ53: weak | AL53: 0 | AM53: {=IF(AL53=1,1, IF(ISTEXT(AK53),1, IF(AO53>1,AM52, IF(AI53=1, IF(SUMPRODUCT((LEN($Y$2:$Y$4096)-LEN(SUBSTITUTE($Y$2:$Y$4096,AA53,"")))/LEN(AA53))>0,2,1), IF( SUMPRODUCT((LEN($Y$2:$Y$4096)-LEN(SUBSTITUTE($Y$2:$Y$4096,AA53,"")))/LEN(AA53)) - SUMPRODUCT((LEN($Y$2:$Y$4096)-LEN(SUBSTITUTE($Y$2:$Y$4096,"Alolan "&AA53,"")))/LEN("Alolan "&AA53)) - SUMPRODUCT((LEN($Y$2:$Y$4096)-LEN(SUBSTITUTE($Y$2:$Y$4096,"Galarian "&AA53,"")))/LEN("Galarian "&AA53)) - SUMPRODUCT((LEN($Y$2:$Y$4096)-LEN(SUBSTITUTE($Y$2:$Y$4096,"Hisuian "&AA53,"")))/LEN("Hisuian "&AA53)) - SUMPRODUCT((LEN($Y$2:$Y$4096)-LEN(SUBSTITUTE($Y$2:$Y$4096,"Paldean "&AA53,"")))/LEN("Paldean "&AA53)) >0,2,1) ))))} -> 1 | AN53: 0 | AO53: 0
A54: 14 | B54: Kakuna | C54: Bug | D54: Poison | E54: 45 | F54: 25 | G54: 50 | H54: 25 | I54: 25 | J54: 35 | K54: Cocoon Pokémon | L54: Forest | M54: Temperate | N54: 2.9 | O54: 4.05 | Q54: 1 | R54: =MROUND(N54,1)+P54 -> 3 | S54: =MROUND(O54,1)+Q54 -> 5 | T54: =SUM(S54,R54) -> 8 | U54: Bug | V54: Poison | W54: Flying | X54: Dark | Y54: Beedrill | Z54: {=IF(ISBLANK(AK54),_xlfn.LET( _xlpm.nameBeforeSlash, IF(ISNUMBER(SEARCH("/", Y54)), LEFT(Y54, SEARCH("/", Y54)-1), Y54), _xlpm.matchRow, IFERROR(MATCH(_xlpm.nameBeforeSlash, AA:AA, 0), ""), _xlpm.difference, IF(_xlpm.matchRow="", "", ABS((R54 + S54) - (INDEX(R:R, _xlpm.matchRow) + INDEX(S:S, _xlpm.matchRow)))), _xlpm.category, IF(_xlpm.matchRow="", "", INDEX(AJ:AJ, _xlpm.matchRow)), _xlpm.adjustment, IF(_xlpm.matchRow="", "", IF(_xlpm.category="weak", 2, IF(_xlpm.category="moderate", 4, IF(_xlpm.category="strong", 8, IF(_xlpm.category="legendary", _xlpm.difference + 12, IF(_xlpm.category="warp", _xlpm.difference + 12, 0)))))), _xlpm.result, IF(_xlpm.matchRow="", "", IF(_xlpm.category="legendary", _xlpm.adjustment, _xlpm.difference + _xlpm.adjustment)), _xlpm.result ),IF(ISBLANK(Y54),"","Hidden"))} -> 11 | AA54: Kakuna | AC54: Harden | AD54: =_xlfn.XLOOKUP(AC54,moves!A:A,moves!B:B) -> bug | AE54: =_xlfn.XLOOKUP(AC54,moves!A:A,moves!D:D) -> 1 | AF54: =_xlfn.XLOOKUP(AC54,moves!A:A,moves!E:E) -> When the user is next attacked: Remove 2 regular hits from the roll. | AG54: 0 | AH54: 0 | AI54: =IF(ISNUMBER(SEARCH("Shiny ", AA54)), 1, 0) -> 0 | AJ54: weak | AL54: 0 | AM54: {=IF(AL54=1,1, IF(ISTEXT(AK54),1, IF(AO54>1,AM53, IF(AI54=1, IF(SUMPRODUCT((LEN($Y$2:$Y$4096)-LEN(SUBSTITUTE($Y$2:$Y$4096,AA54,"")))/LEN(AA54))>0,2,1), IF( SUMPRODUCT((LEN($Y$2:$Y$4096)-LEN(SUBSTITUTE($Y$2:$Y$4096,AA54,"")))/LEN(AA54)) - SUMPRODUCT((LEN($Y$2:$Y$4096)-LEN(SUBSTITUTE($Y$2:$Y$4096,"Alolan "&AA54,"")))/LEN("Alolan "&AA54)) - SUMPRODUCT((LEN($Y$2:$Y$4096)-LEN(SUBSTITUTE($Y$2:$Y$4096,"Galarian "&AA54,"")))/LEN("Galarian "&AA54)) - SUMPRODUCT((LEN($Y$2:$Y$4096)-LEN(SUBSTITUTE($Y$2:$Y$4096,"Hisuian "&AA54,"")))/LEN("Hisuian "&AA54)) - SUMPRODUCT((LEN($Y$2:$Y$4096)-LEN(SUBSTITUTE($Y$2:$Y$4096,"Paldean "&AA54,"")))/LEN("Paldean "&AA54)) >0,2,1) ))))} -> 2 | AN54: 0 | AO54: 0
A55: 14-shiny | B55: Kakuna | C55: Bug | D55: Poison | E55: 45 | F55: 25 | G55: 50 | H55: 25 | I55: 25 | J55: 35 | K55: Cocoon Pokémon | L55: Forest | M55: Temperate | N55: 2.9 | O55: 4.05 | Q55: 1 | R55: =MROUND(N55,1)+P55 -> 3 | S55: =MROUND(O55,1)+Q55 -> 5 | T55: =SUM(S55,R55) -> 8 | U55: Bug | V55: Poison | W55: Flying | X55: Dark | Y55: Shiny Beedrill | Z55: {=IF(ISBLANK(AK55),_xlfn.LET( _xlpm.nameBeforeSlash, IF(ISNUMBER(SEARCH("/", Y55)), LEFT(Y55, SEARCH("/", Y55)-1), Y55), _xlpm.matchRow, IFERROR(MATCH(_xlpm.nameBeforeSlash, AA:AA, 0), ""), _xlpm.difference, IF(_xlpm.matchRow="", "", ABS((R55 + S55) - (INDEX(R:R, _xlpm.matchRow) + INDEX(S:S, _xlpm.matchRow)))), _xlpm.category, IF(_xlpm.matchRow="", "", INDEX(AJ:AJ, _xlpm.matchRow)), _xlpm.adjustment, IF(_xlpm.matchRow="", "", IF(_xlpm.category="weak", 2, IF(_xlpm.category="moderate", 4, IF(_xlpm.category="strong", 8, IF(_xlpm.category="legendary", _xlpm.difference + 12, IF(_xlpm.category="warp", _xlpm.difference + 12, 0)))))), _xlpm.result, IF(_xlpm.matchRow="", "", IF(_xlpm.category="legendary", _xlpm.adjustment, _xlpm.difference + _xlpm.adjustment)), _xlpm.result ),IF(ISBLANK(Y55),"","Hidden"))} -> 11 | AA55: Shiny Kakuna | AC55: Harden | AD55: =_xlfn.XLOOKUP(AC55,moves!A:A,moves!B:B) -> bug | AE55: =_xlfn.XLOOKUP(AC55,moves!A:A,moves!D:D) -> 1 | AF55: =_xlfn.XLOOKUP(AC55,moves!A:A,moves!E:E) -> When the user is next attacked: Remove 2 regular hits from the roll. | AG55: 0 | AH55: 0 | AI55: =IF(ISNUMBER(SEARCH("Shiny ", AA55)), 1, 0) -> 1 | AJ55: weak | AL55: 0 | AM55: {=IF(AL55=1,1, IF(ISTEXT(AK55),1, IF(AO55>1,AM54, IF(AI55=1, IF(SUMPRODUCT((LEN($Y$2:$Y$4096)-LEN(SUBSTITUTE($Y$2:$Y$4096,AA55,"")))/LEN(AA55))>0,2,1), IF( SUMPRODUCT((LEN($Y$2:$Y$4096)-LEN(SUBSTITUTE($Y$2:$Y$4096,AA55,"")))/LEN(AA55)) - SUMPRODUCT((LEN($Y$2:$Y$4096)-LEN(SUBSTITUTE($Y$2:$Y$4096,"Alolan "&AA55,"")))/LEN("Alolan "&AA55)) - SUMPRODUCT((LEN($Y$2:$Y$4096)-LEN(SUBSTITUTE($Y$2:$Y$4096,"Galarian "&AA55,"")))/LEN("Galarian "&AA55)) - SUMPRODUCT((LEN($Y$2:$Y$4096)-LEN(SUBSTITUTE($Y$2:$Y$4096,"Hisuian "&AA55,"")))/LEN("Hisuian "&AA55)) - SUMPRODUCT((LEN($Y$2:$Y$4096)-LEN(SUBSTITUTE($Y$2:$Y$4096,"Paldean "&AA55,"")))/LEN("Paldean "&AA55)) >0,2,1) ))))} -> 2 | AN55: 0 | AO55: 0
A56: 15 | B56: Beedrill | C56: Bug | D56: Poison | E56: 65 | F56: 90 | G56: 40 | H56: 40 | I56: 80 | J56: 75 | K56: Poison Bee Pokémon | L56: Forest | M56: Temperate | N56: 7.9 | O56: 6.2 | P56: 1 | R56: =MROUND(N56,1)+P56 -> 9 | S56: =MROUND(O56,1)+Q56 -> 6 | T56: =SUM(S56,R56) -> 15 | U56: Bug | V56: Poison | W56: Flying | X56: Dark | Z56: {=IF(ISBLANK(AK56),_xlfn.LET( _xlpm.nameBeforeSlash, IF(ISNUMBER(SEARCH("/", Y56)), LEFT(Y56, SEARCH("/", Y56)-1), Y56), _xlpm.matchRow, IFERROR(MATCH(_xlpm.nameBeforeSlash, AA:AA, 0), ""), _xlpm.difference, IF(_xlpm.matchRow="", "", ABS((R56 + S56) - (INDEX(R:R, _xlpm.matchRow) + INDEX(S:S, _xlpm.matchRow)))), _xlpm.category, IF(_xlpm.matchRow="", "", INDEX(AJ:AJ, _xlpm.matchRow)), _xlpm.adjustment, IF(_xlpm.matchRow="", "", IF(_xlpm.category="weak", 2, IF(_xlpm.category="moderate", 4, IF(_xlpm.category="strong", 8, IF(_xlpm.category="legendary", _xlpm.difference + 12, IF(_xlpm.category="warp", _xlpm.difference + 12, 0)))))), _xlpm.result, IF(_xlpm.matchRow="", "", IF(_xlpm.category="legendary", _xlpm.adjustment, _xlpm.difference + _xlpm.adjustment)), _xlpm.result ),IF(ISBLANK(Y56),"","Hidden"))} | AA56: Beedrill | AC56: Twineedle | AD56: =_xlfn.XLOOKUP(AC56,moves!A:A,moves!B:B) -> bug | AE56: =_xlfn.XLOOKUP(AC56,moves!A:A,moves!D:D) -> 1 | AF56: =_xlfn.XLOOKUP(AC56,moves!A:A,moves!E:E) -> If any status symbols are rolled: Inflict the Poisoned status on the target, ignoring type immunity. If any critical hits are rolled: the user may use this move a second time this turn. | AG56: 0 | AH56: 0 | AI56: =IF(ISNUMBER(SEARCH("Shiny ", AA56)), 1, 0) -> 0 | AJ56: moderate | AL56: 0 | AM56: {=IF(AL56=1,1, IF(ISTEXT(AK56),1, IF(AO56>1,AM55, IF(AI56=1, IF(SUMPRODUCT((LEN($Y$2:$Y$4096)-LEN(SUBSTITUTE($Y$2:$Y$4096,AA56,"")))/LEN(AA56))>0,2,1), IF( SUMPRODUCT((LEN($Y$2:$Y$4096)-LEN(SUBSTITUTE($Y$2:$Y$4096,AA56,"")))/LEN(AA56)) - SUMPRODUCT((LEN($Y$2:$Y$4096)-LEN(SUBSTITUTE($Y$2:$Y$4096,"Alolan "&AA56,"")))/LEN("Alolan "&AA56)) - SUMPRODUCT((LEN($Y$2:$Y$4096)-LEN(SUBSTITUTE($Y$2:$Y$4096,"Galarian "&AA56,"")))/LEN("Galarian "&AA56)) - SUMPRODUCT((LEN($Y$2:$Y$4096)-LEN(SUBSTITUTE($Y$2:$Y$4096,"Hisuian "&AA56,"")))/LEN("Hisuian "&AA56)) - SUMPRODUCT((LEN($Y$2:$Y$4096)-LEN(SUBSTITUTE($Y$2:$Y$4096,"Paldean "&AA56,"")))/LEN("Paldean "&AA56)) >0,2,1) ))))} -> 2 | AN56: 0 | AO56: 1
A57: 15-m | B57: Beedrill | C57: Bug | D57: Poison | E57: 65 | F57: 150 | G57: 40 | H57: 15 | I57: 80 | J57: 145 | K57: Poison Bee Pokémon | L57: blank | M57: Mega | N57: 13.45 | O57: 6.2 | P57: 1 | Q57: 3 | R57: =MROUND(N57,1)+P57 -> 14 | S57: =MROUND(O57,1)+Q57 -> 9 | T57: =SUM(S57,R57) -> 23 | U57: Bug | V57: Poison | W57: Flying | X57: Dark | Z57: {=IF(ISBLANK(AK57),_xlfn.LET( _xlpm.nameBeforeSlash, IF(ISNUMBER(SEARCH("/", Y57)), LEFT(Y57, SEARCH("/", Y57)-1), Y57), _xlpm.matchRow, IFERROR(MATCH(_xlpm.nameBeforeSlash, AA:AA, 0), ""), _xlpm.difference, IF(_xlpm.matchRow="", "", ABS((R57 + S57) - (INDEX(R:R, _xlpm.matchRow) + INDEX(S:S, _xlpm.matchRow)))), _xlpm.category, IF(_xlpm.matchRow="", "", INDEX(AJ:AJ, _xlpm.matchRow)), _xlpm.adjustment, IF(_xlpm.matchRow="", "", IF(_xlpm.category="weak", 2, IF(_xlpm.category="moderate", 4, IF(_xlpm.category="strong", 8, IF(_xlpm.category="legendary", _xlpm.difference + 12, IF(_xlpm.category="warp", _xlpm.difference + 12, 0)))))), _xlpm.result, IF(_xlpm.matchRow="", "", IF(_xlpm.category="legendary", _xlpm.adjustment, _xlpm.difference + _xlpm.adjustment)), _xlpm.result ),IF(ISBLANK(Y57),"","Hidden"))} | AA57: Mega Beedrill | AB57: Mega Form | AC57: Fell Stinger | AD57: =_xlfn.XLOOKUP(AC57,moves!A:A,moves!B:B) -> bug | AE57: =_xlfn.XLOOKUP(AC57,moves!A:A,moves!D:D) -> 2 | AF57: =_xlfn.XLOOKUP(AC57,moves!A:A,moves!E:E) -> Each time a target faints due to this attack: Increase the user's attack strength by 2. | AG57: 0 | AH57: 0 | AI57: =IF(ISNUMBER(SEARCH("Shiny ", AA57)), 1, 0) -> 0 | AJ57: moderate | AL57: 0 | AM57: {=IF(AL57=1,1, IF(ISTEXT(AK57),1, IF(AO57>1,AM56, IF(AI57=1, IF(SUMPRODUCT((LEN($Y$2:$Y$4096)-LEN(SUBSTITUTE($Y$2:$Y$4096,AA57,"")))/LEN(AA57))>0,2,1), IF( SUMPRODUCT((LEN($Y$2:$Y$4096)-LEN(SUBSTITUTE($Y$2:$Y$4096,AA57,"")))/LEN(AA57)) - SUMPRODUCT((LEN($Y$2:$Y$4096)-LEN(SUBSTITUTE($Y$2:$Y$4096,"Alolan "&AA57,"")))/LEN("Alolan "&AA57)) - SUMPRODUCT((LEN($Y$2:$Y$4096)-LEN(SUBSTITUTE($Y$2:$Y$4096,"Galarian "&AA57,"")))/LEN("Galarian "&AA57)) - SUMPRODUCT((LEN($Y$2:$Y$4096)-LEN(SUBSTITUTE($Y$2:$Y$4096,"Hisuian "&AA57,"")))/LEN("Hisuian "&AA57)) - SUMPRODUCT((LEN($Y$2:$Y$4096)-LEN(SUBSTITUTE($Y$2:$Y$4096,"Paldean "&AA57,"")))/LEN("Paldean "&AA57)) >0,2,1) ))))} -> 2 | AN57: 0 | AO57: 2
A58: 15-shiny | B58: Beedrill | C58: Bug | D58: Poison | E58: 65 | F58: 90 | G58: 40 | H58: 40 | I58: 80 | J58: 75 | K58: Poison Bee Pokémon | L58: Forest | M58: Temperate | N58: 7.9 | O58: 6.2 | P58: 1 | R58: =MROUND(N58,1)+P58 -> 9 | S58: =MROUND(O58,1)+Q58 -> 6 | T58: =SUM(S58,R58) -> 15 | U58: Bug | V58: Poison | W58: Flying | X58: Dark | Z58: {=IF(ISBLANK(AK58),_xlfn.LET( _xlpm.nameBeforeSlash, IF(ISNUMBER(SEARCH("/", Y58)), LEFT(Y58, SEARCH("/", Y58)-1), Y58), _xlpm.matchRow, IFERROR(MATCH(_xlpm.nameBeforeSlash, AA:AA, 0), ""), _xlpm.difference, IF(_xlpm.matchRow="", "", ABS((R58 + S58) - (INDEX(R:R, _xlpm.matchRow) + INDEX(S:S, _xlpm.matchRow)))), _xlpm.category, IF(_xlpm.matchRow="", "", INDEX(AJ:AJ, _xlpm.matchRow)), _xlpm.adjustment, IF(_xlpm.matchRow="", "", IF(_xlpm.category="weak", 2, IF(_xlpm.category="moderate", 4, IF(_xlpm.category="strong", 8, IF(_xlpm.category="legendary", _xlpm.difference + 12, IF(_xlpm.category="warp", _xlpm.difference + 12, 0)))))), _xlpm.result, IF(_xlpm.matchRow="", "", IF(_xlpm.category="legendary", _xlpm.adjustment, _xlpm.difference + _xlpm.adjustment)), _xlpm.result ),IF(ISBLANK(Y58),"","Hidden"))} | AA58: Shiny Beedrill | AC58: Flash Needle | AD58: =_xlfn.XLOOKUP(AC58,moves!A:A,moves!B:B) -> bug | AE58: =_xlfn.XLOOKUP(AC58,moves!A:A,moves!D:D) -> 2 | AF58: =_xlfn.XLOOKUP(AC58,moves!A:A,moves!E:E) -> If all dice rolled are the same: the user gains the PROTECT effect. | AG58: 0 | AH58: 0 | AI58: =IF(ISNUMBER(SEARCH("Shiny ", AA58)), 1, 0) -> 1 | AJ58: moderate | AL58: 0 | AM58: {=IF(AL58=1,1, IF(ISTEXT(AK58),1, IF(AO58>1,AM57, IF(AI58=1, IF(SUMPRODUCT((LEN($Y$2:$Y$4096)-LEN(SUBSTITUTE($Y$2:$Y$4096,AA58,"")))/LEN(AA58))>0,2,1), IF( SUMPRODUCT((LEN($Y$2:$Y$4096)-LEN(SUBSTITUTE($Y$2:$Y$4096,AA58,"")))/LEN(AA58)) - SUMPRODUCT((LEN($Y$2:$Y$4096)-LEN(SUBSTITUTE($Y$2:$Y$4096,"Alolan "&AA58,"")))/LEN("Alolan "&AA58)) - SUMPRODUCT((LEN($Y$2:$Y$4096)-LEN(SUBSTITUTE($Y$2:$Y$4096,"Galarian "&AA58,"")))/LEN("Galarian "&AA58)) - SUMPRODUCT((LEN($Y$2:$Y$4096)-LEN(SUBSTITUTE($Y$2:$Y$4096,"Hisuian "&AA58,"")))/LEN("Hisuian "&AA58)) - SUMPRODUCT((LEN($Y$2:$Y$4096)-LEN(SUBSTITUTE($Y$2:$Y$4096,"Paldean "&AA58,"")))/LEN("Paldean "&AA58)) >0,2,1) ))))} -> 2 | AN58: 0 | AO58: 1
A59: 15-m-shiny | B59: Beedrill | C59: Bug | D59: Poison | E59: 65 | F59: 150 | G59: 40 | H59: 15 | I59: 80 | J59: 145 | K59: Poison Bee Pokémon | L59: blank | M59: Mega | N59: 13.45 | O59: 6.2 | P59: 1 | Q59: 3 | R59: =MROUND(N59,1)+P59 -> 14 | S59: =MROUND(O59,1)+Q59 -> 9 | T59: =SUM(S59,R59) -> 23 | U59: Bug | V59: Poison | W59: Flying | X59: Dark | Z59: {=IF(ISBLANK(AK59),_xlfn.LET( _xlpm.nameBeforeSlash, IF(ISNUMBER(SEARCH("/", Y59)), LEFT(Y59, SEARCH("/", Y59)-1), Y59), _xlpm.matchRow, IFERROR(MATCH(_xlpm.nameBeforeSlash, AA:AA, 0), ""), _xlpm.difference, IF(_xlpm.matchRow="", "", ABS((R59 + S59) - (INDEX(R:R, _xlpm.matchRow) + INDEX(S:S, _xlpm.matchRow)))), _xlpm.category, IF(_xlpm.matchRow="", "", INDEX(AJ:AJ, _xlpm.matchRow)), _xlpm.adjustment, IF(_xlpm.matchRow="", "", IF(_xlpm.category="weak", 2, IF(_xlpm.category="moderate", 4, IF(_xlpm.category="strong", 8, IF(_xlpm.category="legendary", _xlpm.difference + 12, IF(_xlpm.category="warp", _xlpm.difference + 12, 0)))))), _xlpm.result, IF(_xlpm.matchRow="", "", IF(_xlpm.category="legendary", _xlpm.adjustment, _xlpm.difference + _xlpm.adjustment)), _xlpm.result ),IF(ISBLANK(Y59),"","Hidden"))} | AA59: Shiny Mega Beedrill | AB59: Mega Form | AC59: Hazard Sting | AD59: =_xlfn.XLOOKUP(AC59,moves!A:A,moves!B:B) -> poison | AE59: =_xlfn.XLOOKUP(AC59,moves!A:A,moves!D:D) -> 2 | AF59: =_xlfn.XLOOKUP(AC59,moves!A:A,moves!E:E) -> Inflict the Poisoned and Paralyzed status on the target, simultaneously. Pokémon poisoned by this move take 1 extra damage from poison each turn. | AG59: 0 | AH59: 0 | AI59: =IF(ISNUMBER(SEARCH("Shiny ", AA59)), 1, 0) -> 1 | AJ59: moderate | AL59: 0 | AM59: {=IF(AL59=1,1, IF(ISTEXT(AK59),1, IF(AO59>1,AM58, IF(AI59=1, IF(SUMPRODUCT((LEN($Y$2:$Y$4096)-LEN(SUBSTITUTE($Y$2:$Y$4096,AA59,"")))/LEN(AA59))>0,2,1), IF( SUMPRODUCT((LEN($Y$2:$Y$4096)-LEN(SUBSTITUTE($Y$2:$Y$4096,AA59,"")))/LEN(AA59)) - SUMPRODUCT((LEN($Y$2:$Y$4096)-LEN(SUBSTITUTE($Y$2:$Y$4096,"Alolan "&AA59,"")))/LEN("Alolan "&AA59)) - SUMPRODUCT((LEN($Y$2:$Y$4096)-LEN(SUBSTITUTE($Y$2:$Y$4096,"Galarian "&AA59,"")))/LEN("Galarian "&AA59)) - SUMPRODUCT((LEN($Y$2:$Y$4096)-LEN(SUBSTITUTE($Y$2:$Y$4096,"Hisuian "&AA59,"")))/LEN("Hisuian "&AA59)) - SUMPRODUCT((LEN($Y$2:$Y$4096)-LEN(SUBSTITUTE($Y$2:$Y$4096,"Paldean "&AA59,"")))/LEN("Paldean "&AA59)) >0,2,1) ))))} -> 2 | AN59: 0 | AO59: 2
A60: 16 | B60: Pidgey | C60: Normal | D60: Flying | E60: 40 | F60: 45 | G60: 40 | H60: 35 | I60: 35 | J60: 56 | K60: Tiny Bird Pokémon | L60: Forest | M60: Temperate | N60: 4.84 | O60: 3.85 | R60: =MROUND(N60,1)+P60 -> 5 | S60: =MROUND(O60,1)+Q60 -> 4 | T60: =SUM(S60,R60) -> 9 | U60: Normal | V60: Flying | W60: Steel | X60: Bug | Y60: Pidgeotto | Z60: {=IF(ISBLANK(AK60),_xlfn.LET( _xlpm.nameBeforeSlash, IF(ISNUMBER(SEARCH("/", Y60)), LEFT(Y60, SEARCH("/", Y60)-1), Y60), _xlpm.matchRow, IFERROR(MATCH(_xlpm.nameBeforeSlash, AA:AA, 0), ""), _xlpm.difference, IF(_xlpm.matchRow="", "", ABS((R60 + S60) - (INDEX(R:R, _xlpm.matchRow) + INDEX(S:S, _xlpm.matchRow)))), _xlpm.category, IF(_xlpm.matchRow="", "", INDEX(AJ:AJ, _xlpm.matchRow)), _xlpm.adjustment, IF(_xlpm.matchRow="", "", IF(_xlpm.category="weak", 2, IF(_xlpm.category="moderate", 4, IF(_xlpm.category="strong", 8, IF(_xlpm.category="legendary", _xlpm.difference + 12, IF(_xlpm.category="warp", _xlpm.difference + 12, 0)))))), _xlpm.result, IF(_xlpm.matchRow="", "", IF(_xlpm.category="legendary", _xlpm.adjustment, _xlpm.difference + _xlpm.adjustment)), _xlpm.result ),IF(ISBLANK(Y60),"","Hidden"))} -> 9 | AA60: Pidgey | AC60: Quick Attack | AD60: =_xlfn.XLOOKUP(AC60,moves!A:A,moves!B:B) -> normal | AE60: =_xlfn.XLOOKUP(AC60,moves!A:A,moves!D:D) -> 2 | AF60: =_xlfn.XLOOKUP(AC60,moves!A:A,moves!E:E) | AG60: 1 | AH60: 0 | AI60: =IF(ISNUMBER(SEARCH("Shiny ", AA60)), 1, 0) -> 0 | AJ60: starter | AL60: 0 | AM60: {=IF(AL60=1,1, IF(ISTEXT(AK60),1, IF(AO60>1,AM59, IF(AI60=1, IF(SUMPRODUCT((LEN($Y$2:$Y$4096)-LEN(SUBSTITUTE($Y$2:$Y$4096,AA60,"")))/LEN(AA60))>0,2,1), IF( SUMPRODUCT((LEN($Y$2:$Y$4096)-LEN(SUBSTITUTE($Y$2:$Y$4096,AA60,"")))/LEN(AA60)) - SUMPRODUCT((LEN($Y$2:$Y$4096)-LEN(SUBSTITUTE($Y$2:$Y$4096,"Alolan "&AA60,"")))/LEN("Alolan "&AA60)) - SUMPRODUCT((LEN($Y$2:$Y$4096)-LEN(SUBSTITUTE($Y$2:$Y$4096,"Galarian "&AA60,"")))/LEN("Galarian "&AA60)) - SUMPRODUCT((LEN($Y$2:$Y$4096)-LEN(SUBSTITUTE($Y$2:$Y$4096,"Hisuian "&AA60,"")))/LEN("Hisuian "&AA60)) - SUMPRODUCT((LEN($Y$2:$Y$4096)-LEN(SUBSTITUTE($Y$2:$Y$4096,"Paldean "&AA60,"")))/LEN("Paldean "&AA60)) >0,2,1) ))))} -> 1 | AN60: 0 | AO60: 0
A61: 16 | B61: Pidgey | C61: Normal | D61: Flying | E61: 40 | F61: 45 | G61: 40 | H61: 35 | I61: 35 | J61: 56 | K61: Tiny Bird Pokémon | L61: Forest | M61: Temperate | N61: 4.84 | O61: 3.85 | R61: =MROUND(N61,1)+P61 -> 5 | S61: =MROUND(O61,1)+Q61 -> 4 | T61: =SUM(S61,R61) -> 9 | U61: Normal | V61: Flying | W61: Steel | X61: Bug | Y61: Pidgeotto | Z61: {=IF(ISBLANK(AK61),_xlfn.LET( _xlpm.nameBeforeSlash, IF(ISNUMBER(SEARCH("/", Y61)), LEFT(Y61, SEARCH("/", Y61)-1), Y61), _xlpm.matchRow, IFERROR(MATCH(_xlpm.nameBeforeSlash, AA:AA, 0), ""), _xlpm.difference, IF(_xlpm.matchRow="", "", ABS((R61 + S61) - (INDEX(R:R, _xlpm.matchRow) + INDEX(S:S, _xlpm.matchRow)))), _xlpm.category, IF(_xlpm.matchRow="", "", INDEX(AJ:AJ, _xlpm.matchRow)), _xlpm.adjustment, IF(_xlpm.matchRow="", "", IF(_xlpm.category="weak", 2, IF(_xlpm.category="moderate", 4, IF(_xlpm.category="strong", 8, IF(_xlpm.category="legendary", _xlpm.difference + 12, IF(_xlpm.category="warp", _xlpm.difference + 12, 0)))))), _xlpm.result, IF(_xlpm.matchRow="", "", IF(_xlpm.category="legendary", _xlpm.adjustment, _xlpm.difference + _xlpm.adjustment)), _xlpm.result ),IF(ISBLANK(Y61),"","Hidden"))} -> 9 | AA61: Pidgey | AC61: Quick Attack | AD61: =_xlfn.XLOOKUP(AC61,moves!A:A,moves!B:B) -> normal | AE61: =_xlfn.XLOOKUP(AC61,moves!A:A,moves!D:D) -> 2 | AF61: =_xlfn.XLOOKUP(AC61,moves!A:A,moves!E:E) | AG61: 0 | AH61: 0 | AI61: =IF(ISNUMBER(SEARCH("Shiny ", AA61)), 1, 0) -> 0 | AJ61: weak | AL61: 0 | AM61: {=IF(AL61=1,1, IF(ISTEXT(AK61),1, IF(AO61>1,AM60, IF(AI61=1, IF(SUMPRODUCT((LEN($Y$2:$Y$4096)-LEN(SUBSTITUTE($Y$2:$Y$4096,AA61,"")))/LEN(AA61))>0,2,1), IF( SUMPRODUCT((LEN($Y$2:$Y$4096)-LEN(SUBSTITUTE($Y$2:$Y$4096,AA61,"")))/LEN(AA61)) - SUMPRODUCT((LEN($Y$2:$Y$4096)-LEN(SUBSTITUTE($Y$2:$Y$4096,"Alolan "&AA61,"")))/LEN("Alolan "&AA61)) - SUMPRODUCT((LEN($Y$2:$Y$4096)-LEN(SUBSTITUTE($Y$2:$Y$4096,"Galarian "&AA61,"")))/LEN("Galarian "&AA61)) - SUMPRODUCT((LEN($Y$2:$Y$4096)-LEN(SUBSTITUTE($Y$2:$Y$4096,"Hisuian "&AA61,"")))/LEN("Hisuian "&AA61)) - SUMPRODUCT((LEN($Y$2:$Y$4096)-LEN(SUBSTITUTE($Y$2:$Y$4096,"Paldean "&AA61,"")))/LEN("Paldean "&AA61)) >0,2,1) ))))} -> 1 | AN61: 0 | AO61: 0
A62: 16 | B62: Pidgey | C62: Normal | D62: Flying | E62: 40 | F62: 45 | G62: 40 | H62: 35 | I62: 35 | J62: 56 | K62: Tiny Bird Pokémon | L62: Forest | M62: Temperate | N62: 4.84 | O62: 3.85 | R62: =MROUND(N62,1)+P62 -> 5 | S62: =MROUND(O62,1)+Q62 -> 4 | T62: =SUM(S62,R62) -> 9 | U62: Normal | V62: Flying | W62: Steel | X62: Bug | Y62: Pidgeotto | Z62: {=IF(ISBLANK(AK62),_xlfn.LET( _xlpm.nameBeforeSlash, IF(ISNUMBER(SEARCH("/", Y62)), LEFT(Y62, SEARCH("/", Y62)-1), Y62), _xlpm.matchRow, IFERROR(MATCH(_xlpm.nameBeforeSlash, AA:AA, 0), ""), _xlpm.difference, IF(_xlpm.matchRow="", "", ABS((R62 + S62) - (INDEX(R:R, _xlpm.matchRow) + INDEX(S:S, _xlpm.matchRow)))), _xlpm.category, IF(_xlpm.matchRow="", "", INDEX(AJ:AJ, _xlpm.matchRow)), _xlpm.adjustment, IF(_xlpm.matchRow="", "", IF(_xlpm.category="weak", 2, IF(_xlpm.category="moderate", 4, IF(_xlpm.category="strong", 8, IF(_xlpm.category="legendary", _xlpm.difference + 12, IF(_xlpm.category="warp", _xlpm.difference + 12, 0)))))), _xlpm.result, IF(_xlpm.matchRow="", "", IF(_xlpm.category="legendary", _xlpm.adjustment, _xlpm.difference + _xlpm.adjustment)), _xlpm.result ),IF(ISBLANK(Y62),"","Hidden"))} -> 9 | AA62: Pidgey | AC62: Quick Attack | AD62: =_xlfn.XLOOKUP(AC62,moves!A:A,moves!B:B) -> normal | AE62: =_xlfn.XLOOKUP(AC62,moves!A:A,moves!D:D) -> 2 | AF62: =_xlfn.XLOOKUP(AC62,moves!A:A,moves!E:E) | AG62: 0 | AH62: 0 | AI62: =IF(ISNUMBER(SEARCH("Shiny ", AA62)), 1, 0) -> 0 | AJ62: weak | AL62: 0 | AM62: {=IF(AL62=1,1, IF(ISTEXT(AK62),1, IF(AO62>1,AM61, IF(AI62=1, IF(SUMPRODUCT((LEN($Y$2:$Y$4096)-LEN(SUBSTITUTE($Y$2:$Y$4096,AA62,"")))/LEN(AA62))>0,2,1), IF( SUMPRODUCT((LEN($Y$2:$Y$4096)-LEN(SUBSTITUTE($Y$2:$Y$4096,AA62,"")))/LEN(AA62)) - SUMPRODUCT((LEN($Y$2:$Y$4096)-LEN(SUBSTITUTE($Y$2:$Y$4096,"Alolan "&AA62,"")))/LEN("Alolan "&AA62)) - SUMPRODUCT((LEN($Y$2:$Y$4096)-LEN(SUBSTITUTE($Y$2:$Y$4096,"Galarian "&AA62,"")))/LEN("Galarian "&AA62)) - SUMPRODUCT((LEN($Y$2:$Y$4096)-LEN(SUBSTITUTE($Y$2:$Y$4096,"Hisuian "&AA62,"")))/LEN("Hisuian "&AA62)) - SUMPRODUCT((LEN($Y$2:$Y$4096)-LEN(SUBSTITUTE($Y$2:$Y$4096,"Paldean "&AA62,"")))/LEN("Paldean "&AA62)) >0,2,1) ))))} -> 1 | AN62: 0 | AO62: 0
A63: 16 | B63: Pidgey | C63: Normal | D63: Flying | E63: 40 | F63: 45 | G63: 40 | H63: 35 | I63: 35 | J63: 56 | K63: Tiny Bird Pokémon | L63: Forest | M63: Temperate | N63: 4.84 | O63: 3.85 | R63: =MROUND(N63,1)+P63 -> 5 | S63: =MROUND(O63,1)+Q63 -> 4 | T63: =SUM(S63,R63) -> 9 | U63: Normal | V63: Flying | W63: Steel | X63: Bug | Y63: Pidgeotto | Z63: {=IF(ISBLANK(AK63),_xlfn.LET( _xlpm.nameBeforeSlash, IF(ISNUMBER(SEARCH("/", Y63)), LEFT(Y63, SEARCH("/", Y63)-1), Y63), _xlpm.matchRow, IFERROR(MATCH(_xlpm.nameBeforeSlash, AA:AA, 0), ""), _xlpm.difference, IF(_xlpm.matchRow="", "", ABS((R63 + S63) - (INDEX(R:R, _xlpm.matchRow) + INDEX(S:S, _xlpm.matchRow)))), _xlpm.category, IF(_xlpm.matchRow="", "", INDEX(AJ:AJ, _xlpm.matchRow)), _xlpm.adjustment, IF(_xlpm.matchRow="", "", IF(_xlpm.category="weak", 2, IF(_xlpm.category="moderate", 4, IF(_xlpm.category="strong", 8, IF(_xlpm.category="legendary", _xlpm.difference + 12, IF(_xlpm.category="warp", _xlpm.difference + 12, 0)))))), _xlpm.result, IF(_xlpm.matchRow="", "", IF(_xlpm.category="legendary", _xlpm.adjustment, _xlpm.difference + _xlpm.adjustment)), _xlpm.result ),IF(ISBLANK(Y63),"","Hidden"))} -> 9 | AA63: Pidgey | AC63: Quick Attack | AD63: =_xlfn.XLOOKUP(AC63,moves!A:A,moves!B:B) -> normal | AE63: =_xlfn.XLOOKUP(AC63,moves!A:A,moves!D:D) -> 2 | AF63: =_xlfn.XLOOKUP(AC63,moves!A:A,moves!E:E) | AG63: 0 | AH63: 0 | AI63: =IF(ISNUMBER(SEARCH("Shiny ", AA63)), 1, 0) -> 0 | AJ63: weak | AL63: 0 | AM63: {=IF(AL63=1,1, IF(ISTEXT(AK63),1, IF(AO63>1,AM62, IF(AI63=1, IF(SUMPRODUCT((LEN($Y$2:$Y$4096)-LEN(SUBSTITUTE($Y$2:$Y$4096,AA63,"")))/LEN(AA63))>0,2,1), IF( SUMPRODUCT((LEN($Y$2:$Y$4096)-LEN(SUBSTITUTE($Y$2:$Y$4096,AA63,"")))/LEN(AA63)) - SUMPRODUCT((LEN($Y$2:$Y$4096)-LEN(SUBSTITUTE($Y$2:$Y$4096,"Alolan "&AA63,"")))/LEN("Alolan "&AA63)) - SUMPRODUCT((LEN($Y$2:$Y$4096)-LEN(SUBSTITUTE($Y$2:$Y$4096,"Galarian "&AA63,"")))/LEN("Galarian "&AA63)) - SUMPRODUCT((LEN($Y$2:$Y$4096)-LEN(SUBSTITUTE($Y$2:$Y$4096,"Hisuian "&AA63,"")))/LEN("Hisuian "&AA63)) - SUMPRODUCT((LEN($Y$2:$Y$4096)-LEN(SUBSTITUTE($Y$2:$Y$4096,"Paldean "&AA63,"")))/LEN("Paldean "&AA63)) >0,2,1) ))))} -> 1 | AN63: 0 | AO63: 0
A64: 16 | B64: Pidgey | C64: Normal | D64: Flying | E64: 40 | F64: 45 | G64: 40 | H64: 35 | I64: 35 | J64: 56 | K64: Tiny Bird Pokémon | L64: Forest | M64: Temperate | N64: 4.84 | O64: 3.85 | R64: =MROUND(N64,1)+P64 -> 5 | S64: =MROUND(O64,1)+Q64 -> 4 | T64: =SUM(S64,R64) -> 9 | U64: Normal | V64: Flying | W64: Steel | X64: Bug | Y64: Pidgeotto | Z64: {=IF(ISBLANK(AK64),_xlfn.LET( _xlpm.nameBeforeSlash, IF(ISNUMBER(SEARCH("/", Y64)), LEFT(Y64, SEARCH("/", Y64)-1), Y64), _xlpm.matchRow, IFERROR(MATCH(_xlpm.nameBeforeSlash, AA:AA, 0), ""), _xlpm.difference, IF(_xlpm.matchRow="", "", ABS((R64 + S64) - (INDEX(R:R, _xlpm.matchRow) + INDEX(S:S, _xlpm.matchRow)))), _xlpm.category, IF(_xlpm.matchRow="", "", INDEX(AJ:AJ, _xlpm.matchRow)), _xlpm.adjustment, IF(_xlpm.matchRow="", "", IF(_xlpm.category="weak", 2, IF(_xlpm.category="moderate", 4, IF(_xlpm.category="strong", 8, IF(_xlpm.category="legendary", _xlpm.difference + 12, IF(_xlpm.category="warp", _xlpm.difference + 12, 0)))))), _xlpm.result, IF(_xlpm.matchRow="", "", IF(_xlpm.category="legendary", _xlpm.adjustment, _xlpm.difference + _xlpm.adjustment)), _xlpm.result ),IF(ISBLANK(Y64),"","Hidden"))} -> 9 | AA64: Pidgey | AC64: Quick Attack | AD64: =_xlfn.XLOOKUP(AC64,moves!A:A,moves!B:B) -> normal | AE64: =_xlfn.XLOOKUP(AC64,moves!A:A,moves!D:D) -> 2 | AF64: =_xlfn.XLOOKUP(AC64,moves!A:A,moves!E:E) | AG64: 0 | AH64: 0 | AI64: =IF(ISNUMBER(SEARCH("Shiny ", AA64)), 1, 0) -> 0 | AJ64: weak | AL64: 0 | AM64: {=IF(AL64=1,1, IF(ISTEXT(AK64),1, IF(AO64>1,AM63, IF(AI64=1, IF(SUMPRODUCT((LEN($Y$2:$Y$4096)-LEN(SUBSTITUTE($Y$2:$Y$4096,AA64,"")))/LEN(AA64))>0,2,1), IF( SUMPRODUCT((LEN($Y$2:$Y$4096)-LEN(SUBSTITUTE($Y$2:$Y$4096,AA64,"")))/LEN(AA64)) - SUMPRODUCT((LEN($Y$2:$Y$4096)-LEN(SUBSTITUTE($Y$2:$Y$4096,"Alolan "&AA64,"")))/LEN("Alolan "&AA64)) - SUMPRODUCT((LEN($Y$2:$Y$4096)-LEN(SUBSTITUTE($Y$2:$Y$4096,"Galarian "&AA64,"")))/LEN("Galarian "&AA64)) - SUMPRODUCT((LEN($Y$2:$Y$4096)-LEN(SUBSTITUTE($Y$2:$Y$4096,"Hisuian "&AA64,"")))/LEN("Hisuian "&AA64)) - SUMPRODUCT((LEN($Y$2:$Y$4096)-LEN(SUBSTITUTE($Y$2:$Y$4096,"Paldean "&AA64,"")))/LEN("Paldean "&AA64)) >0,2,1) ))))} -> 1 | AN64: 0 | AO64: 0
A65: 16 | B65: Pidgey | C65: Normal | D65: Flying | E65: 40 | F65: 45 | G65: 40 | H65: 35 | I65: 35 | J65: 56 | K65: Tiny Bird Pokémon | L65: Forest | M65: Temperate | N65: 4.84 | O65: 3.85 | R65: =MROUND(N65,1)+P65 -> 5 | S65: =MROUND(O65,1)+Q65 -> 4 | T65: =SUM(S65,R65) -> 9 | U65: Normal | V65: Flying | W65: Steel | X65: Bug | Y65: Pidgeotto | Z65: {=IF(ISBLANK(AK65),_xlfn.LET( _xlpm.nameBeforeSlash, IF(ISNUMBER(SEARCH("/", Y65)), LEFT(Y65, SEARCH("/", Y65)-1), Y65), _xlpm.matchRow, IFERROR(MATCH(_xlpm.nameBeforeSlash, AA:AA, 0), ""), _xlpm.difference, IF(_xlpm.matchRow="", "", ABS((R65 + S65) - (INDEX(R:R, _xlpm.matchRow) + INDEX(S:S, _xlpm.matchRow)))), _xlpm.category, IF(_xlpm.matchRow="", "", INDEX(AJ:AJ, _xlpm.matchRow)), _xlpm.adjustment, IF(_xlpm.matchRow="", "", IF(_xlpm.category="weak", 2, IF(_xlpm.category="moderate", 4, IF(_xlpm.category="strong", 8, IF(_xlpm.category="legendary", _xlpm.difference + 12, IF(_xlpm.category="warp", _xlpm.difference + 12, 0)))))), _xlpm.result, IF(_xlpm.matchRow="", "", IF(_xlpm.category="legendary", _xlpm.adjustment, _xlpm.difference + _xlpm.adjustment)), _xlpm.result ),IF(ISBLANK(Y65),"","Hidden"))} -> 9 | AA65: Pidgey | AC65: Quick Attack | AD65: =_xlfn.XLOOKUP(AC65,moves!A:A,moves!B:B) -> normal | AE65: =_xlfn.XLOOKUP(AC65,moves!A:A,moves!D:D) -> 2 | AF65: =_xlfn.XLOOKUP(AC65,moves!A:A,moves!E:E) | AG65: 0 | AH65: 0 | AI65: =IF(ISNUMBER(SEARCH("Shiny ", AA65)), 1, 0) -> 0 | AJ65: weak | AL65: 0 | AM65: {=IF(AL65=1,1, IF(ISTEXT(AK65),1, IF(AO65>1,AM64, IF(AI65=1, IF(SUMPRODUCT((LEN($Y$2:$Y$4096)-LEN(SUBSTITUTE($Y$2:$Y$4096,AA65,"")))/LEN(AA65))>0,2,1), IF( SUMPRODUCT((LEN($Y$2:$Y$4096)-LEN(SUBSTITUTE($Y$2:$Y$4096,AA65,"")))/LEN(AA65)) - SUMPRODUCT((LEN($Y$2:$Y$4096)-LEN(SUBSTITUTE($Y$2:$Y$4096,"Alolan "&AA65,"")))/LEN("Alolan "&AA65)) - SUMPRODUCT((LEN($Y$2:$Y$4096)-LEN(SUBSTITUTE($Y$2:$Y$4096,"Galarian "&AA65,"")))/LEN("Galarian "&AA65)) - SUMPRODUCT((LEN($Y$2:$Y$4096)-LEN(SUBSTITUTE($Y$2:$Y$4096,"Hisuian "&AA65,"")))/LEN("Hisuian "&AA65)) - SUMPRODUCT((LEN($Y$2:$Y$4096)-LEN(SUBSTITUTE($Y$2:$Y$4096,"Paldean "&AA65,"")))/LEN("Paldean "&AA65)) >0,2,1) ))))} -> 1 | AN65: 0 | AO65: 0
A66: 16 | B66: Pidgey | C66: Normal | D66: Flying | E66: 40 | F66: 45 | G66: 40 | H66: 35 | I66: 35 | J66: 56 | K66: Tiny Bird Pokémon | L66: Forest | M66: Temperate | N66: 4.84 | O66: 3.85 | R66: =MROUND(N66,1)+P66 -> 5 | S66: =MROUND(O66,1)+Q66 -> 4 | T66: =SUM(S66,R66) -> 9 | U66: Normal | V66: Flying | W66: Steel | X66: Bug | Y66: Pidgeotto | Z66: {=IF(ISBLANK(AK66),_xlfn.LET( _xlpm.nameBeforeSlash, IF(ISNUMBER(SEARCH("/", Y66)), LEFT(Y66, SEARCH("/", Y66)-1), Y66), _xlpm.matchRow, IFERROR(MATCH(_xlpm.nameBeforeSlash, AA:AA, 0), ""), _xlpm.difference, IF(_xlpm.matchRow="", "", ABS((R66 + S66) - (INDEX(R:R, _xlpm.matchRow) + INDEX(S:S, _xlpm.matchRow)))), _xlpm.category, IF(_xlpm.matchRow="", "", INDEX(AJ:AJ, _xlpm.matchRow)), _xlpm.adjustment, IF(_xlpm.matchRow="", "", IF(_xlpm.category="weak", 2, IF(_xlpm.category="moderate", 4, IF(_xlpm.category="strong", 8, IF(_xlpm.category="legendary", _xlpm.difference + 12, IF(_xlpm.category="warp", _xlpm.difference + 12, 0)))))), _xlpm.result, IF(_xlpm.matchRow="", "", IF(_xlpm.category="legendary", _xlpm.adjustment, _xlpm.difference + _xlpm.adjustment)), _xlpm.result ),IF(ISBLANK(Y66),"","Hidden"))} -> 9 | AA66: Pidgey | AC66: Quick Attack | AD66: =_xlfn.XLOOKUP(AC66,moves!A:A,moves!B:B) -> normal | AE66: =_xlfn.XLOOKUP(AC66,moves!A:A,moves!D:D) -> 2 | AF66: =_xlfn.XLOOKUP(AC66,moves!A:A,moves!E:E) | AG66: 0 | AH66: 0 | AI66: =IF(ISNUMBER(SEARCH("Shiny ", AA66)), 1, 0) -> 0 | AJ66: weak | AL66: 0 | AM66: {=IF(AL66=1,1, IF(ISTEXT(AK66),1, IF(AO66>1,AM65, IF(AI66=1, IF(SUMPRODUCT((LEN($Y$2:$Y$4096)-LEN(SUBSTITUTE($Y$2:$Y$4096,AA66,"")))/LEN(AA66))>0,2,1), IF( SUMPRODUCT((LEN($Y$2:$Y$4096)-LEN(SUBSTITUTE($Y$2:$Y$4096,AA66,"")))/LEN(AA66)) - SUMPRODUCT((LEN($Y$2:$Y$4096)-LEN(SUBSTITUTE($Y$2:$Y$4096,"Alolan "&AA66,"")))/LEN("Alolan "&AA66)) - SUMPRODUCT((LEN($Y$2:$Y$4096)-LEN(SUBSTITUTE($Y$2:$Y$4096,"Galarian "&AA66,"")))/LEN("Galarian "&AA66)) - SUMPRODUCT((LEN($Y$2:$Y$4096)-LEN(SUBSTITUTE($Y$2:$Y$4096,"Hisuian "&AA66,"")))/LEN("Hisuian "&AA66)) - SUMPRODUCT((LEN($Y$2:$Y$4096)-LEN(SUBSTITUTE($Y$2:$Y$4096,"Paldean "&AA66,"")))/LEN("Paldean "&AA66)) >0,2,1) ))))} -> 1 | AN66: 0 | AO66: 0
A67: 16 | B67: Pidgey | C67: Normal | D67: Flying | E67: 40 | F67: 45 | G67: 40 | H67: 35 | I67: 35 | J67: 56 | K67: Tiny Bird Pokémon | L67: Forest | M67: Temperate | N67: 4.84 | O67: 3.85 | R67: =MROUND(N67,1)+P67 -> 5 | S67: =MROUND(O67,1)+Q67 -> 4 | T67: =SUM(S67,R67) -> 9 | U67: Normal | V67: Flying | W67: Steel | X67: Bug | Y67: Pidgeotto | Z67: {=IF(ISBLANK(AK67),_xlfn.LET( _xlpm.nameBeforeSlash, IF(ISNUMBER(SEARCH("/", Y67)), LEFT(Y67, SEARCH("/", Y67)-1), Y67), _xlpm.matchRow, IFERROR(MATCH(_xlpm.nameBeforeSlash, AA:AA, 0), ""), _xlpm.difference, IF(_xlpm.matchRow="", "", ABS((R67 + S67) - (INDEX(R:R, _xlpm.matchRow) + INDEX(S:S, _xlpm.matchRow)))), _xlpm.category, IF(_xlpm.matchRow="", "", INDEX(AJ:AJ, _xlpm.matchRow)), _xlpm.adjustment, IF(_xlpm.matchRow="", "", IF(_xlpm.category="weak", 2, IF(_xlpm.category="moderate", 4, IF(_xlpm.category="strong", 8, IF(_xlpm.category="legendary", _xlpm.difference + 12, IF(_xlpm.category="warp", _xlpm.difference + 12, 0)))))), _xlpm.result, IF(_xlpm.matchRow="", "", IF(_xlpm.category="legendary", _xlpm.adjustment, _xlpm.difference + _xlpm.adjustment)), _xlpm.result ),IF(ISBLANK(Y67),"","Hidden"))} -> 9 | AA67: Pidgey | AC67: Quick Attack | AD67: =_xlfn.XLOOKUP(AC67,moves!A:A,moves!B:B) -> normal | AE67: =_xlfn.XLOOKUP(AC67,moves!A:A,moves!D:D) -> 2 | AF67: =_xlfn.XLOOKUP(AC67,moves!A:A,moves!E:E) | AG67: 0 | AH67: 0 | AI67: =IF(ISNUMBER(SEARCH("Shiny ", AA67)), 1, 0) -> 0 | AJ67: weak | AL67: 0 | AM67: {=IF(AL67=1,1, IF(ISTEXT(AK67),1, IF(AO67>1,AM66, IF(AI67=1, IF(SUMPRODUCT((LEN($Y$2:$Y$4096)-LEN(SUBSTITUTE($Y$2:$Y$4096,AA67,"")))/LEN(AA67))>0,2,1), IF( SUMPRODUCT((LEN($Y$2:$Y$4096)-LEN(SUBSTITUTE($Y$2:$Y$4096,AA67,"")))/LEN(AA67)) - SUMPRODUCT((LEN($Y$2:$Y$4096)-LEN(SUBSTITUTE($Y$2:$Y$4096,"Alolan "&AA67,"")))/LEN("Alolan "&AA67)) - SUMPRODUCT((LEN($Y$2:$Y$4096)-LEN(SUBSTITUTE($Y$2:$Y$4096,"Galarian "&AA67,"")))/LEN("Galarian "&AA67)) - SUMPRODUCT((LEN($Y$2:$Y$4096)-LEN(SUBSTITUTE($Y$2:$Y$4096,"Hisuian "&AA67,"")))/LEN("Hisuian "&AA67)) - SUMPRODUCT((LEN($Y$2:$Y$4096)-LEN(SUBSTITUTE($Y$2:$Y$4096,"Paldean "&AA67,"")))/LEN("Paldean "&AA67)) >0,2,1) ))))} -> 1 | AN67: 0 | AO67: 0
A68: 16 | B68: Pidgey | C68: Normal | D68: Flying | E68: 40 | F68: 45 | G68: 40 | H68: 35 | I68: 35 | J68: 56 | K68: Tiny Bird Pokémon | L68: Forest | M68: Temperate | N68: 4.84 | O68: 3.85 | R68: =MROUND(N68,1)+P68 -> 5 | S68: =MROUND(O68,1)+Q68 -> 4 | T68: =SUM(S68,R68) -> 9 | U68: Normal | V68: Flying | W68: Steel | X68: Bug | Y68: Pidgeotto | Z68: {=IF(ISBLANK(AK68),_xlfn.LET( _xlpm.nameBeforeSlash, IF(ISNUMBER(SEARCH("/", Y68)), LEFT(Y68, SEARCH("/", Y68)-1), Y68), _xlpm.matchRow, IFERROR(MATCH(_xlpm.nameBeforeSlash, AA:AA, 0), ""), _xlpm.difference, IF(_xlpm.matchRow="", "", ABS((R68 + S68) - (INDEX(R:R, _xlpm.matchRow) + INDEX(S:S, _xlpm.matchRow)))), _xlpm.category, IF(_xlpm.matchRow="", "", INDEX(AJ:AJ, _xlpm.matchRow)), _xlpm.adjustment, IF(_xlpm.matchRow="", "", IF(_xlpm.category="weak", 2, IF(_xlpm.category="moderate", 4, IF(_xlpm.category="strong", 8, IF(_xlpm.category="legendary", _xlpm.difference + 12, IF(_xlpm.category="warp", _xlpm.difference + 12, 0)))))), _xlpm.result, IF(_xlpm.matchRow="", "", IF(_xlpm.category="legendary", _xlpm.adjustment, _xlpm.difference + _xlpm.adjustment)), _xlpm.result ),IF(ISBLANK(Y68),"","Hidden"))} -> 9 | AA68: Pidgey | AC68: Quick Attack | AD68: =_xlfn.XLOOKUP(AC68,moves!A:A,moves!B:B) -> normal | AE68: =_xlfn.XLOOKUP(AC68,moves!A:A,moves!D:D) -> 2 | AF68: =_xlfn.XLOOKUP(AC68,moves!A:A,moves!E:E) | AG68: 0 | AH68: 0 | AI68: =IF(ISNUMBER(SEARCH("Shiny ", AA68)), 1, 0) -> 0 | AJ68: weak | AL68: 0 | AM68: {=IF(AL68=1,1, IF(ISTEXT(AK68),1, IF(AO68>1,AM67, IF(AI68=1, IF(SUMPRODUCT((LEN($Y$2:$Y$4096)-LEN(SUBSTITUTE($Y$2:$Y$4096,AA68,"")))/LEN(AA68))>0,2,1), IF( SUMPRODUCT((LEN($Y$2:$Y$4096)-LEN(SUBSTITUTE($Y$2:$Y$4096,AA68,"")))/LEN(AA68)) - SUMPRODUCT((LEN($Y$2:$Y$4096)-LEN(SUBSTITUTE($Y$2:$Y$4096,"Alolan "&AA68,"")))/LEN("Alolan "&AA68)) - SUMPRODUCT((LEN($Y$2:$Y$4096)-LEN(SUBSTITUTE($Y$2:$Y$4096,"Galarian "&AA68,"")))/LEN("Galarian "&AA68)) - SUMPRODUCT((LEN($Y$2:$Y$4096)-LEN(SUBSTITUTE($Y$2:$Y$4096,"Hisuian "&AA68,"")))/LEN("Hisuian "&AA68)) - SUMPRODUCT((LEN($Y$2:$Y$4096)-LEN(SUBSTITUTE($Y$2:$Y$4096,"Paldean "&AA68,"")))/LEN("Paldean "&AA68)) >0,2,1) ))))} -> 1 | AN68: 0 | AO68: 0
A69: 16 | B69: Pidgey | C69: Normal | D69: Flying | E69: 40 | F69: 45 | G69: 40 | H69: 35 | I69: 35 | J69: 56 | K69: Tiny Bird Pokémon | L69: Forest | M69: Temperate | N69: 4.84 | O69: 3.85 | R69: =MROUND(N69,1)+P69 -> 5 | S69: =MROUND(O69,1)+Q69 -> 4 | T69: =SUM(S69,R69) -> 9 | U69: Normal | V69: Flying | W69: Steel | X69: Bug | Y69: Pidgeotto | Z69: {=IF(ISBLANK(AK69),_xlfn.LET( _xlpm.nameBeforeSlash, IF(ISNUMBER(SEARCH("/", Y69)), LEFT(Y69, SEARCH("/", Y69)-1), Y69), _xlpm.matchRow, IFERROR(MATCH(_xlpm.nameBeforeSlash, AA:AA, 0), ""), _xlpm.difference, IF(_xlpm.matchRow="", "", ABS((R69 + S69) - (INDEX(R:R, _xlpm.matchRow) + INDEX(S:S, _xlpm.matchRow)))), _xlpm.category, IF(_xlpm.matchRow="", "", INDEX(AJ:AJ, _xlpm.matchRow)), _xlpm.adjustment, IF(_xlpm.matchRow="", "", IF(_xlpm.category="weak", 2, IF(_xlpm.category="moderate", 4, IF(_xlpm.category="strong", 8, IF(_xlpm.category="legendary", _xlpm.difference + 12, IF(_xlpm.category="warp", _xlpm.difference + 12, 0)))))), _xlpm.result, IF(_xlpm.matchRow="", "", IF(_xlpm.category="legendary", _xlpm.adjustment, _xlpm.difference + _xlpm.adjustment)), _xlpm.result ),IF(ISBLANK(Y69),"","Hidden"))} -> 9 | AA69: Pidgey | AC69: Quick Attack | AD69: =_xlfn.XLOOKUP(AC69,moves!A:A,moves!B:B) -> normal | AE69: =_xlfn.XLOOKUP(AC69,moves!A:A,moves!D:D) -> 2 | AF69: =_xlfn.XLOOKUP(AC69,moves!A:A,moves!E:E) | AG69: 0 | AH69: 0 | AI69: =IF(ISNUMBER(SEARCH("Shiny ", AA69)), 1, 0) -> 0 | AJ69: weak | AL69: 0 | AM69: {=IF(AL69=1,1, IF(ISTEXT(AK69),1, IF(AO69>1,AM68, IF(AI69=1, IF(SUMPRODUCT((LEN($Y$2:$Y$4096)-LEN(SUBSTITUTE($Y$2:$Y$4096,AA69,"")))/LEN(AA69))>0,2,1), IF( SUMPRODUCT((LEN($Y$2:$Y$4096)-LEN(SUBSTITUTE($Y$2:$Y$4096,AA69,"")))/LEN(AA69)) - SUMPRODUCT((LEN($Y$2:$Y$4096)-LEN(SUBSTITUTE($Y$2:$Y$4096,"Alolan "&AA69,"")))/LEN("Alolan "&AA69)) - SUMPRODUCT((LEN($Y$2:$Y$4096)-LEN(SUBSTITUTE($Y$2:$Y$4096,"Galarian "&AA69,"")))/LEN("Galarian "&AA69)) - SUMPRODUCT((LEN($Y$2:$Y$4096)-LEN(SUBSTITUTE($Y$2:$Y$4096,"Hisuian "&AA69,"")))/LEN("Hisuian "&AA69)) - SUMPRODUCT((LEN($Y$2:$Y$4096)-LEN(SUBSTITUTE($Y$2:$Y$4096,"Paldean "&AA69,"")))/LEN("Paldean "&AA69)) >0,2,1) ))))} -> 1 | AN69: 0 | AO69: 0
A70: 16 | B70: Pidgey | C70: Normal | D70: Flying | E70: 40 | F70: 45 | G70: 40 | H70: 35 | I70: 35 | J70: 56 | K70: Tiny Bird Pokémon | L70: Forest | M70: Temperate | N70: 4.84 | O70: 3.85 | R70: =MROUND(N70,1)+P70 -> 5 | S70: =MROUND(O70,1)+Q70 -> 4 | T70: =SUM(S70,R70) -> 9 | U70: Normal | V70: Flying | W70: Steel | X70: Bug | Y70: Pidgeotto | Z70: {=IF(ISBLANK(AK70),_xlfn.LET( _xlpm.nameBeforeSlash, IF(ISNUMBER(SEARCH("/", Y70)), LEFT(Y70, SEARCH("/", Y70)-1), Y70), _xlpm.matchRow, IFERROR(MATCH(_xlpm.nameBeforeSlash, AA:AA, 0), ""), _xlpm.difference, IF(_xlpm.matchRow="", "", ABS((R70 + S70) - (INDEX(R:R, _xlpm.matchRow) + INDEX(S:S, _xlpm.matchRow)))), _xlpm.category, IF(_xlpm.matchRow="", "", INDEX(AJ:AJ, _xlpm.matchRow)), _xlpm.adjustment, IF(_xlpm.matchRow="", "", IF(_xlpm.category="weak", 2, IF(_xlpm.category="moderate", 4, IF(_xlpm.category="strong", 8, IF(_xlpm.category="legendary", _xlpm.difference + 12, IF(_xlpm.category="warp", _xlpm.difference + 12, 0)))))), _xlpm.result, IF(_xlpm.matchRow="", "", IF(_xlpm.category="legendary", _xlpm.adjustment, _xlpm.difference + _xlpm.adjustment)), _xlpm.result ),IF(ISBLANK(Y70),"","Hidden"))} -> 9 | AA70: Pidgey | AC70: Quick Attack | AD70: =_xlfn.XLOOKUP(AC70,moves!A:A,moves!B:B) -> normal | AE70: =_xlfn.XLOOKUP(AC70,moves!A:A,moves!D:D) -> 2 | AF70: =_xlfn.XLOOKUP(AC70,moves!A:A,moves!E:E) | AG70: 0 | AH70: 0 | AI70: =IF(ISNUMBER(SEARCH("Shiny ", AA70)), 1, 0) -> 0 | AJ70: weak | AL70: 0 | AM70: {=IF(AL70=1,1, IF(ISTEXT(AK70),1, IF(AO70>1,AM69, IF(AI70=1, IF(SUMPRODUCT((LEN($Y$2:$Y$4096)-LEN(SUBSTITUTE($Y$2:$Y$4096,AA70,"")))/LEN(AA70))>0,2,1), IF( SUMPRODUCT((LEN($Y$2:$Y$4096)-LEN(SUBSTITUTE($Y$2:$Y$4096,AA70,"")))/LEN(AA70)) - SUMPRODUCT((LEN($Y$2:$Y$4096)-LEN(SUBSTITUTE($Y$2:$Y$4096,"Alolan "&AA70,"")))/LEN("Alolan "&AA70)) - SUMPRODUCT((LEN($Y$2:$Y$4096)-LEN(SUBSTITUTE($Y$2:$Y$4096,"Galarian "&AA70,"")))/LEN("Galarian "&AA70)) - SUMPRODUCT((LEN($Y$2:$Y$4096)-LEN(SUBSTITUTE($Y$2:$Y$4096,"Hisuian "&AA70,"")))/LEN("Hisuian "&AA70)) - SUMPRODUCT((LEN($Y$2:$Y$4096)-LEN(SUBSTITUTE($Y$2:$Y$4096,"Paldean "&AA70,"")))/LEN("Paldean "&AA70)) >0,2,1) ))))} -> 1 | AN70: 0 | AO70: 0
A71: 16-shiny | B71: Pidgey | C71: Normal | D71: Flying | E71: 40 | F71: 45 | G71: 40 | H71: 35 | I71: 35 | J71: 56 | K71: Tiny Bird Pokémon | L71: Forest | M71: Temperate | N71: 4.84 | O71: 3.85 | R71: =MROUND(N71,1)+P71 -> 5 | S71: =MROUND(O71,1)+Q71 -> 4 | T71: =SUM(S71,R71) -> 9 | U71: Normal | V71: Flying | W71: Steel | X71: Bug | Y71: Shiny Pidgeotto | Z71: {=IF(ISBLANK(AK71),_xlfn.LET( _xlpm.nameBeforeSlash, IF(ISNUMBER(SEARCH("/", Y71)), LEFT(Y71, SEARCH("/", Y71)-1), Y71), _xlpm.matchRow, IFERROR(MATCH(_xlpm.nameBeforeSlash, AA:AA, 0), ""), _xlpm.difference, IF(_xlpm.matchRow="", "", ABS((R71 + S71) - (INDEX(R:R, _xlpm.matchRow) + INDEX(S:S, _xlpm.matchRow)))), _xlpm.category, IF(_xlpm.matchRow="", "", INDEX(AJ:AJ, _xlpm.matchRow)), _xlpm.adjustment, IF(_xlpm.matchRow="", "", IF(_xlpm.category="weak", 2, IF(_xlpm.category="moderate", 4, IF(_xlpm.category="strong", 8, IF(_xlpm.category="legendary", _xlpm.difference + 12, IF(_xlpm.category="warp", _xlpm.difference + 12, 0)))))), _xlpm.result, IF(_xlpm.matchRow="", "", IF(_xlpm.category="legendary", _xlpm.adjustment, _xlpm.difference + _xlpm.adjustment)), _xlpm.result ),IF(ISBLANK(Y71),"","Hidden"))} -> 9 | AA71: Shiny Pidgey | AC71: Gust | AD71: =_xlfn.XLOOKUP(AC71,moves!A:A,moves!B:B) -> flying | AE71: =_xlfn.XLOOKUP(AC71,moves!A:A,moves!D:D) -> 2 | AF71: =_xlfn.XLOOKUP(AC71,moves!A:A,moves!E:E) -> When the user is next attacked: Remove 1 critical hit from the roll. | AG71: 1 | AH71: 0 | AI71: =IF(ISNUMBER(SEARCH("Shiny ", AA71)), 1, 0) -> 1 | AJ71: weak | AL71: 0 | AM71: {=IF(AL71=1,1, IF(ISTEXT(AK71),1, IF(AO71>1,AM70, IF(AI71=1, IF(SUMPRODUCT((LEN($Y$2:$Y$4096)-LEN(SUBSTITUTE($Y$2:$Y$4096,AA71,"")))/LEN(AA71))>0,2,1), IF( SUMPRODUCT((LEN($Y$2:$Y$4096)-LEN(SUBSTITUTE($Y$2:$Y$4096,AA71,"")))/LEN(AA71)) - SUMPRODUCT((LEN($Y$2:$Y$4096)-LEN(SUBSTITUTE($Y$2:$Y$4096,"Alolan "&AA71,"")))/LEN("Alolan "&AA71)) - SUMPRODUCT((LEN($Y$2:$Y$4096)-LEN(SUBSTITUTE($Y$2:$Y$4096,"Galarian "&AA71,"")))/LEN("Galarian "&AA71)) - SUMPRODUCT((LEN($Y$2:$Y$4096)-LEN(SUBSTITUTE($Y$2:$Y$4096,"Hisuian "&AA71,"")))/LEN("Hisuian "&AA71)) - SUMPRODUCT((LEN($Y$2:$Y$4096)-LEN(SUBSTITUTE($Y$2:$Y$4096,"Paldean "&AA71,"")))/LEN("Paldean "&AA71)) >0,2,1) ))))} -> 1 | AN71: 0 | AO71: 0
A72: 17 | B72: Pidgeotto | C72: Normal | D72: Flying | E72: 63 | F72: 60 | G72: 55 | H72: 50 | I72: 50 | J72: 71 | K72: Bird Pokémon | L72: Forest | M72: Temperate | N72: 6.34 | O72: 5.67 | P72: 1 | Q72: 1 | R72: =MROUND(N72,1)+P72 -> 7 | S72: =MROUND(O72,1)+Q72 -> 7 | T72: =SUM(S72,R72) -> 14 | U72: Normal | V72: Flying | W72: Steel | X72: Bug | Y72: Pidgeot | Z72: {=IF(ISBLANK(AK72),_xlfn.LET( _xlpm.nameBeforeSlash, IF(ISNUMBER(SEARCH("/", Y72)), LEFT(Y72, SEARCH("/", Y72)-1), Y72), _xlpm.matchRow, IFERROR(MATCH(_xlpm.nameBeforeSlash, AA:AA, 0), ""), _xlpm.difference, IF(_xlpm.matchRow="", "", ABS((R72 + S72) - (INDEX(R:R, _xlpm.matchRow) + INDEX(S:S, _xlpm.matchRow)))), _xlpm.category, IF(_xlpm.matchRow="", "", INDEX(AJ:AJ, _xlpm.matchRow)), _xlpm.adjustment, IF(_xlpm.matchRow="", "", IF(_xlpm.category="weak", 2, IF(_xlpm.category="moderate", 4, IF(_xlpm.category="strong", 8, IF(_xlpm.category="legendary", _xlpm.difference + 12, IF(_xlpm.category="warp", _xlpm.difference + 12, 0)))))), _xlpm.result, IF(_xlpm.matchRow="", "", IF(_xlpm.category="legendary", _xlpm.adjustment, _xlpm.difference + _xlpm.adjustment)), _xlpm.result ),IF(ISBLANK(Y72),"","Hidden"))} -> 13 | AA72: Pidgeotto | AC72: Wing Attack | AD72: =_xlfn.XLOOKUP(AC72,moves!A:A,moves!B:B) -> flying | AE72: =_xlfn.XLOOKUP(AC72,moves!A:A,moves!D:D) -> 3 | AF72: =_xlfn.XLOOKUP(AC72,moves!A:A,moves!E:E) -> When the target next attacks: Remove 1 regular hit from the roll. | AG72: 0 | AH72: 0 | AI72: =IF(ISNUMBER(SEARCH("Shiny ", AA72)), 1, 0) -> 0 | AJ72: moderate | AL72: 0 | AM72: {=IF(AL72=1,1, IF(ISTEXT(AK72),1, IF(AO72>1,AM71, IF(AI72=1, IF(SUMPRODUCT((LEN($Y$2:$Y$4096)-LEN(SUBSTITUTE($Y$2:$Y$4096,AA72,"")))/LEN(AA72))>0,2,1), IF( SUMPRODUCT((LEN($Y$2:$Y$4096)-LEN(SUBSTITUTE($Y$2:$Y$4096,AA72,"")))/LEN(AA72)) - SUMPRODUCT((LEN($Y$2:$Y$4096)-LEN(SUBSTITUTE($Y$2:$Y$4096,"Alolan "&AA72,"")))/LEN("Alolan "&AA72)) - SUMPRODUCT((LEN($Y$2:$Y$4096)-LEN(SUBSTITUTE($Y$2:$Y$4096,"Galarian "&AA72,"")))/LEN("Galarian "&AA72)) - SUMPRODUCT((LEN($Y$2:$Y$4096)-LEN(SUBSTITUTE($Y$2:$Y$4096,"Hisuian "&AA72,"")))/LEN("Hisuian "&AA72)) - SUMPRODUCT((LEN($Y$2:$Y$4096)-LEN(SUBSTITUTE($Y$2:$Y$4096,"Paldean "&AA72,"")))/LEN("Paldean "&AA72)) >0,2,1) ))))} -> 2 | AN72: 0 | AO72: 0
A73: 17-shiny | B73: Pidgeotto | C73: Normal | D73: Flying | E73: 63 | F73: 60 | G73: 55 | H73: 50 | I73: 50 | J73: 71 | K73: Bird Pokémon | L73: Forest | M73: Temperate | N73: 6.34 | O73: 5.67 | P73: 1 | Q73: 1 | R73: =MROUND(N73,1)+P73 -> 7 | S73: =MROUND(O73,1)+Q73 -> 7 | T73: =SUM(S73,R73) -> 14 | U73: Normal | V73: Flying | W73: Steel | X73: Bug | Y73: Shiny Pidgeot | Z73: {=IF(ISBLANK(AK73),_xlfn.LET( _xlpm.nameBeforeSlash, IF(ISNUMBER(SEARCH("/", Y73)), LEFT(Y73, SEARCH("/", Y73)-1), Y73), _xlpm.matchRow, IFERROR(MATCH(_xlpm.nameBeforeSlash, AA:AA, 0), ""), _xlpm.difference, IF(_xlpm.matchRow="", "", ABS((R73 + S73) - (INDEX(R:R, _xlpm.matchRow) + INDEX(S:S, _xlpm.matchRow)))), _xlpm.category, IF(_xlpm.matchRow="", "", INDEX(AJ:AJ, _xlpm.matchRow)), _xlpm.adjustment, IF(_xlpm.matchRow="", "", IF(_xlpm.category="weak", 2, IF(_xlpm.category="moderate", 4, IF(_xlpm.category="strong", 8, IF(_xlpm.category="legendary", _xlpm.difference + 12, IF(_xlpm.category="warp", _xlpm.difference + 12, 0)))))), _xlpm.result, IF(_xlpm.matchRow="", "", IF(_xlpm.category="legendary", _xlpm.adjustment, _xlpm.difference + _xlpm.adjustment)), _xlpm.result ),IF(ISBLANK(Y73),"","Hidden"))} -> 13 | AA73: Shiny Pidgeotto | AC73: Roost | AD73: =_xlfn.XLOOKUP(AC73,moves!A:A,moves!B:B) -> flying | AE73: =_xlfn.XLOOKUP(AC73,moves!A:A,moves!D:D) -> 0 | AF73: =_xlfn.XLOOKUP(AC73,moves!A:A,moves!E:E) -> Heal 4. The user loses its Flying typing. | AG73: 0 | AH73: 0 | AI73: =IF(ISNUMBER(SEARCH("Shiny ", AA73)), 1, 0) -> 1 | AJ73: moderate | AL73: 0 | AM73: {=IF(AL73=1,1, IF(ISTEXT(AK73),1, IF(AO73>1,AM72, IF(AI73=1, IF(SUMPRODUCT((LEN($Y$2:$Y$4096)-LEN(SUBSTITUTE($Y$2:$Y$4096,AA73,"")))/LEN(AA73))>0,2,1), IF( SUMPRODUCT((LEN($Y$2:$Y$4096)-LEN(SUBSTITUTE($Y$2:$Y$4096,AA73,"")))/LEN(AA73)) - SUMPRODUCT((LEN($Y$2:$Y$4096)-LEN(SUBSTITUTE($Y$2:$Y$4096,"Alolan "&AA73,"")))/LEN("Alolan "&AA73)) - SUMPRODUCT((LEN($Y$2:$Y$4096)-LEN(SUBSTITUTE($Y$2:$Y$4096,"Galarian "&AA73,"")))/LEN("Galarian "&AA73)) - SUMPRODUCT((LEN($Y$2:$Y$4096)-LEN(SUBSTITUTE($Y$2:$Y$4096,"Hisuian "&AA73,"")))/LEN("Hisuian "&AA73)) - SUMPRODUCT((LEN($Y$2:$Y$4096)-LEN(SUBSTITUTE($Y$2:$Y$4096,"Paldean "&AA73,"")))/LEN("Paldean "&AA73)) >0,2,1) ))))} -> 2 | AN73: 0 | AO73: 0
A74: 18 | B74: Pidgeot | C74: Normal | D74: Flying | E74: 83 | F74: 80 | G74: 75 | H74: 70 | I74: 70 | J74: 91 | K74: Bird Pokémon | L74: Forest | M74: Temperate | N74: 8.34 | O74: 7.67 | P74: 2 | Q74: 1 | R74: =MROUND(N74,1)+P74 -> 10 | S74: =MROUND(O74,1)+Q74 -> 9 | T74: =SUM(S74,R74) -> 19 | U74: Normal | V74: Flying | W74: Steel | X74: Bug | Z74: {=IF(ISBLANK(AK74),_xlfn.LET( _xlpm.nameBeforeSlash, IF(ISNUMBER(SEARCH("/", Y74)), LEFT(Y74, SEARCH("/", Y74)-1), Y74), _xlpm.matchRow, IFERROR(MATCH(_xlpm.nameBeforeSlash, AA:AA, 0), ""), _xlpm.difference, IF(_xlpm.matchRow="", "", ABS((R74 + S74) - (INDEX(R:R, _xlpm.matchRow) + INDEX(S:S, _xlpm.matchRow)))), _xlpm.category, IF(_xlpm.matchRow="", "", INDEX(AJ:AJ, _xlpm.matchRow)), _xlpm.adjustment, IF(_xlpm.matchRow="", "", IF(_xlpm.category="weak", 2, IF(_xlpm.category="moderate", 4, IF(_xlpm.category="strong", 8, IF(_xlpm.category="legendary", _xlpm.difference + 12, IF(_xlpm.category="warp", _xlpm.difference + 12, 0)))))), _xlpm.result, IF(_xlpm.matchRow="", "", IF(_xlpm.category="legendary", _xlpm.adjustment, _xlpm.difference + _xlpm.adjustment)), _xlpm.result ),IF(ISBLANK(Y74),"","Hidden"))} | AA74: Pidgeot | AC74: Facade | AD74: =_xlfn.XLOOKUP(AC74,moves!A:A,moves!B:B) -> normal | AE74: =_xlfn.XLOOKUP(AC74,moves!A:A,moves!D:D) -> 4 | AF74: =_xlfn.XLOOKUP(AC74,moves!A:A,moves!E:E) -> If the user has any status conditions: Deal double damage. | AG74: 0 | AH74: 0 | AI74: =IF(ISNUMBER(SEARCH("Shiny ", AA74)), 1, 0) -> 0 | AJ74: strong | AL74: 0 | AM74: {=IF(AL74=1,1, IF(ISTEXT(AK74),1, IF(AO74>1,AM73, IF(AI74=1, IF(SUMPRODUCT((LEN($Y$2:$Y$4096)-LEN(SUBSTITUTE($Y$2:$Y$4096,AA74,"")))/LEN(AA74))>0,2,1), IF( SUMPRODUCT((LEN($Y$2:$Y$4096)-LEN(SUBSTITUTE($Y$2:$Y$4096,AA74,"")))/LEN(AA74)) - SUMPRODUCT((LEN($Y$2:$Y$4096)-LEN(SUBSTITUTE($Y$2:$Y$4096,"Alolan "&AA74,"")))/LEN("Alolan "&AA74)) - SUMPRODUCT((LEN($Y$2:$Y$4096)-LEN(SUBSTITUTE($Y$2:$Y$4096,"Galarian "&AA74,"")))/LEN("Galarian "&AA74)) - SUMPRODUCT((LEN($Y$2:$Y$4096)-LEN(SUBSTITUTE($Y$2:$Y$4096,"Hisuian "&AA74,"")))/LEN("Hisuian "&AA74)) - SUMPRODUCT((LEN($Y$2:$Y$4096)-LEN(SUBSTITUTE($Y$2:$Y$4096,"Paldean "&AA74,"")))/LEN("Paldean "&AA74)) >0,2,1) ))))} -> 2 | AN74: 0 | AO74: 1
A75: 18-m | B75: Pidgeot | C75: Normal | D75: Flying | E75: 83 | F75: 80 | G75: 80 | H75: 135 | I75: 80 | J75: 121 | K75: Bird Pokémon | L75: blank | M75: Mega | N75: 12.39 | O75: 8.12 | P75: 2 | Q75: 1 | R75: =MROUND(N75,1)+P75 -> 14 | S75: =MROUND(O75,1)+Q75 -> 9 | T75: =SUM(S75,R75) -> 23 | U75: Normal | V75: Flying | W75: Steel | X75: Bug | Z75: {=IF(ISBLANK(AK75),_xlfn.LET( _xlpm.nameBeforeSlash, IF(ISNUMBER(SEARCH("/", Y75)), LEFT(Y75, SEARCH("/", Y75)-1), Y75), _xlpm.matchRow, IFERROR(MATCH(_xlpm.nameBeforeSlash, AA:AA, 0), ""), _xlpm.difference, IF(_xlpm.matchRow="", "", ABS((R75 + S75) - (INDEX(R:R, _xlpm.matchRow) + INDEX(S:S, _xlpm.matchRow)))), _xlpm.category, IF(_xlpm.matchRow="", "", INDEX(AJ:AJ, _xlpm.matchRow)), _xlpm.adjustment, IF(_xlpm.matchRow="", "", IF(_xlpm.category="weak", 2, IF(_xlpm.category="moderate", 4, IF(_xlpm.category="strong", 8, IF(_xlpm.category="legendary", _xlpm.difference + 12, IF(_xlpm.category="warp", _xlpm.difference + 12, 0)))))), _xlpm.result, IF(_xlpm.matchRow="", "", IF(_xlpm.category="legendary", _xlpm.adjustment, _xlpm.difference + _xlpm.adjustment)), _xlpm.result ),IF(ISBLANK(Y75),"","Hidden"))} | AA75: Mega Pidgeot | AB75: Mega Form | AC75: Hurricane | AD75: =_xlfn.XLOOKUP(AC75,moves!A:A,moves!B:B) -> flying | AE75: =_xlfn.XLOOKUP(AC75,moves!A:A,moves!D:D) -> 5 | AF75: =_xlfn.XLOOKUP(AC75,moves!A:A,moves!E:E) -> Critical hits deal +1 damage. If the weather condition is not Rain or Strong Winds: Status symbols deal -2 damage | AG75: 0 | AH75: 0 | AI75: =IF(ISNUMBER(SEARCH("Shiny ", AA75)), 1, 0) -> 0 | AJ75: strong | AL75: 0 | AM75: {=IF(AL75=1,1, IF(ISTEXT(AK75),1, IF(AO75>1,AM74, IF(AI75=1, IF(SUMPRODUCT((LEN($Y$2:$Y$4096)-LEN(SUBSTITUTE($Y$2:$Y$4096,AA75,"")))/LEN(AA75))>0,2,1), IF( SUMPRODUCT((LEN($Y$2:$Y$4096)-LEN(SUBSTITUTE($Y$2:$Y$4096,AA75,"")))/LEN(AA75)) - SUMPRODUCT((LEN($Y$2:$Y$4096)-LEN(SUBSTITUTE($Y$2:$Y$4096,"Alolan "&AA75,"")))/LEN("Alolan "&AA75)) - SUMPRODUCT((LEN($Y$2:$Y$4096)-LEN(SUBSTITUTE($Y$2:$Y$4096,"Galarian "&AA75,"")))/LEN("Galarian "&AA75)) - SUMPRODUCT((LEN($Y$2:$Y$4096)-LEN(SUBSTITUTE($Y$2:$Y$4096,"Hisuian "&AA75,"")))/LEN("Hisuian "&AA75)) - SUMPRODUCT((LEN($Y$2:$Y$4096)-LEN(SUBSTITUTE($Y$2:$Y$4096,"Paldean "&AA75,"")))/LEN("Paldean "&AA75)) >0,2,1) ))))} -> 2 | AN75: 0 | AO75: 2
A76: 18-shiny | B76: Pidgeot | C76: Normal | D76: Flying | E76: 83 | F76: 80 | G76: 75 | H76: 70 | I76: 70 | J76: 91 | K76: Bird Pokémon | L76: Forest | M76: Temperate | N76: 8.34 | O76: 7.67 | P76: 2 | Q76: 1 | R76: =MROUND(N76,1)+P76 -> 10 | S76: =MROUND(O76,1)+Q76 -> 9 | T76: =SUM(S76,R76) -> 19 | U76: Normal | V76: Flying | W76: Steel | X76: Bug | Z76: {=IF(ISBLANK(AK76),_xlfn.LET( _xlpm.nameBeforeSlash, IF(ISNUMBER(SEARCH("/", Y76)), LEFT(Y76, SEARCH("/", Y76)-1), Y76), _xlpm.matchRow, IFERROR(MATCH(_xlpm.nameBeforeSlash, AA:AA, 0), ""), _xlpm.difference, IF(_xlpm.matchRow="", "", ABS((R76 + S76) - (INDEX(R:R, _xlpm.matchRow) + INDEX(S:S, _xlpm.matchRow)))), _xlpm.category, IF(_xlpm.matchRow="", "", INDEX(AJ:AJ, _xlpm.matchRow)), _xlpm.adjustment, IF(_xlpm.matchRow="", "", IF(_xlpm.category="weak", 2, IF(_xlpm.category="moderate", 4, IF(_xlpm.category="strong", 8, IF(_xlpm.category="legendary", _xlpm.difference + 12, IF(_xlpm.category="warp", _xlpm.difference + 12, 0)))))), _xlpm.result, IF(_xlpm.matchRow="", "", IF(_xlpm.category="legendary", _xlpm.adjustment, _xlpm.difference + _xlpm.adjustment)), _xlpm.result ),IF(ISBLANK(Y76),"","Hidden"))} | AA76: Shiny Pidgeot | AC76: Fly | AD76: =_xlfn.XLOOKUP(AC76,moves!A:A,moves!B:B) -> flying | AE76: =_xlfn.XLOOKUP(AC76,moves!A:A,moves!D:D) -> 4 | AF76: =_xlfn.XLOOKUP(AC76,moves!A:A,moves!E:E) | AG76: 0 | AH76: 0 | AI76: =IF(ISNUMBER(SEARCH("Shiny ", AA76)), 1, 0) -> 1 | AJ76: strong | AL76: 0 | AM76: {=IF(AL76=1,1, IF(ISTEXT(AK76),1, IF(AO76>1,AM75, IF(AI76=1, IF(SUMPRODUCT((LEN($Y$2:$Y$4096)-LEN(SUBSTITUTE($Y$2:$Y$4096,AA76,"")))/LEN(AA76))>0,2,1), IF( SUMPRODUCT((LEN($Y$2:$Y$4096)-LEN(SUBSTITUTE($Y$2:$Y$4096,AA76,"")))/LEN(AA76)) - SUMPRODUCT((LEN($Y$2:$Y$4096)-LEN(SUBSTITUTE($Y$2:$Y$4096,"Alolan "&AA76,"")))/LEN("Alolan "&AA76)) - SUMPRODUCT((LEN($Y$2:$Y$4096)-LEN(SUBSTITUTE($Y$2:$Y$4096,"Galarian "&AA76,"")))/LEN("Galarian "&AA76)) - SUMPRODUCT((LEN($Y$2:$Y$4096)-LEN(SUBSTITUTE($Y$2:$Y$4096,"Hisuian "&AA76,"")))/LEN("Hisuian "&AA76)) - SUMPRODUCT((LEN($Y$2:$Y$4096)-LEN(SUBSTITUTE($Y$2:$Y$4096,"Paldean "&AA76,"")))/LEN("Paldean "&AA76)) >0,2,1) ))))} -> 2 | AN76: 0 | AO76: 1
A77: 18-m-shiny | B77: Pidgeot | C77: Normal | D77: Flying | E77: 83 | F77: 80 | G77: 80 | H77: 135 | I77: 80 | J77: 121 | K77: Bird Pokémon | L77: blank | M77: Mega | N77: 12.39 | O77: 8.12 | P77: 2 | Q77: 1 | R77: =MROUND(N77,1)+P77 -> 14 | S77: =MROUND(O77,1)+Q77 -> 9 | T77: =SUM(S77,R77) -> 23 | U77: Normal | V77: Flying | W77: Steel | X77: Bug | Z77: {=IF(ISBLANK(AK77),_xlfn.LET( _xlpm.nameBeforeSlash, IF(ISNUMBER(SEARCH("/", Y77)), LEFT(Y77, SEARCH("/", Y77)-1), Y77), _xlpm.matchRow, IFERROR(MATCH(_xlpm.nameBeforeSlash, AA:AA, 0), ""), _xlpm.difference, IF(_xlpm.matchRow="", "", ABS((R77 + S77) - (INDEX(R:R, _xlpm.matchRow) + INDEX(S:S, _xlpm.matchRow)))), _xlpm.category, IF(_xlpm.matchRow="", "", INDEX(AJ:AJ, _xlpm.matchRow)), _xlpm.adjustment, IF(_xlpm.matchRow="", "", IF(_xlpm.category="weak", 2, IF(_xlpm.category="moderate", 4, IF(_xlpm.category="strong", 8, IF(_xlpm.category="legendary", _xlpm.difference + 12, IF(_xlpm.category="warp", _xlpm.difference + 12, 0)))))), _xlpm.result, IF(_xlpm.matchRow="", "", IF(_xlpm.category="legendary", _xlpm.adjustment, _xlpm.difference + _xlpm.adjustment)), _xlpm.result ),IF(ISBLANK(Y77),"","Hidden"))} | AA77: Shiny Mega Pidgeot | AB77: Mega Form | AC77: Mach Cyclone | AD77: =_xlfn.XLOOKUP(AC77,moves!A:A,moves!B:B) -> flying | AE77: =_xlfn.XLOOKUP(AC77,moves!A:A,moves!D:D) -> 4 | AF77: =_xlfn.XLOOKUP(AC77,moves!A:A,moves!E:E) -> You may force the target to switch out, if able. | AG77: 0 | AH77: 0 | AI77: =IF(ISNUMBER(SEARCH("Shiny ", AA77)), 1, 0) -> 1 | AJ77: strong | AL77: 0 | AM77: {=IF(AL77=1,1, IF(ISTEXT(AK77),1, IF(AO77>1,AM76, IF(AI77=1, IF(SUMPRODUCT((LEN($Y$2:$Y$4096)-LEN(SUBSTITUTE($Y$2:$Y$4096,AA77,"")))/LEN(AA77))>0,2,1), IF( SUMPRODUCT((LEN($Y$2:$Y$4096)-LEN(SUBSTITUTE($Y$2:$Y$4096,AA77,"")))/LEN(AA77)) - SUMPRODUCT((LEN($Y$2:$Y$4096)-LEN(SUBSTITUTE($Y$2:$Y$4096,"Alolan "&AA77,"")))/LEN("Alolan "&AA77)) - SUMPRODUCT((LEN($Y$2:$Y$4096)-LEN(SUBSTITUTE($Y$2:$Y$4096,"Galarian "&AA77,"")))/LEN("Galarian "&AA77)) - SUMPRODUCT((LEN($Y$2:$Y$4096)-LEN(SUBSTITUTE($Y$2:$Y$4096,"Hisuian "&AA77,"")))/LEN("Hisuian "&AA77)) - SUMPRODUCT((LEN($Y$2:$Y$4096)-LEN(SUBSTITUTE($Y$2:$Y$4096,"Paldean "&AA77,"")))/LEN("Paldean "&AA77)) >0,2,1) ))))} -> 2 | AN77: 0 | AO77: 2
A78: 19 | B78: Rattata | C78: Normal | E78: 30 | F78: 56 | G78: 35 | H78: 25 | I78: 35 | J78: 72 | K78: Mouse Pokémon | L78: Plains | M78: Temperate | N78: 5.93 | O78: 3.3 | R78: =MROUND(N78,1)+P78 -> 6 | S78: =MROUND(O78,1)+Q78 -> 3 | T78: =SUM(S78,R78) -> 9 | U78: Normal | V78: Dark | W78: Fighting | X78: Electric | Y78: Raticate | Z78: {=IF(ISBLANK(AK78),_xlfn.LET( _xlpm.nameBeforeSlash, IF(ISNUMBER(SEARCH("/", Y78)), LEFT(Y78, SEARCH("/", Y78)-1), Y78), _xlpm.matchRow, IFERROR(MATCH(_xlpm.nameBeforeSlash, AA:AA, 0), ""), _xlpm.difference, IF(_xlpm.matchRow="", "", ABS((R78 + S78) - (INDEX(R:R, _xlpm.matchRow) + INDEX(S:S, _xlpm.matchRow)))), _xlpm.category, IF(_xlpm.matchRow="", "", INDEX(AJ:AJ, _xlpm.matchRow)), _xlpm.adjustment, IF(_xlpm.matchRow="", "", IF(_xlpm.category="weak", 2, IF(_xlpm.category="moderate", 4, IF(_xlpm.category="strong", 8, IF(_xlpm.category="legendary", _xlpm.difference + 12, IF(_xlpm.category="warp", _xlpm.difference + 12, 0)))))), _xlpm.result, IF(_xlpm.matchRow="", "", IF(_xlpm.category="legendary", _xlpm.adjustment, _xlpm.difference + _xlpm.adjustment)), _xlpm.result ),IF(ISBLANK(Y78),"","Hidden"))} -> 10 | AA78: Rattata | AC78: Quick Attack | AD78: =_xlfn.XLOOKUP(AC78,moves!A:A,moves!B:B) -> normal | AE78: =_xlfn.XLOOKUP(AC78,moves!A:A,moves!D:D) -> 2 | AF78: =_xlfn.XLOOKUP(AC78,moves!A:A,moves!E:E) | AG78: 0 | AH78: 0 | AI78: =IF(ISNUMBER(SEARCH("Shiny ", AA78)), 1, 0) -> 0 | AJ78: weak | AL78: 0 | AM78: {=IF(AL78=1,1, IF(ISTEXT(AK78),1, IF(AO78>1,AM77, IF(AI78=1, IF(SUMPRODUCT((LEN($Y$2:$Y$4096)-LEN(SUBSTITUTE($Y$2:$Y$4096,AA78,"")))/LEN(AA78))>0,2,1), IF( SUMPRODUCT((LEN($Y$2:$Y$4096)-LEN(SUBSTITUTE($Y$2:$Y$4096,AA78,"")))/LEN(AA78)) - SUMPRODUCT((LEN($Y$2:$Y$4096)-LEN(SUBSTITUTE($Y$2:$Y$4096,"Alolan "&AA78,"")))/LEN("Alolan "&AA78)) - SUMPRODUCT((LEN($Y$2:$Y$4096)-LEN(SUBSTITUTE($Y$2:$Y$4096,"Galarian "&AA78,"")))/LEN("Galarian "&AA78)) - SUMPRODUCT((LEN($Y$2:$Y$4096)-LEN(SUBSTITUTE($Y$2:$Y$4096,"Hisuian "&AA78,"")))/LEN("Hisuian "&AA78)) - SUMPRODUCT((LEN($Y$2:$Y$4096)-LEN(SUBSTITUTE($Y$2:$Y$4096,"Paldean "&AA78,"")))/LEN("Paldean "&AA78)) >0,2,1) ))))} -> 1 | AN78: 0 | AO78: 0
A79: 19-a | B79: Rattata | C79: Dark | D79: Normal | E79: 30 | F79: 56 | G79: 35 | H79: 25 | I79: 35 | J79: 72 | K79: Mouse Pokémon | L79: Plains | M79: Temperate | N79: 5.93 | O79: 3.3 | R79: =MROUND(N79,1)+P79 -> 6 | S79: =MROUND(O79,1)+Q79 -> 3 | T79: =SUM(S79,R79) -> 9 | U79: Dark | V79: Normal | W79: Fighting | X79: Ghost | Y79: Alolan Raticate | Z79: {=IF(ISBLANK(AK79),_xlfn.LET( _xlpm.nameBeforeSlash, IF(ISNUMBER(SEARCH("/", Y79)), LEFT(Y79, SEARCH("/", Y79)-1), Y79), _xlpm.matchRow, IFERROR(MATCH(_xlpm.nameBeforeSlash, AA:AA, 0), ""), _xlpm.difference, IF(_xlpm.matchRow="", "", ABS((R79 + S79) - (INDEX(R:R, _xlpm.matchRow) + INDEX(S:S, _xlpm.matchRow)))), _xlpm.category, IF(_xlpm.matchRow="", "", INDEX(AJ:AJ, _xlpm.matchRow)), _xlpm.adjustment, IF(_xlpm.matchRow="", "", IF(_xlpm.category="weak", 2, IF(_xlpm.category="moderate", 4, IF(_xlpm.category="strong", 8, IF(_xlpm.category="legendary", _xlpm.difference + 12, IF(_xlpm.category="warp", _xlpm.difference + 12, 0)))))), _xlpm.result, IF(_xlpm.matchRow="", "", IF(_xlpm.category="legendary", _xlpm.adjustment, _xlpm.difference + _xlpm.adjustment)), _xlpm.result ),IF(ISBLANK(Y79),"","Hidden"))} -> 10 | AA79: Alolan Rattata | AB79: Alolan Form | AC79: Bite | AD79: =_xlfn.XLOOKUP(AC79,moves!A:A,moves!B:B) -> dark | AE79: =_xlfn.XLOOKUP(AC79,moves!A:A,moves!D:D) -> 3 | AF79: =_xlfn.XLOOKUP(AC79,moves!A:A,moves!E:E) -> When the target is next attacked: Add 1 regular hit to the roll. | AG79: 0 | AH79: 0 | AI79: =IF(ISNUMBER(SEARCH("Shiny ", AA79)), 1, 0) -> 0 | AJ79: weak | AL79: 0 | AM79: {=IF(AL79=1,1, IF(ISTEXT(AK79),1, IF(AO79>1,AM78, IF(AI79=1, IF(SUMPRODUCT((LEN($Y$2:$Y$4096)-LEN(SUBSTITUTE($Y$2:$Y$4096,AA79,"")))/LEN(AA79))>0,2,1), IF( SUMPRODUCT((LEN($Y$2:$Y$4096)-LEN(SUBSTITUTE($Y$2:$Y$4096,AA79,"")))/LEN(AA79)) - SUMPRODUCT((LEN($Y$2:$Y$4096)-LEN(SUBSTITUTE($Y$2:$Y$4096,"Alolan "&AA79,"")))/LEN("Alolan "&AA79)) - SUMPRODUCT((LEN($Y$2:$Y$4096)-LEN(SUBSTITUTE($Y$2:$Y$4096,"Galarian "&AA79,"")))/LEN("Galarian "&AA79)) - SUMPRODUCT((LEN($Y$2:$Y$4096)-LEN(SUBSTITUTE($Y$2:$Y$4096,"Hisuian "&AA79,"")))/LEN("Hisuian "&AA79)) - SUMPRODUCT((LEN($Y$2:$Y$4096)-LEN(SUBSTITUTE($Y$2:$Y$4096,"Paldean "&AA79,"")))/LEN("Paldean "&AA79)) >0,2,1) ))))} -> 1 | AN79: 0 | AO79: 0
A80: 19-shiny | B80: Rattata | C80: Normal | E80: 30 | F80: 56 | G80: 35 | H80: 25 | I80: 35 | J80: 72 | K80: Mouse Pokémon | L80: Plains | M80: Temperate | N80: 5.93 | O80: 3.3 | R80: =MROUND(N80,1)+P80 -> 6 | S80: =MROUND(O80,1)+Q80 -> 3 | T80: =SUM(S80,R80) -> 9 | U80: Normal | V80: Dark | W80: Fighting | X80: Electric | Y80: Shiny Raticate | Z80: {=IF(ISBLANK(AK80),_xlfn.LET( _xlpm.nameBeforeSlash, IF(ISNUMBER(SEARCH("/", Y80)), LEFT(Y80, SEARCH("/", Y80)-1), Y80), _xlpm.matchRow, IFERROR(MATCH(_xlpm.nameBeforeSlash, AA:AA, 0), ""), _xlpm.difference, IF(_xlpm.matchRow="", "", ABS((R80 + S80) - (INDEX(R:R, _xlpm.matchRow) + INDEX(S:S, _xlpm.matchRow)))), _xlpm.category, IF(_xlpm.matchRow="", "", INDEX(AJ:AJ, _xlpm.matchRow)), _xlpm.adjustment, IF(_xlpm.matchRow="", "", IF(_xlpm.category="weak", 2, IF(_xlpm.category="moderate", 4, IF(_xlpm.category="strong", 8, IF(_xlpm.category="legendary", _xlpm.difference + 12, IF(_xlpm.category="warp", _xlpm.difference + 12, 0)))))), _xlpm.result, IF(_xlpm.matchRow="", "", IF(_xlpm.category="legendary", _xlpm.adjustment, _xlpm.difference + _xlpm.adjustment)), _xlpm.result ),IF(ISBLANK(Y80),"","Hidden"))} -> 10 | AA80: Shiny Rattata | AC80: Bite | AD80: =_xlfn.XLOOKUP(AC80,moves!A:A,moves!B:B) -> dark | AE80: =_xlfn.XLOOKUP(AC80,moves!A:A,moves!D:D) -> 3 | AF80: =_xlfn.XLOOKUP(AC80,moves!A:A,moves!E:E) -> When the target is next attacked: Add 1 regular hit to the roll. | AG80: 0 | AH80: 0 | AI80: =IF(ISNUMBER(SEARCH("Shiny ", AA80)), 1, 0) -> 1 | AJ80: weak | AL80: 0 | AM80: {=IF(AL80=1,1, IF(ISTEXT(AK80),1, IF(AO80>1,AM79, IF(AI80=1, IF(SUMPRODUCT((LEN($Y$2:$Y$4096)-LEN(SUBSTITUTE($Y$2:$Y$4096,AA80,"")))/LEN(AA80))>0,2,1), IF( SUMPRODUCT((LEN($Y$2:$Y$4096)-LEN(SUBSTITUTE($Y$2:$Y$4096,AA80,"")))/LEN(AA80)) - SUMPRODUCT((LEN($Y$2:$Y$4096)-LEN(SUBSTITUTE($Y$2:$Y$4096,"Alolan "&AA80,"")))/LEN("Alolan "&AA80)) - SUMPRODUCT((LEN($Y$2:$Y$4096)-LEN(SUBSTITUTE($Y$2:$Y$4096,"Galarian "&AA80,"")))/LEN("Galarian "&AA80)) - SUMPRODUCT((LEN($Y$2:$Y$4096)-LEN(SUBSTITUTE($Y$2:$Y$4096,"Hisuian "&AA80,"")))/LEN("Hisuian "&AA80)) - SUMPRODUCT((LEN($Y$2:$Y$4096)-LEN(SUBSTITUTE($Y$2:$Y$4096,"Paldean "&AA80,"")))/LEN("Paldean "&AA80)) >0,2,1) ))))} -> 1 | AN80: 0 | AO80: 0
A81: 19-a-shiny | B81: Rattata | C81: Dark | D81: Normal | E81: 30 | F81: 56 | G81: 35 | H81: 25 | I81: 35 | J81: 72 | K81: Mouse Pokémon | L81: Plains | M81: Temperate | N81: 5.93 | O81: 3.3 | R81: =MROUND(N81,1)+P81 -> 6 | S81: =MROUND(O81,1)+Q81 -> 3 | T81: =SUM(S81,R81) -> 9 | U81: Dark | V81: Normal | W81: Fighting | X81: Ghost | Y81: Shiny Alolan Raticate | Z81: {=IF(ISBLANK(AK81),_xlfn.LET( _xlpm.nameBeforeSlash, IF(ISNUMBER(SEARCH("/", Y81)), LEFT(Y81, SEARCH("/", Y81)-1), Y81), _xlpm.matchRow, IFERROR(MATCH(_xlpm.nameBeforeSlash, AA:AA, 0), ""), _xlpm.difference, IF(_xlpm.matchRow="", "", ABS((R81 + S81) - (INDEX(R:R, _xlpm.matchRow) + INDEX(S:S, _xlpm.matchRow)))), _xlpm.category, IF(_xlpm.matchRow="", "", INDEX(AJ:AJ, _xlpm.matchRow)), _xlpm.adjustment, IF(_xlpm.matchRow="", "", IF(_xlpm.category="weak", 2, IF(_xlpm.category="moderate", 4, IF(_xlpm.category="strong", 8, IF(_xlpm.category="legendary", _xlpm.difference + 12, IF(_xlpm.category="warp", _xlpm.difference + 12, 0)))))), _xlpm.result, IF(_xlpm.matchRow="", "", IF(_xlpm.category="legendary", _xlpm.adjustment, _xlpm.difference + _xlpm.adjustment)), _xlpm.result ),IF(ISBLANK(Y81),"","Hidden"))} -> 10 | AA81: Shiny Alolan Rattata | AB81: Alolan Form | AC81: Quick Attack | AD81: =_xlfn.XLOOKUP(AC81,moves!A:A,moves!B:B) -> normal | AE81: =_xlfn.XLOOKUP(AC81,moves!A:A,moves!D:D) -> 2 | AF81: =_xlfn.XLOOKUP(AC81,moves!A:A,moves!E:E) | AG81: 0 | AH81: 0 | AI81: =IF(ISNUMBER(SEARCH("Shiny ", AA81)), 1, 0) -> 1 | AJ81: weak | AL81: 0 | AM81: {=IF(AL81=1,1, IF(ISTEXT(AK81),1, IF(AO81>1,AM80, IF(AI81=1, IF(SUMPRODUCT((LEN($Y$2:$Y$4096)-LEN(SUBSTITUTE($Y$2:$Y$4096,AA81,"")))/LEN(AA81))>0,2,1), IF( SUMPRODUCT((LEN($Y$2:$Y$4096)-LEN(SUBSTITUTE($Y$2:$Y$4096,AA81,"")))/LEN(AA81)) - SUMPRODUCT((LEN($Y$2:$Y$4096)-LEN(SUBSTITUTE($Y$2:$Y$4096,"Alolan "&AA81,"")))/LEN("Alolan "&AA81)) - SUMPRODUCT((LEN($Y$2:$Y$4096)-LEN(SUBSTITUTE($Y$2:$Y$4096,"Galarian "&AA81,"")))/LEN("Galarian "&AA81)) - SUMPRODUCT((LEN($Y$2:$Y$4096)-LEN(SUBSTITUTE($Y$2:$Y$4096,"Hisuian "&AA81,"")))/LEN("Hisuian "&AA81)) - SUMPRODUCT((LEN($Y$2:$Y$4096)-LEN(SUBSTITUTE($Y$2:$Y$4096,"Paldean "&AA81,"")))/LEN("Paldean "&AA81)) >0,2,1) ))))} -> 1 | AN81: 0 | AO81: 0
A82: 20 | B82: Raticate | C82: Normal | E82: 55 | F82: 81 | G82: 60 | H82: 50 | I82: 70 | J82: 97 | K82: Mouse Pokémon | L82: Plains | M82: Temperate | N82: 8.43 | O82: 6.1 | Q82: 1 | R82: =MROUND(N82,1)+P82 -> 8 | S82: =MROUND(O82,1)+Q82 -> 7 | T82: =SUM(S82,R82) -> 15 | U82: Normal | V82: Dark | W82: Fighting | X82: Electric | Z82: {=IF(ISBLANK(AK82),_xlfn.LET( _xlpm.nameBeforeSlash, IF(ISNUMBER(SEARCH("/", Y82)), LEFT(Y82, SEARCH("/", Y82)-1), Y82), _xlpm.matchRow, IFERROR(MATCH(_xlpm.nameBeforeSlash, AA:AA, 0), ""), _xlpm.difference, IF(_xlpm.matchRow="", "", ABS((R82 + S82) - (INDEX(R:R, _xlpm.matchRow) + INDEX(S:S, _xlpm.matchRow)))), _xlpm.category, IF(_xlpm.matchRow="", "", INDEX(AJ:AJ, _xlpm.matchRow)), _xlpm.adjustment, IF(_xlpm.matchRow="", "", IF(_xlpm.category="weak", 2, IF(_xlpm.category="moderate", 4, IF(_xlpm.category="strong", 8, IF(_xlpm.category="legendary", _xlpm.difference + 12, IF(_xlpm.category="warp", _xlpm.difference + 12, 0)))))), _xlpm.result, IF(_xlpm.matchRow="", "", IF(_xlpm.category="legendary", _xlpm.adjustment, _xlpm.difference + _xlpm.adjustment)), _xlpm.result ),IF(ISBLANK(Y82),"","Hidden"))} | AA82: Raticate | AC82: Super Fang | AD82: =_xlfn.XLOOKUP(AC82,moves!A:A,moves!B:B) -> normal | AE82: =_xlfn.XLOOKUP(AC82,moves!A:A,moves!D:D) -> 0 | AF82: =_xlfn.XLOOKUP(AC82,moves!A:A,moves!E:E) -> Set the target's HP equal to half the target's base health, rounded down. This cannot heal the target. | AG82: 0 | AH82: 0 | AI82: =IF(ISNUMBER(SEARCH("Shiny ", AA82)), 1, 0) -> 0 | AJ82: moderate | AL82: 0 | AM82: {=IF(AL82=1,1, IF(ISTEXT(AK82),1, IF(AO82>1,AM81, IF(AI82=1, IF(SUMPRODUCT((LEN($Y$2:$Y$4096)-LEN(SUBSTITUTE($Y$2:$Y$4096,AA82,"")))/LEN(AA82))>0,2,1), IF( SUMPRODUCT((LEN($Y$2:$Y$4096)-LEN(SUBSTITUTE($Y$2:$Y$4096,AA82,"")))/LEN(AA82)) - SUMPRODUCT((LEN($Y$2:$Y$4096)-LEN(SUBSTITUTE($Y$2:$Y$4096,"Alolan "&AA82,"")))/LEN("Alolan "&AA82)) - SUMPRODUCT((LEN($Y$2:$Y$4096)-LEN(SUBSTITUTE($Y$2:$Y$4096,"Galarian "&AA82,"")))/LEN("Galarian "&AA82)) - SUMPRODUCT((LEN($Y$2:$Y$4096)-LEN(SUBSTITUTE($Y$2:$Y$4096,"Hisuian "&AA82,"")))/LEN("Hisuian "&AA82)) - SUMPRODUCT((LEN($Y$2:$Y$4096)-LEN(SUBSTITUTE($Y$2:$Y$4096,"Paldean "&AA82,"")))/LEN("Paldean "&AA82)) >0,2,1) ))))} -> 2 | AN82: 0 | AO82: 0
A83: 20-a | B83: Raticate | C83: Dark | D83: Normal | E83: 75 | F83: 71 | G83: 70 | H83: 40 | I83: 80 | J83: 77 | K83: Mouse Pokémon | L83: Plains | M83: Temperate | N83: 7.03 | O83: 7.5 | R83: =MROUND(N83,1)+P83 -> 7 | S83: =MROUND(O83,1)+Q83 -> 8 | T83: =SUM(S83,R83) -> 15 | U83: Dark | V83: Normal | W83: Fighting | X83: Ghost | Z83: {=IF(ISBLANK(AK83),_xlfn.LET( _xlpm.nameBeforeSlash, IF(ISNUMBER(SEARCH("/", Y83)), LEFT(Y83, SEARCH("/", Y83)-1), Y83), _xlpm.matchRow, IFERROR(MATCH(_xlpm.nameBeforeSlash, AA:AA, 0), ""), _xlpm.difference, IF(_xlpm.matchRow="", "", ABS((R83 + S83) - (INDEX(R:R, _xlpm.matchRow) + INDEX(S:S, _xlpm.matchRow)))), _xlpm.category, IF(_xlpm.matchRow="", "", INDEX(AJ:AJ, _xlpm.matchRow)), _xlpm.adjustment, IF(_xlpm.matchRow="", "", IF(_xlpm.category="weak", 2, IF(_xlpm.category="moderate", 4, IF(_xlpm.category="strong", 8, IF(_xlpm.category="legendary", _xlpm.difference + 12, IF(_xlpm.category="warp", _xlpm.difference + 12, 0)))))), _xlpm.result, IF(_xlpm.matchRow="", "", IF(_xlpm.category="legendary", _xlpm.adjustment, _xlpm.difference + _xlpm.adjustment)), _xlpm.result ),IF(ISBLANK(Y83),"","Hidden"))} | AA83: Alolan Raticate | AB83: Alolan Form | AC83: Snicker Punch | AD83: =_xlfn.XLOOKUP(AC83,moves!A:A,moves!B:B) -> dark | AE83: =_xlfn.XLOOKUP(AC83,moves!A:A,moves!D:D) -> 3 | AF83: =_xlfn.XLOOKUP(AC83,moves!A:A,moves!E:E) | AG83: 0 | AH83: 0 | AI83: =IF(ISNUMBER(SEARCH("Shiny ", AA83)), 1, 0) -> 0 | AJ83: moderate | AL83: 0 | AM83: {=IF(AL83=1,1, IF(ISTEXT(AK83),1, IF(AO83>1,AM82, IF(AI83=1, IF(SUMPRODUCT((LEN($Y$2:$Y$4096)-LEN(SUBSTITUTE($Y$2:$Y$4096,AA83,"")))/LEN(AA83))>0,2,1), IF( SUMPRODUCT((LEN($Y$2:$Y$4096)-LEN(SUBSTITUTE($Y$2:$Y$4096,AA83,"")))/LEN(AA83)) - SUMPRODUCT((LEN($Y$2:$Y$4096)-LEN(SUBSTITUTE($Y$2:$Y$4096,"Alolan "&AA83,"")))/LEN("Alolan "&AA83)) - SUMPRODUCT((LEN($Y$2:$Y$4096)-LEN(SUBSTITUTE($Y$2:$Y$4096,"Galarian "&AA83,"")))/LEN("Galarian "&AA83)) - SUMPRODUCT((LEN($Y$2:$Y$4096)-LEN(SUBSTITUTE($Y$2:$Y$4096,"Hisuian "&AA83,"")))/LEN("Hisuian "&AA83)) - SUMPRODUCT((LEN($Y$2:$Y$4096)-LEN(SUBSTITUTE($Y$2:$Y$4096,"Paldean "&AA83,"")))/LEN("Paldean "&AA83)) >0,2,1) ))))} -> 2 | AN83: 0 | AO83: 0
A84: 20-shiny | B84: Raticate | C84: Normal | E84: 55 | F84: 81 | G84: 60 | H84: 50 | I84: 70 | J84: 97 | K84: Mouse Pokémon | L84: Plains | M84: Temperate | N84: 8.43 | O84: 6.1 | Q84: 1 | R84: =MROUND(N84,1)+P84 -> 8 | S84: =MROUND(O84,1)+Q84 -> 7 | T84: =SUM(S84,R84) -> 15 | U84: Normal | V84: Dark | W84: Fighting | X84: Electric | Z84: {=IF(ISBLANK(AK84),_xlfn.LET( _xlpm.nameBeforeSlash, IF(ISNUMBER(SEARCH("/", Y84)), LEFT(Y84, SEARCH("/", Y84)-1), Y84), _xlpm.matchRow, IFERROR(MATCH(_xlpm.nameBeforeSlash, AA:AA, 0), ""), _xlpm.difference, IF(_xlpm.matchRow="", "", ABS((R84 + S84) - (INDEX(R:R, _xlpm.matchRow) + INDEX(S:S, _xlpm.matchRow)))), _xlpm.category, IF(_xlpm.matchRow="", "", INDEX(AJ:AJ, _xlpm.matchRow)), _xlpm.adjustment, IF(_xlpm.matchRow="", "", IF(_xlpm.category="weak", 2, IF(_xlpm.category="moderate", 4, IF(_xlpm.category="strong", 8, IF(_xlpm.category="legendary", _xlpm.difference + 12, IF(_xlpm.category="warp", _xlpm.difference + 12, 0)))))), _xlpm.result, IF(_xlpm.matchRow="", "", IF(_xlpm.category="legendary", _xlpm.adjustment, _xlpm.difference + _xlpm.adjustment)), _xlpm.result ),IF(ISBLANK(Y84),"","Hidden"))} | AA84: Shiny Raticate | AC84: Hyper Fang | AD84: =_xlfn.XLOOKUP(AC84,moves!A:A,moves!B:B) -> normal | AE84: =_xlfn.XLOOKUP(AC84,moves!A:A,moves!D:D) -> 4 | AF84: =_xlfn.XLOOKUP(AC84,moves!A:A,moves!E:E) -> If you roll at least twice the number of critical hits than status symbols: The target skips their turn this round. | AG84: 0 | AH84: 0 | AI84: =IF(ISNUMBER(SEARCH("Shiny ", AA84)), 1, 0) -> 1 | AJ84: moderate | AL84: 0 | AM84: {=IF(AL84=1,1, IF(ISTEXT(AK84),1, IF(AO84>1,AM83, IF(AI84=1, IF(SUMPRODUCT((LEN($Y$2:$Y$4096)-LEN(SUBSTITUTE($Y$2:$Y$4096,AA84,"")))/LEN(AA84))>0,2,1), IF( SUMPRODUCT((LEN($Y$2:$Y$4096)-LEN(SUBSTITUTE($Y$2:$Y$4096,AA84,"")))/LEN(AA84)) - SUMPRODUCT((LEN($Y$2:$Y$4096)-LEN(SUBSTITUTE($Y$2:$Y$4096,"Alolan "&AA84,"")))/LEN("Alolan "&AA84)) - SUMPRODUCT((LEN($Y$2:$Y$4096)-LEN(SUBSTITUTE($Y$2:$Y$4096,"Galarian "&AA84,"")))/LEN("Galarian "&AA84)) - SUMPRODUCT((LEN($Y$2:$Y$4096)-LEN(SUBSTITUTE($Y$2:$Y$4096,"Hisuian "&AA84,"")))/LEN("Hisuian "&AA84)) - SUMPRODUCT((LEN($Y$2:$Y$4096)-LEN(SUBSTITUTE($Y$2:$Y$4096,"Paldean "&AA84,"")))/LEN("Paldean "&AA84)) >0,2,1) ))))} -> 2 | AN84: 0 | AO84: 0
A85: 20-a-shiny | B85: Raticate | C85: Dark | D85: Normal | E85: 75 | F85: 71 | G85: 70 | H85: 40 | I85: 80 | J85: 77 | K85: Mouse Pokémon | L85: Plains | M85: Temperate | N85: 7.03 | O85: 7.5 | R85: =MROUND(N85,1)+P85 -> 7 | S85: =MROUND(O85,1)+Q85 -> 8 | T85: =SUM(S85,R85) -> 15 | U85: Dark | V85: Normal | W85: Fighting | X85: Ghost | Z85: {=IF(ISBLANK(AK85),_xlfn.LET( _xlpm.nameBeforeSlash, IF(ISNUMBER(SEARCH("/", Y85)), LEFT(Y85, SEARCH("/", Y85)-1), Y85), _xlpm.matchRow, IFERROR(MATCH(_xlpm.nameBeforeSlash, AA:AA, 0), ""), _xlpm.difference, IF(_xlpm.matchRow="", "", ABS((R85 + S85) - (INDEX(R:R, _xlpm.matchRow) + INDEX(S:S, _xlpm.matchRow)))), _xlpm.category, IF(_xlpm.matchRow="", "", INDEX(AJ:AJ, _xlpm.matchRow)), _xlpm.adjustment, IF(_xlpm.matchRow="", "", IF(_xlpm.category="weak", 2, IF(_xlpm.category="moderate", 4, IF(_xlpm.category="strong", 8, IF(_xlpm.category="legendary", _xlpm.difference + 12, IF(_xlpm.category="warp", _xlpm.difference + 12, 0)))))), _xlpm.result, IF(_xlpm.matchRow="", "", IF(_xlpm.category="legendary", _xlpm.adjustment, _xlpm.difference + _xlpm.adjustment)), _xlpm.result ),IF(ISBLANK(Y85),"","Hidden"))} | AA85: Shiny Alolan Raticate | AB85: Alolan Form | AC85: Chase Up | AD85: =_xlfn.XLOOKUP(AC85,moves!A:A,moves!B:B) -> dark | AE85: =_xlfn.XLOOKUP(AC85,moves!A:A,moves!D:D) -> 0 | AF85: =_xlfn.XLOOKUP(AC85,moves!A:A,moves!E:E) -> You may shuffle the battle card discard pile and reveal the top 2 cards. Draw 1 of these cards. At the end of the battle, return the chosen battle card to the discard pile. | AG85: 0 | AH85: 0 | AI85: =IF(ISNUMBER(SEARCH("Shiny ", AA85)), 1, 0) -> 1 | AJ85: moderate | AL85: 0 | AM85: {=IF(AL85=1,1, IF(ISTEXT(AK85),1, IF(AO85>1,AM84, IF(AI85=1, IF(SUMPRODUCT((LEN($Y$2:$Y$4096)-LEN(SUBSTITUTE($Y$2:$Y$4096,AA85,"")))/LEN(AA85))>0,2,1), IF( SUMPRODUCT((LEN($Y$2:$Y$4096)-LEN(SUBSTITUTE($Y$2:$Y$4096,AA85,"")))/LEN(AA85)) - SUMPRODUCT((LEN($Y$2:$Y$4096)-LEN(SUBSTITUTE($Y$2:$Y$4096,"Alolan "&AA85,"")))/LEN("Alolan "&AA85)) - SUMPRODUCT((LEN($Y$2:$Y$4096)-LEN(SUBSTITUTE($Y$2:$Y$4096,"Galarian "&AA85,"")))/LEN("Galarian "&AA85)) - SUMPRODUCT((LEN($Y$2:$Y$4096)-LEN(SUBSTITUTE($Y$2:$Y$4096,"Hisuian "&AA85,"")))/LEN("Hisuian "&AA85)) - SUMPRODUCT((LEN($Y$2:$Y$4096)-LEN(SUBSTITUTE($Y$2:$Y$4096,"Paldean "&AA85,"")))/LEN("Paldean "&AA85)) >0,2,1) ))))} -> 2 | AN85: 0 | AO85: 0
A86: 21 | B86: Spearow | C86: Normal | D86: Flying | E86: 40 | F86: 60 | G86: 30 | H86: 31 | I86: 31 | J86: 70 | K86: Tiny Bird Pokémon | L86: Forest | M86: Temperate | N86: 6.11 | O86: 3.43 | R86: =MROUND(N86,1)+P86 -> 6 | S86: =MROUND(O86,1)+Q86 -> 3 | T86: =SUM(S86,R86) -> 9 | U86: Normal | V86: Flying | W86: Dark | X86: Ground | Y86: Fearow | Z86: {=IF(ISBLANK(AK86),_xlfn.LET( _xlpm.nameBeforeSlash, IF(ISNUMBER(SEARCH("/", Y86)), LEFT(Y86, SEARCH("/", Y86)-1), Y86), _xlpm.matchRow, IFERROR(MATCH(_xlpm.nameBeforeSlash, AA:AA, 0), ""), _xlpm.difference, IF(_xlpm.matchRow="", "", ABS((R86 + S86) - (INDEX(R:R, _xlpm.matchRow) + INDEX(S:S, _xlpm.matchRow)))), _xlpm.category, IF(_xlpm.matchRow="", "", INDEX(AJ:AJ, _xlpm.matchRow)), _xlpm.adjustment, IF(_xlpm.matchRow="", "", IF(_xlpm.category="weak", 2, IF(_xlpm.category="moderate", 4, IF(_xlpm.category="strong", 8, IF(_xlpm.category="legendary", _xlpm.difference + 12, IF(_xlpm.category="warp", _xlpm.difference + 12, 0)))))), _xlpm.result, IF(_xlpm.matchRow="", "", IF(_xlpm.category="legendary", _xlpm.adjustment, _xlpm.difference + _xlpm.adjustment)), _xlpm.result ),IF(ISBLANK(Y86),"","Hidden"))} -> 11 | AA86: Spearow | AC86: Peck | AD86: =_xlfn.XLOOKUP(AC86,moves!A:A,moves!B:B) -> flying | AE86: =_xlfn.XLOOKUP(AC86,moves!A:A,moves!D:D) -> 2 | AF86: =_xlfn.XLOOKUP(AC86,moves!A:A,moves!E:E) -> When the target is next attacked: Add 1 critical hit to the roll. | AG86: 0 | AH86: 0 | AI86: =IF(ISNUMBER(SEARCH("Shiny ", AA86)), 1, 0) -> 0 | AJ86: weak | AL86: 0 | AM86: {=IF(AL86=1,1, IF(ISTEXT(AK86),1, IF(AO86>1,AM85, IF(AI86=1, IF(SUMPRODUCT((LEN($Y$2:$Y$4096)-LEN(SUBSTITUTE($Y$2:$Y$4096,AA86,"")))/LEN(AA86))>0,2,1), IF( SUMPRODUCT((LEN($Y$2:$Y$4096)-LEN(SUBSTITUTE($Y$2:$Y$4096,AA86,"")))/LEN(AA86)) - SUMPRODUCT((LEN($Y$2:$Y$4096)-LEN(SUBSTITUTE($Y$2:$Y$4096,"Alolan "&AA86,"")))/LEN("Alolan "&AA86)) - SUMPRODUCT((LEN($Y$2:$Y$4096)-LEN(SUBSTITUTE($Y$2:$Y$4096,"Galarian "&AA86,"")))/LEN("Galarian "&AA86)) - SUMPRODUCT((LEN($Y$2:$Y$4096)-LEN(SUBSTITUTE($Y$2:$Y$4096,"Hisuian "&AA86,"")))/LEN("Hisuian "&AA86)) - SUMPRODUCT((LEN($Y$2:$Y$4096)-LEN(SUBSTITUTE($Y$2:$Y$4096,"Paldean "&AA86,"")))/LEN("Paldean "&AA86)) >0,2,1) ))))} -> 1 | AN86: 0 | AO86: 0
A87: 21-shiny | B87: Spearow | C87: Normal | D87: Flying | E87: 40 | F87: 60 | G87: 30 | H87: 31 | I87: 31 | J87: 70 | K87: Tiny Bird Pokémon | L87: Forest | M87: Temperate | N87: 6.11 | O87: 3.43 | R87: =MROUND(N87,1)+P87 -> 6 | S87: =MROUND(O87,1)+Q87 -> 3 | T87: =SUM(S87,R87) -> 9 | U87: Normal | V87: Flying | W87: Dark | X87: Ground | Y87: Shiny Fearow | Z87: {=IF(ISBLANK(AK87),_xlfn.LET( _xlpm.nameBeforeSlash, IF(ISNUMBER(SEARCH("/", Y87)), LEFT(Y87, SEARCH("/", Y87)-1), Y87), _xlpm.matchRow, IFERROR(MATCH(_xlpm.nameBeforeSlash, AA:AA, 0), ""), _xlpm.difference, IF(_xlpm.matchRow="", "", ABS((R87 + S87) - (INDEX(R:R, _xlpm.matchRow) + INDEX(S:S, _xlpm.matchRow)))), _xlpm.category, IF(_xlpm.matchRow="", "", INDEX(AJ:AJ, _xlpm.matchRow)), _xlpm.adjustment, IF(_xlpm.matchRow="", "", IF(_xlpm.category="weak", 2, IF(_xlpm.category="moderate", 4, IF(_xlpm.category="strong", 8, IF(_xlpm.category="legendary", _xlpm.difference + 12, IF(_xlpm.category="warp", _xlpm.difference + 12, 0)))))), _xlpm.result, IF(_xlpm.matchRow="", "", IF(_xlpm.category="legendary", _xlpm.adjustment, _xlpm.difference + _xlpm.adjustment)), _xlpm.result ),IF(ISBLANK(Y87),"","Hidden"))} -> 11 | AA87: Shiny Spearow | AC87: Fury Attack | AD87: =_xlfn.XLOOKUP(AC87,moves!A:A,moves!B:B) -> normal | AE87: =_xlfn.XLOOKUP(AC87,moves!A:A,moves!D:D) -> 2 | AF87: =_xlfn.XLOOKUP(AC87,moves!A:A,moves!E:E) -> Status symbols and critical hits deal +1 damage. | AG87: 0 | AH87: 0 | AI87: =IF(ISNUMBER(SEARCH("Shiny ", AA87)), 1, 0) -> 1 | AJ87: weak | AL87: 0 | AM87: {=IF(AL87=1,1, IF(ISTEXT(AK87),1, IF(AO87>1,AM86, IF(AI87=1, IF(SUMPRODUCT((LEN($Y$2:$Y$4096)-LEN(SUBSTITUTE($Y$2:$Y$4096,AA87,"")))/LEN(AA87))>0,2,1), IF( SUMPRODUCT((LEN($Y$2:$Y$4096)-LEN(SUBSTITUTE($Y$2:$Y$4096,AA87,"")))/LEN(AA87)) - SUMPRODUCT((LEN($Y$2:$Y$4096)-LEN(SUBSTITUTE($Y$2:$Y$4096,"Alolan "&AA87,"")))/LEN("Alolan "&AA87)) - SUMPRODUCT((LEN($Y$2:$Y$4096)-LEN(SUBSTITUTE($Y$2:$Y$4096,"Galarian "&AA87,"")))/LEN("Galarian "&AA87)) - SUMPRODUCT((LEN($Y$2:$Y$4096)-LEN(SUBSTITUTE($Y$2:$Y$4096,"Hisuian "&AA87,"")))/LEN("Hisuian "&AA87)) - SUMPRODUCT((LEN($Y$2:$Y$4096)-LEN(SUBSTITUTE($Y$2:$Y$4096,"Paldean "&AA87,"")))/LEN("Paldean "&AA87)) >0,2,1) ))))} -> 1 | AN87: 0 | AO87: 0
A88: 22 | B88: Fearow | C88: Normal | D88: Flying | E88: 65 | F88: 90 | G88: 65 | H88: 61 | I88: 61 | J88: 100 | K88: Beak Pokémon | L88: Forest | M88: Temperate | N88: 9.11 | O88: 6.38 | Q88: 1 | R88: =MROUND(N88,1)+P88 -> 9 | S88: =MROUND(O88,1)+Q88 -> 7 | T88: =SUM(S88,R88) -> 16 | U88: Normal | V88: Flying | W88: Dark | X88: Ground | Z88: {=IF(ISBLANK(AK88),_xlfn.LET( _xlpm.nameBeforeSlash, IF(ISNUMBER(SEARCH("/", Y88)), LEFT(Y88, SEARCH("/", Y88)-1), Y88), _xlpm.matchRow, IFERROR(MATCH(_xlpm.nameBeforeSlash, AA:AA, 0), ""), _xlpm.difference, IF(_xlpm.matchRow="", "", ABS((R88 + S88) - (INDEX(R:R, _xlpm.matchRow) + INDEX(S:S, _xlpm.matchRow)))), _xlpm.category, IF(_xlpm.matchRow="", "", INDEX(AJ:AJ, _xlpm.matchRow)), _xlpm.adjustment, IF(_xlpm.matchRow="", "", IF(_xlpm.category="weak", 2, IF(_xlpm.category="moderate", 4, IF(_xlpm.category="strong", 8, IF(_xlpm.category="legendary", _xlpm.difference + 12, IF(_xlpm.category="warp", _xlpm.difference + 12, 0)))))), _xlpm.result, IF(_xlpm.matchRow="", "", IF(_xlpm.category="legendary", _xlpm.adjustment, _xlpm.difference + _xlpm.adjustment)), _xlpm.result ),IF(ISBLANK(Y88),"","Hidden"))} | AA88: Fearow | AC88: Drill Run | AD88: =_xlfn.XLOOKUP(AC88,moves!A:A,moves!B:B) -> ground | AE88: =_xlfn.XLOOKUP(AC88,moves!A:A,moves!D:D) -> 4 | AF88: =_xlfn.XLOOKUP(AC88,moves!A:A,moves!E:E) -> Critical hits deal +1 damage. | AG88: 0 | AH88: 0 | AI88: =IF(ISNUMBER(SEARCH("Shiny ", AA88)), 1, 0) -> 0 | AJ88: moderate | AL88: 0 | AM88: {=IF(AL88=1,1, IF(ISTEXT(AK88),1, IF(AO88>1,AM87, IF(AI88=1, IF(SUMPRODUCT((LEN($Y$2:$Y$4096)-LEN(SUBSTITUTE($Y$2:$Y$4096,AA88,"")))/LEN(AA88))>0,2,1), IF( SUMPRODUCT((LEN($Y$2:$Y$4096)-LEN(SUBSTITUTE($Y$2:$Y$4096,AA88,"")))/LEN(AA88)) - SUMPRODUCT((LEN($Y$2:$Y$4096)-LEN(SUBSTITUTE($Y$2:$Y$4096,"Alolan "&AA88,"")))/LEN("Alolan "&AA88)) - SUMPRODUCT((LEN($Y$2:$Y$4096)-LEN(SUBSTITUTE($Y$2:$Y$4096,"Galarian "&AA88,"")))/LEN("Galarian "&AA88)) - SUMPRODUCT((LEN($Y$2:$Y$4096)-LEN(SUBSTITUTE($Y$2:$Y$4096,"Hisuian "&AA88,"")))/LEN("Hisuian "&AA88)) - SUMPRODUCT((LEN($Y$2:$Y$4096)-LEN(SUBSTITUTE($Y$2:$Y$4096,"Paldean "&AA88,"")))/LEN("Paldean "&AA88)) >0,2,1) ))))} -> 2 | AN88: 0 | AO88: 0
A89: 22-shiny | B89: Fearow | C89: Normal | D89: Flying | E89: 65 | F89: 90 | G89: 65 | H89: 61 | I89: 61 | J89: 100 | K89: Beak Pokémon | L89: Forest | M89: Temperate | N89: 9.11 | O89: 6.38 | Q89: 1 | R89: =MROUND(N89,1)+P89 -> 9 | S89: =MROUND(O89,1)+Q89 -> 7 | T89: =SUM(S89,R89) -> 16 | U89: Normal | V89: Flying | W89: Dark | X89: Ground | Z89: {=IF(ISBLANK(AK89),_xlfn.LET( _xlpm.nameBeforeSlash, IF(ISNUMBER(SEARCH("/", Y89)), LEFT(Y89, SEARCH("/", Y89)-1), Y89), _xlpm.matchRow, IFERROR(MATCH(_xlpm.nameBeforeSlash, AA:AA, 0), ""), _xlpm.difference, IF(_xlpm.matchRow="", "", ABS((R89 + S89) - (INDEX(R:R, _xlpm.matchRow) + INDEX(S:S, _xlpm.matchRow)))), _xlpm.category, IF(_xlpm.matchRow="", "", INDEX(AJ:AJ, _xlpm.matchRow)), _xlpm.adjustment, IF(_xlpm.matchRow="", "", IF(_xlpm.category="weak", 2, IF(_xlpm.category="moderate", 4, IF(_xlpm.category="strong", 8, IF(_xlpm.category="legendary", _xlpm.difference + 12, IF(_xlpm.category="warp", _xlpm.difference + 12, 0)))))), _xlpm.result, IF(_xlpm.matchRow="", "", IF(_xlpm.category="legendary", _xlpm.adjustment, _xlpm.difference + _xlpm.adjustment)), _xlpm.result ),IF(ISBLANK(Y89),"","Hidden"))} | AA89: Shiny Fearow | AC89: Drill Peck | AD89: =_xlfn.XLOOKUP(AC89,moves!A:A,moves!B:B) -> flying | AE89: =_xlfn.XLOOKUP(AC89,moves!A:A,moves!D:D) -> 4 | AF89: =_xlfn.XLOOKUP(AC89,moves!A:A,moves!E:E) -> Critical hits deal +2 damage. Status symbols deal -1 damage. | AG89: 0 | AH89: 0 | AI89: =IF(ISNUMBER(SEARCH("Shiny ", AA89)), 1, 0) -> 1 | AJ89: moderate | AL89: 0 | AM89: {=IF(AL89=1,1, IF(ISTEXT(AK89),1, IF(AO89>1,AM88, IF(AI89=1, IF(SUMPRODUCT((LEN($Y$2:$Y$4096)-LEN(SUBSTITUTE($Y$2:$Y$4096,AA89,"")))/LEN(AA89))>0,2,1), IF( SUMPRODUCT((LEN($Y$2:$Y$4096)-LEN(SUBSTITUTE($Y$2:$Y$4096,AA89,"")))/LEN(AA89)) - SUMPRODUCT((LEN($Y$2:$Y$4096)-LEN(SUBSTITUTE($Y$2:$Y$4096,"Alolan "&AA89,"")))/LEN("Alolan "&AA89)) - SUMPRODUCT((LEN($Y$2:$Y$4096)-LEN(SUBSTITUTE($Y$2:$Y$4096,"Galarian "&AA89,"")))/LEN("Galarian "&AA89)) - SUMPRODUCT((LEN($Y$2:$Y$4096)-LEN(SUBSTITUTE($Y$2:$Y$4096,"Hisuian "&AA89,"")))/LEN("Hisuian "&AA89)) - SUMPRODUCT((LEN($Y$2:$Y$4096)-LEN(SUBSTITUTE($Y$2:$Y$4096,"Paldean "&AA89,"")))/LEN("Paldean "&AA89)) >0,2,1) ))))} -> 2 | AN89: 0 | AO89: 0
A90: 23 | B90: Ekans | C90: Poison | E90: 30 | F90: 60 | G90: 44 | H90: 40 | I90: 54 | J90: 55 | K90: Snake Pokémon | L90: Forest | M90: Temperate | N90: 5.6 | O90: 4.14 | R90: =MROUND(N90,1)+P90 -> 6 | S90: =MROUND(O90,1)+Q90 -> 4 | T90: =SUM(S90,R90) -> 10 | U90: Poison | V90: Dark | W90: Normal | X90: Psychic | Y90: Arbok | Z90: {=IF(ISBLANK(AK90),_xlfn.LET( _xlpm.nameBeforeSlash, IF(ISNUMBER(SEARCH("/", Y90)), LEFT(Y90, SEARCH("/", Y90)-1), Y90), _xlpm.matchRow, IFERROR(MATCH(_xlpm.nameBeforeSlash, AA:AA, 0), ""), _xlpm.difference, IF(_xlpm.matchRow="", "", ABS((R90 + S90) - (INDEX(R:R, _xlpm.matchRow) + INDEX(S:S, _xlpm.matchRow)))), _xlpm.category, IF(_xlpm.matchRow="", "", INDEX(AJ:AJ, _xlpm.matchRow)), _xlpm.adjustment, IF(_xlpm.matchRow="", "", IF(_xlpm.category="weak", 2, IF(_xlpm.category="moderate", 4, IF(_xlpm.category="strong", 8, IF(_xlpm.category="legendary", _xlpm.difference + 12, IF(_xlpm.category="warp", _xlpm.difference + 12, 0)))))), _xlpm.result, IF(_xlpm.matchRow="", "", IF(_xlpm.category="legendary", _xlpm.adjustment, _xlpm.difference + _xlpm.adjustment)), _xlpm.result ),IF(ISBLANK(Y90),"","Hidden"))} -> 15 | AA90: Ekans | AC90: Glare | AD90: =_xlfn.XLOOKUP(AC90,moves!A:A,moves!B:B) -> normal | AE90: =_xlfn.XLOOKUP(AC90,moves!A:A,moves!D:D) -> 1 | AF90: =_xlfn.XLOOKUP(AC90,moves!A:A,moves!E:E) -> Inflict the Paralyzed status on the target, ignoring type immunity. | AG90: 0 | AH90: 0 | AI90: =IF(ISNUMBER(SEARCH("Shiny ", AA90)), 1, 0) -> 0 | AJ90: weak | AL90: 0 | AM90: {=IF(AL90=1,1, IF(ISTEXT(AK90),1, IF(AO90>1,AM89, IF(AI90=1, IF(SUMPRODUCT((LEN($Y$2:$Y$4096)-LEN(SUBSTITUTE($Y$2:$Y$4096,AA90,"")))/LEN(AA90))>0,2,1), IF( SUMPRODUCT((LEN($Y$2:$Y$4096)-LEN(SUBSTITUTE($Y$2:$Y$4096,AA90,"")))/LEN(AA90)) - SUMPRODUCT((LEN($Y$2:$Y$4096)-LEN(SUBSTITUTE($Y$2:$Y$4096,"Alolan "&AA90,"")))/LEN("Alolan "&AA90)) - SUMPRODUCT((LEN($Y$2:$Y$4096)-LEN(SUBSTITUTE($Y$2:$Y$4096,"Galarian "&AA90,"")))/LEN("Galarian "&AA90)) - SUMPRODUCT((LEN($Y$2:$Y$4096)-LEN(SUBSTITUTE($Y$2:$Y$4096,"Hisuian "&AA90,"")))/LEN("Hisuian "&AA90)) - SUMPRODUCT((LEN($Y$2:$Y$4096)-LEN(SUBSTITUTE($Y$2:$Y$4096,"Paldean "&AA90,"")))/LEN("Paldean "&AA90)) >0,2,1) ))))} -> 1 | AN90: 0 | AO90: 0
